Workbook

Sheet Paramètres
A1: PARAMÈTRES — Prévisions élevage de silure
A2: Cellules en bleu sur fond jaune = valeurs à modifier par vous. Le reste se calcule automatiquement.
A4: VENTE
A5: Prix de vente moyen (FCFA / kg) | B5: 1900
A6: Poids moyen d'un poisson à la vente (kg) | B6: 0.4 | C6: Sortie à 400 g en moyenne (les plus gros jusqu'à 600 g).
A7: Part du stock vendue à la fin du 2e mois du cycle | B7: 0 | C7: Mettre 0 % pour vendre la totalité au 3e mois ; augmenter si vous commencez à écouler dès la fin du 2e mois.
A8: Part vendue au cours du 3e mois (jusqu'à sa fin) | B8: =1-B7 -> 1 | C8: Calculé : 100 % − part du 2e mois. Ex. : vague d'août → la totalité vendue en octobre.
A10: ALEVINS
A11: Marge de sécurité sur les alevins (% ajouté à la commande) | B11: 0.1 | C11: On commande 10% d'alevins en plus pour couvrir le taux de perte.
A12: Prix d'un alevin (FCFA) | B12: 70 | C12: Prix D'EXEMPLE — mettez votre prix réel.
A14: REMISES FOURNISSEURS (négociées selon la taille des commandes)
A15: Remise obtenue sur les aliments et les alevins, selon la taille de la vague :
A16: Palier 1 — vague à partir de (t) / remise | B16: 0 | C16: 0 | D16: Remises D'EXEMPLE, à ajuster selon vos négociations réelles. Les seuils doivent rester en ordre croissant.
A17: Palier 2 — vague à partir de (t) / remise | B17: 5 | C17: 0.02
A18: Palier 3 — vague à partir de (t) / remise | B18: 10 | C18: 0.04
A19: Palier 4 — vague à partir de (t) / remise | B19: 15 | C19: 0.06
A21: ALIMENTS
A22: Kg d'aliment par kg de poisson — info, découle du standard de sacs | B22: =Aliments!$D$11/1000 -> 1.14 | C22: Le standard de sacs par tonne, les marques, prix et répartition se règlent dans la feuille Aliments.
A24: LOGISTIQUE — transport au voyage
A25: Capacité d'un voyage — aliments (sacs) | B25: 60 | C25: Nombre de sacs transportés par rotation.
A26: Coût d'un voyage — aliments (FCFA) | B26: 15000 | C26: Carburant + chauffeur + manutention, aller-retour.
A27: Capacité d'un voyage — poissons (kg) | B27: 1500 | C27: Charge utile par livraison de poisson vivant/frais.
A28: Coût d'un voyage — poissons (FCFA) | B28: 25000 | C28: Transport isotherme / glace incluse le cas échéant.
A29: Capacité d'un voyage — alevins (nb) | B29: 20000 | C29: Alevins transportés par rotation depuis l'écloserie.
A30: Coût d'un voyage — alevins (FCFA) | B30: 30000 | C30: Trajet écloserie → ferme.
A32: AUTRES DÉPENSES
A33: Saisie dans la feuille Dépenses (charges d'exploitation et charges ponctuelles). Le total remonte automatiquement dans les Prévisions. | C33: La logistique, elle, se calcule toute seule à partir des tarifs au voyage ci-dessus.
A35: FINANCES
A36: Part du résultat mensuel mise en épargne | B36: 0.3
A37: Trésorerie de départ en août 2026 (FCFA) | B37: 0
A39: INDICATEURS (calculés automatiquement)
A40: Coût aliment par kg de poisson produit (FCFA, sans remise) | B40: =Aliments!$D$13 -> 1216
A41: Coût alevins par kg vendu (FCFA, sans remise) | B41: =IF(B6=0,0,B12*(1+B11)/B6) -> 192.5
A42: Coût de production hors autres dépenses (FCFA / kg, sans remise) | B42: =B40+B41 -> 1408.5
A43: Idem pour une vague de 15 t, remise incluse (FCFA / kg) | B43: =B42*(1-INDEX($C$16:$C$19,MATCH(15,$B$16:$B$19,1))) -> 1323.99
A44: Marge brute d'une vague de 15 t, remise incluse (FCFA) | B44: =15000*(B5-B43) -> 8640150 | C44: Hors « autres dépenses », qui sont saisies mois par mois dans les Prévisions.
A45: Poissons à vendre dans une vague de 15 tonnes (nb) | B45: =IF(B6=0,0,15000/B6) -> 37500
A46: Alevins à commander pour une vague de 15 tonnes (nb) | B46: =B45*(1+B11) -> 41250

Sheet Aliments
A1: ALIMENTS — granulométries, marques, prix et répartition sur le cycle
A2: Grossissement du 2 mm au 4 mm (sortie à 400 g). Colonne « Sacs par tonne » : votre STANDARD de consommation pour produire 1 tonne de poisson (ex. 8 sacs de 2 mm, 18 de 3 mm, 50 de 4 mm) — c'est lui qui calcule les sacs de chaque vague selon son tonnage. Colonnes F, G, H : répartition de CHAQUE granulé sur les mois du cycle (chaque ligne doit faire 100%). Marques, poids et prix D'EXEMPLE à remplacer par vos valeurs réelles.
A3: Granulométrie | B3: Marque | C3: Poids du sac (kg) | D3: Prix du sac (FCFA) | E3: Prix au kg (FCFA) | F3: % consommé au mois 1 du cycle | G3: % consommé au mois 2 | H3: % consommé au mois 3 | I3: Total (doit faire 100%) | J3: Sacs par tonne de poisson (STANDARD) | K3: Contrôle
A4: 2 mm | B4: Marque A | C4: 15 | D4: 18000 | E4: =IF(N(C4)=0,0,D4/C4) -> 1200 | F4: 0.8 | G4: 0.2 | I4: =SUM(F4:H4) -> 1 | J4: 8 | K4: =IF(N(J4)=0,"",IF(ABS(I4-1)<0.001,"OK","≠ 100%")) -> OK
A5: 3 mm | B5: Marque A | C5: 15 | D5: 16500 | E5: =IF(N(C5)=0,0,D5/C5) -> 1100 | F5: 0.2 | G5: 0.8 | I5: =SUM(F5:H5) -> 1 | J5: 18 | K5: =IF(N(J5)=0,"",IF(ABS(I5-1)<0.001,"OK","≠ 100%")) -> OK
A6: 4 mm | B6: Marque B | C6: 15 | D6: 15500 | E6: =IF(N(C6)=0,0,D6/C6) -> 1033.3333 | G6: 0.4 | H6: 0.6 | I6: =SUM(F6:H6) -> 1 | J6: 50 | K6: =IF(N(J6)=0,"",IF(ABS(I6-1)<0.001,"OK","≠ 100%")) -> OK
E7: =IF(N(C7)=0,0,D7/C7) -> 0 | I7: =SUM(F7:H7) -> 0 | K7: =IF(N(J7)=0,"",IF(ABS(I7-1)<0.001,"OK","≠ 100%"))
E8: =IF(N(C8)=0,0,D8/C8) -> 0 | I8: =SUM(F8:H8) -> 0 | K8: =IF(N(J8)=0,"",IF(ABS(I8-1)<0.001,"OK","≠ 100%"))
E9: =IF(N(C9)=0,0,D9/C9) -> 0 | I9: =SUM(F9:H9) -> 0 | K9: =IF(N(J9)=0,"",IF(ABS(I9-1)<0.001,"OK","≠ 100%"))
A11: Aliment total par tonne de poisson (kg) — info | D11: =SUMPRODUCT($J$4:$J$9,$C$4:$C$9) -> 1140
A12: Coût aliment par tonne de poisson (FCFA, prix catalogue) | D12: =SUMPRODUCT($J$4:$J$9,$D$4:$D$9) -> 1216000
A13: Coût aliment par kg de poisson (FCFA, prix catalogue) | D13: =D12/1000 -> 1216 | E13: À comparer à votre expérience — remplacez marques, poids et prix d'exemple par vos valeurs réelles.

Sheet Empoissonnement
A1: PLAN D'EMPOISSONNEMENT — une ligne par vague
A2: Colonnes en bleu à modifier : C (tonnage visé) et F (alevins achetés ? OUI/NON — NON = alevins issus de votre production locale, coût nul). Le plan démarre en août 2026 (V1) et se termine en février 2028 (V19) ; les ventes du dernier cycle vont jusqu'en avril 2028.
A3: Vague | B3: Mois d'empoissonnement | C3: Objectif de vente (t) | D3: Poissons à vendre (nb approx.) | E3: Alevins à commander (nb, marge de sécurité incluse) | F3: Alevins achetés ? (OUI/NON) | G3: Remise fournisseur (%) | H3: Coût alevins (FCFA) | I3: Coût aliments de la vague (FCFA) | J3: Coût total aliments + alevins (FCFA) | K3: Coût de production partiel (FCFA/kg — aliments + alevins seuls) | L3: Chiffre d'affaires attendu (FCFA) | M3: Marge brute attendue (FCFA) | N3: Dépenses affectées à la vague (FCFA) | O3: Quote-part charges générales (FCFA) | P3: Coût complet de la vague (FCFA) | Q3: COÛT DE PRODUCTION COMPLET (FCFA/kg) | R3: Marge nette attendue (FCFA)
A4: V1 | B4: 46235 | C4: 4 | D4: =IF(Paramètres!$B$6=0,0,ROUND(C4*1000/Paramètres!$B$6,0)) -> 10000 | E4: =ROUNDUP(D4*(1+Paramètres!$B$11),0) -> 11000 | F4: NON | G4: =INDEX(Paramètres!$C$16:$C$19,MATCH(C4,Paramètres!$B$16:$B$19,1)) -> 0 | H4: =IF($F4="NON",0,E4*Paramètres!$B$12*(1-G4)) -> 0 | I4: ='Aliment par vague'!$L4 -> 4864000 | J4: =H4+I4 -> 4864000 | K4: =IF(C4=0,0,J4/(C4*1000)) -> 1216 | L4: =C4*1000*Paramètres!$B$5 -> 7600000 | M4: =L4-J4 -> 2736000 | N4: =SUMIFS(Journal[Montant],Journal[Vague],$A4,Journal[Catégorie],"Opérationnel") -> 0 | O4: ='Aliment par vague'!$W4 -> 2252740.1 | P4: =J4+N4+O4 -> 7116740.1 | Q4: =IF(C4=0,0,P4/(C4*1000)) -> 1779.185 | R4: =L4-P4 -> 483259.86
A5: V2 | B5: 46266 | C5: 4 | D5: =IF(Paramètres!$B$6=0,0,ROUND(C5*1000/Paramètres!$B$6,0)) -> 10000 | E5: =ROUNDUP(D5*(1+Paramètres!$B$11),0) -> 11000 | F5: NON | G5: =INDEX(Paramètres!$C$16:$C$19,MATCH(C5,Paramètres!$B$16:$B$19,1)) -> 0 | H5: =IF($F5="NON",0,E5*Paramètres!$B$12*(1-G5)) -> 0 | I5: ='Aliment par vague'!$L5 -> 4864000 | J5: =H5+I5 -> 4864000 | K5: =IF(C5=0,0,J5/(C5*1000)) -> 1216 | L5: =C5*1000*Paramètres!$B$5 -> 7600000 | M5: =L5-J5 -> 2736000 | N5: =SUMIFS(Journal[Montant],Journal[Vague],$A5,Journal[Catégorie],"Opérationnel") -> 0 | O5: ='Aliment par vague'!$W5 -> 1044404.3 | P5: =J5+N5+O5 -> 5908404.3 | Q5: =IF(C5=0,0,P5/(C5*1000)) -> 1477.1011 | R5: =L5-P5 -> 1691595.7
A6: V3 | B6: 46296 | C6: 8 | D6: =IF(Paramètres!$B$6=0,0,ROUND(C6*1000/Paramètres!$B$6,0)) -> 20000 | E6: =ROUNDUP(D6*(1+Paramètres!$B$11),0) -> 22000 | F6: NON | G6: =INDEX(Paramètres!$C$16:$C$19,MATCH(C6,Paramètres!$B$16:$B$19,1)) -> 0.02 | H6: =IF($F6="NON",0,E6*Paramètres!$B$12*(1-G6)) -> 0 | I6: ='Aliment par vague'!$L6 -> 9533440 | J6: =H6+I6 -> 9533440 | K6: =IF(C6=0,0,J6/(C6*1000)) -> 1191.68 | L6: =C6*1000*Paramètres!$B$5 -> 15200000 | M6: =L6-J6 -> 5666560 | N6: =SUMIFS(Journal[Montant],Journal[Vague],$A6,Journal[Catégorie],"Opérationnel") -> 0 | O6: ='Aliment par vague'!$W6 -> 1535771.9 | P6: =J6+N6+O6 -> 11069212 | Q6: =IF(C6=0,0,P6/(C6*1000)) -> 1383.6515 | R6: =L6-P6 -> 4130788.1
A7: V4 | B7: 46327 | C7: 8 | D7: =IF(Paramètres!$B$6=0,0,ROUND(C7*1000/Paramètres!$B$6,0)) -> 20000 | E7: =ROUNDUP(D7*(1+Paramètres!$B$11),0) -> 22000 | F7: NON | G7: =INDEX(Paramètres!$C$16:$C$19,MATCH(C7,Paramètres!$B$16:$B$19,1)) -> 0.02 | H7: =IF($F7="NON",0,E7*Paramètres!$B$12*(1-G7)) -> 0 | I7: ='Aliment par vague'!$L7 -> 9533440 | J7: =H7+I7 -> 9533440 | K7: =IF(C7=0,0,J7/(C7*1000)) -> 1191.68 | L7: =C7*1000*Paramètres!$B$5 -> 15200000 | M7: =L7-J7 -> 5666560 | N7: =SUMIFS(Journal[Montant],Journal[Vague],$A7,Journal[Catégorie],"Opérationnel") -> 0 | O7: ='Aliment par vague'!$W7 -> 1287986 | P7: =J7+N7+O7 -> 10821426 | Q7: =IF(C7=0,0,P7/(C7*1000)) -> 1352.6782 | R7: =L7-P7 -> 4378574
A8: V5 | B8: 46357 | C8: 10 | D8: =IF(Paramètres!$B$6=0,0,ROUND(C8*1000/Paramètres!$B$6,0)) -> 25000 | E8: =ROUNDUP(D8*(1+Paramètres!$B$11),0) -> 27500 | F8: NON | G8: =INDEX(Paramètres!$C$16:$C$19,MATCH(C8,Paramètres!$B$16:$B$19,1)) -> 0.04 | H8: =IF($F8="NON",0,E8*Paramètres!$B$12*(1-G8)) -> 0 | I8: ='Aliment par vague'!$L8 -> 11673600 | J8: =H8+I8 -> 11673600 | K8: =IF(C8=0,0,J8/(C8*1000)) -> 1167.36 | L8: =C8*1000*Paramètres!$B$5 -> 19000000 | M8: =L8-J8 -> 7326400 | N8: =SUMIFS(Journal[Montant],Journal[Vague],$A8,Journal[Catégorie],"Opérationnel") -> 0 | O8: ='Aliment par vague'!$W8 -> 1408264.3 | P8: =J8+N8+O8 -> 13081864 | Q8: =IF(C8=0,0,P8/(C8*1000)) -> 1308.1864 | R8: =L8-P8 -> 5918135.7
A9: V6 | B9: 46388 | C9: 12 | D9: =IF(Paramètres!$B$6=0,0,ROUND(C9*1000/Paramètres!$B$6,0)) -> 30000 | E9: =ROUNDUP(D9*(1+Paramètres!$B$11),0) -> 33000 | F9: NON | G9: =INDEX(Paramètres!$C$16:$C$19,MATCH(C9,Paramètres!$B$16:$B$19,1)) -> 0.04 | H9: =IF($F9="NON",0,E9*Paramètres!$B$12*(1-G9)) -> 0 | I9: ='Aliment par vague'!$L9 -> 14008320 | J9: =H9+I9 -> 14008320 | K9: =IF(C9=0,0,J9/(C9*1000)) -> 1167.36 | L9: =C9*1000*Paramètres!$B$5 -> 22800000 | M9: =L9-J9 -> 8791680 | N9: =SUMIFS(Journal[Montant],Journal[Vague],$A9,Journal[Catégorie],"Opérationnel") -> 0 | O9: ='Aliment par vague'!$W9 -> 1478833.3 | P9: =J9+N9+O9 -> 15487153 | Q9: =IF(C9=0,0,P9/(C9*1000)) -> 1290.5961 | R9: =L9-P9 -> 7312846.7
A10: V7 | B10: 46419 | C10: 15 | D10: =IF(Paramètres!$B$6=0,0,ROUND(C10*1000/Paramètres!$B$6,0)) -> 37500 | E10: =ROUNDUP(D10*(1+Paramètres!$B$11),0) -> 41250 | F10: NON | G10: =INDEX(Paramètres!$C$16:$C$19,MATCH(C10,Paramètres!$B$16:$B$19,1)) -> 0.06 | H10: =IF($F10="NON",0,E10*Paramètres!$B$12*(1-G10)) -> 0 | I10: ='Aliment par vague'!$L10 -> 17145600 | J10: =H10+I10 -> 17145600 | K10: =IF(C10=0,0,J10/(C10*1000)) -> 1143.04 | L10: =C10*1000*Paramètres!$B$5 -> 28500000 | M10: =L10-J10 -> 11354400 | N10: =SUMIFS(Journal[Montant],Journal[Vague],$A10,Journal[Catégorie],"Opérationnel") -> 0 | O10: ='Aliment par vague'!$W10 -> 1675552.6 | P10: =J10+N10+O10 -> 18821153 | Q10: =IF(C10=0,0,P10/(C10*1000)) -> 1254.7435 | R10: =L10-P10 -> 9678847.4
A11: V8 | B11: 46447 | C11: 15 | D11: =IF(Paramètres!$B$6=0,0,ROUND(C11*1000/Paramètres!$B$6,0)) -> 37500 | E11: =ROUNDUP(D11*(1+Paramètres!$B$11),0) -> 41250 | F11: NON | G11: =INDEX(Paramètres!$C$16:$C$19,MATCH(C11,Paramètres!$B$16:$B$19,1)) -> 0.06 | H11: =IF($F11="NON",0,E11*Paramètres!$B$12*(1-G11)) -> 0 | I11: ='Aliment par vague'!$L11 -> 17145600 | J11: =H11+I11 -> 17145600 | K11: =IF(C11=0,0,J11/(C11*1000)) -> 1143.04 | L11: =C11*1000*Paramètres!$B$5 -> 28500000 | M11: =L11-J11 -> 11354400 | N11: =SUMIFS(Journal[Montant],Journal[Vague],$A11,Journal[Catégorie],"Opérationnel") -> 0 | O11: ='Aliment par vague'!$W11 -> 1613815.8 | P11: =J11+N11+O11 -> 18759416 | Q11: =IF(C11=0,0,P11/(C11*1000)) -> 1250.6277 | R11: =L11-P11 -> 9740584.2
A12: V9 | B12: 46478 | C12: 15 | D12: =IF(Paramètres!$B$6=0,0,ROUND(C12*1000/Paramètres!$B$6,0)) -> 37500 | E12: =ROUNDUP(D12*(1+Paramètres!$B$11),0) -> 41250 | F12: NON | G12: =INDEX(Paramètres!$C$16:$C$19,MATCH(C12,Paramètres!$B$16:$B$19,1)) -> 0.06 | H12: =IF($F12="NON",0,E12*Paramètres!$B$12*(1-G12)) -> 0 | I12: ='Aliment par vague'!$L12 -> 17145600 | J12: =H12+I12 -> 17145600 | K12: =IF(C12=0,0,J12/(C12*1000)) -> 1143.04 | L12: =C12*1000*Paramètres!$B$5 -> 28500000 | M12: =L12-J12 -> 11354400 | N12: =SUMIFS(Journal[Montant],Journal[Vague],$A12,Journal[Catégorie],"Opérationnel") -> 0 | O12: ='Aliment par vague'!$W12 -> 1605000 | P12: =J12+N12+O12 -> 18750600 | Q12: =IF(C12=0,0,P12/(C12*1000)) -> 1250.04 | R12: =L12-P12 -> 9749400
A13: V10 | B13: 46508 | C13: 15 | D13: =IF(Paramètres!$B$6=0,0,ROUND(C13*1000/Paramètres!$B$6,0)) -> 37500 | E13: =ROUNDUP(D13*(1+Paramètres!$B$11),0) -> 41250 | F13: NON | G13: =INDEX(Paramètres!$C$16:$C$19,MATCH(C13,Paramètres!$B$16:$B$19,1)) -> 0.06 | H13: =IF($F13="NON",0,E13*Paramètres!$B$12*(1-G13)) -> 0 | I13: ='Aliment par vague'!$L13 -> 17145600 | J13: =H13+I13 -> 17145600 | K13: =IF(C13=0,0,J13/(C13*1000)) -> 1143.04 | L13: =C13*1000*Paramètres!$B$5 -> 28500000 | M13: =L13-J13 -> 11354400 | N13: =SUMIFS(Journal[Montant],Journal[Vague],$A13,Journal[Catégorie],"Opérationnel") -> 0 | O13: ='Aliment par vague'!$W13 -> 1605000 | P13: =J13+N13+O13 -> 18750600 | Q13: =IF(C13=0,0,P13/(C13*1000)) -> 1250.04 | R13: =L13-P13 -> 9749400
A14: V11 | B14: 46539 | C14: 15 | D14: =IF(Paramètres!$B$6=0,0,ROUND(C14*1000/Paramètres!$B$6,0)) -> 37500 | E14: =ROUNDUP(D14*(1+Paramètres!$B$11),0) -> 41250 | F14: NON | G14: =INDEX(Paramètres!$C$16:$C$19,MATCH(C14,Paramètres!$B$16:$B$19,1)) -> 0.06 | H14: =IF($F14="NON",0,E14*Paramètres!$B$12*(1-G14)) -> 0 | I14: ='Aliment par vague'!$L14 -> 17145600 | J14: =H14+I14 -> 17145600 | K14: =IF(C14=0,0,J14/(C14*1000)) -> 1143.04 | L14: =C14*1000*Paramètres!$B$5 -> 28500000 | M14: =L14-J14 -> 11354400 | N14: =SUMIFS(Journal[Montant],Journal[Vague],$A14,Journal[Catégorie],"Opérationnel") -> 0 | O14: ='Aliment par vague'!$W14 -> 1605000 | P14: =J14+N14+O14 -> 18750600 | Q14: =IF(C14=0,0,P14/(C14*1000)) -> 1250.04 | R14: =L14-P14 -> 9749400
A15: V12 | B15: 46569 | C15: 15 | D15: =IF(Paramètres!$B$6=0,0,ROUND(C15*1000/Paramètres!$B$6,0)) -> 37500 | E15: =ROUNDUP(D15*(1+Paramètres!$B$11),0) -> 41250 | F15: NON | G15: =INDEX(Paramètres!$C$16:$C$19,MATCH(C15,Paramètres!$B$16:$B$19,1)) -> 0.06 | H15: =IF($F15="NON",0,E15*Paramètres!$B$12*(1-G15)) -> 0 | I15: ='Aliment par vague'!$L15 -> 17145600 | J15: =H15+I15 -> 17145600 | K15: =IF(C15=0,0,J15/(C15*1000)) -> 1143.04 | L15: =C15*1000*Paramètres!$B$5 -> 28500000 | M15: =L15-J15 -> 11354400 | N15: =SUMIFS(Journal[Montant],Journal[Vague],$A15,Journal[Catégorie],"Opérationnel") -> 0 | O15: ='Aliment par vague'!$W15 -> 1605000 | P15: =J15+N15+O15 -> 18750600 | Q15: =IF(C15=0,0,P15/(C15*1000)) -> 1250.04 | R15: =L15-P15 -> 9749400
... A22: V19 | B22: 46784 | C22: 15 | D22: =IF(Paramètres!$B$6=0,0,ROUND(C22*1000/Paramètres!$B$6,0)) -> 37500 | E22: =ROUNDUP(D22*(1+Paramètres!$B$11),0) -> 41250 | F22: NON | G22: =INDEX(Paramètres!$C$16:$C$19,MATCH(C22,Paramètres!$B$16:$B$19,1)) -> 0.06 | H22: =IF($F22="NON",0,E22*Paramètres!$B$12*(1-G22)) -> 0 | I22: ='Aliment par vague'!$L22 -> 17145600 | J22: =H22+I22 -> 17145600 | K22: =IF(C22=0,0,J22/(C22*1000)) -> 1143.04 | L22: =C22*1000*Paramètres!$B$5 -> 28500000 | M22: =L22-J22 -> 11354400 | N22: =SUMIFS(Journal[Montant],Journal[Vague],$A22,Journal[Catégorie],"Opérationnel") -> 0 | O22: ='Aliment par vague'!$W22 -> 2371184.2 | P22: =J22+N22+O22 -> 19516784 | Q22: =IF(C22=0,0,P22/(C22*1000)) -> 1301.1189 | R22: =L22-P22 -> 8983215.8
A23: TOTAL | C23: =SUM(C4:C22) -> 241 | D23: =SUM(D4:D22) -> 602500 | E23: =SUM(E4:E22) -> 662750 | H23: =SUM(H4:H22) -> 0 | I23: =SUM(I4:I22) -> 277369600 | J23: =SUM(J4:J22) -> 277369600 | K23: =IF(C23=0,0,J23/(C23*1000)) -> 1150.9112 | L23: =SUM(L4:L22) -> 457900000 | M23: =SUM(M4:M22) -> 180530400 | N23: =SUM(N4:N22) -> 0 | O23: =SUM(O4:O22) -> 30760000 | P23: =SUM(P4:P22) -> 308129600 | Q23: =IF(C23=0,0,P23/(C23*1000)) -> 1278.5461 | R23: =SUM(R4:R22) -> 149770400

Sheet Aliment par vague
A1: ALIMENT PAR VAGUE — saisissez les SACS de chaque vague, par granulométrie
A2: Les sacs de chaque vague sont CALCULÉS depuis son tonnage (Empoissonnement) × le standard « sacs par tonne » de la feuille Aliments. Pour une vague particulière, vous pouvez taper un nombre de sacs par-dessus la formule. Kilos et coûts (remise fournisseur déduite) se calculent tout seuls ; la répartition de chaque granulé entre les mois du cycle suit la feuille Aliments.
A3: Vague | B3: Mois d'empoissonnement | C3: Objectif (t) | D3: =IF(Aliments!$A$4="","—",Aliments!$A$4&" (sacs)") -> 2 mm (sacs) | E3: =IF(Aliments!$A$5="","—",Aliments!$A$5&" (sacs)") -> 3 mm (sacs) | F3: =IF(Aliments!$A$6="","—",Aliments!$A$6&" (sacs)") -> 4 mm (sacs) | G3: =IF(Aliments!$A$7="","—",Aliments!$A$7&" (sacs)") -> — | H3: =IF(Aliments!$A$8="","—",Aliments!$A$8&" (sacs)") -> — | I3: =IF(Aliments!$A$9="","—",Aliments!$A$9&" (sacs)") -> — | J3: Total sacs | K3: Total kg | L3: Coût total aliments (FCFA, remise déduite) | Q3: Aliment mois 1 (kg) | R3: Aliment mois 2 (kg) | S3: Aliment mois 3 (kg) | T3: Quote-part charges mois 1 (FCFA) | U3: Quote-part charges mois 2 (FCFA) | V3: Quote-part charges mois 3 (FCFA) | W3: Quote-part charges générales — total (FCFA)
A4: =Empoissonnement!A4 -> V1 | B4: =Empoissonnement!B4 -> 46235 | C4: =Empoissonnement!C4 -> 4 | D4: =ROUNDUP(Empoissonnement!C4*N(Aliments!$J$4),0) -> 32 | E4: =ROUNDUP(Empoissonnement!C4*N(Aliments!$J$5),0) -> 72 | F4: =ROUNDUP(Empoissonnement!C4*N(Aliments!$J$6),0) -> 200 | G4: =ROUNDUP(Empoissonnement!C4*N(Aliments!$J$7),0) -> 0 | H4: =ROUNDUP(Empoissonnement!C4*N(Aliments!$J$8),0) -> 0 | I4: =ROUNDUP(Empoissonnement!C4*N(Aliments!$J$9),0) -> 0 | J4: =SUM(D4:I4) -> 304 | K4: =D4*N(Aliments!$C$4)+E4*N(Aliments!$C$5)+F4*N(Aliments!$C$6)+G4*N(Aliments!$C$7)+H4*N(Aliments!$C$8)+I4*N(Aliments!$C$9) -> 4560 | L4: =(D4*N(Aliments!$D$4)+E4*N(Aliments!$D$5)+F4*N(Aliments!$D$6)+G4*N(Aliments!$D$7)+H4*N(Aliments!$D$8)+I4*N(Aliments!$D$9))*(1-Empoissonnement!$G4) -> 4864000 | N4: =(D4*N(Aliments!$D$4)*N(Aliments!$F$4)+E4*N(Aliments!$D$5)*N(Aliments!$F$5)+F4*N(Aliments!$D$6)*N(Aliments!$F$6)+G4*N(Aliments!$D$7)*N(Aliments!$F$7)+H4*N(Aliments!$D$8)*N(Aliments!$F$8)+I4*N(Aliments!$D$9)*N(Aliments!$F$9))*(1-Empoissonnement!$G4) -> 698400 | O4: =(D4*N(Aliments!$D$4)*N(Aliments!$G$4)+E4*N(Aliments!$D$5)*N(Aliments!$G$5)+F4*N(Aliments!$D$6)*N(Aliments!$G$6)+G4*N(Aliments!$D$7)*N(Aliments!$G$7)+H4*N(Aliments!$D$8)*N(Aliments!$G$8)+I4*N(Aliments!$D$9)*N(Aliments!$G$9))*(1-Empoissonnement!$G4) -> 2305600 | P4: =(D4*N(Aliments!$D$4)*N(Aliments!$H$4)+E4*N(Aliments!$D$5)*N(Aliments!$H$5)+F4*N(Aliments!$D$6)*N(Aliments!$H$6)+G4*N(Aliments!$D$7)*N(Aliments!$H$7)+H4*N(Aliments!$D$8)*N(Aliments!$H$8)+I4*N(Aliments!$D$9)*N(Aliments!$H$9))*(1-Empoissonnement!$G4) -> 1860000 | Q4: =D4*N(Aliments!$C$4)*N(Aliments!$F$4)+E4*N(Aliments!$C$5)*N(Aliments!$F$5)+F4*N(Aliments!$C$6)*N(Aliments!$F$6)+G4*N(Aliments!$C$7)*N(Aliments!$F$7)+H4*N(Aliments!$C$8)*N(Aliments!$F$8)+I4*N(Aliments!$C$9)*N(Aliments!$F$9) -> 600 | R4: =D4*N(Aliments!$C$4)*N(Aliments!$G$4)+E4*N(Aliments!$C$5)*N(Aliments!$G$5)+F4*N(Aliments!$C$6)*N(Aliments!$G$6)+G4*N(Aliments!$C$7)*N(Aliments!$G$7)+H4*N(Aliments!$C$8)*N(Aliments!$G$8)+I4*N(Aliments!$C$9)*N(Aliments!$G$9) -> 2160 | S4: =D4*N(Aliments!$C$4)*N(Aliments!$H$4)+E4*N(Aliments!$C$5)*N(Aliments!$H$5)+F4*N(Aliments!$C$6)*N(Aliments!$H$6)+G4*N(Aliments!$C$7)*N(Aliments!$H$7)+H4*N(Aliments!$C$8)*N(Aliments!$H$8)+I4*N(Aliments!$C$9)*N(Aliments!$H$9) -> 1800 | T4: =IFERROR(Q4/INDEX('Besoins aliments'!$H$5:$H$25,MATCH(Empoissonnement!$B4,'Besoins aliments'!$A$5:$A$25,0))*INDEX(Dépenses!$B$31:$V$31,MATCH(Empoissonnement!$B4,Dépenses!$B$3:$V$3,0)),0) -> 995000 | U4: =IFERROR(R4/INDEX('Besoins aliments'!$H$5:$H$25,MATCH(EDATE(Empoissonnement!$B4,1),'Besoins aliments'!$A$5:$A$25,0))*INDEX(Dépenses!$B$31:$V$31,MATCH(EDATE(Empoissonnement!$B4,1),Dépenses!$B$3:$V$3,0)),0) -> 837391.3 | V4: =IFERROR(S4/INDEX('Besoins aliments'!$H$5:$H$25,MATCH(EDATE(Empoissonnement!$B4,2),'Besoins aliments'!$A$5:$A$25,0))*INDEX(Dépenses!$B$31:$V$31,MATCH(EDATE(Empoissonnement!$B4,2),Dépenses!$B$3:$V$3,0)),0) -> 420348.84 | W4: =T4+U4+V4 -> 2252740.1
A5: =Empoissonnement!A5 -> V2 | B5: =Empoissonnement!B5 -> 46266 | C5: =Empoissonnement!C5 -> 4 | D5: =ROUNDUP(Empoissonnement!C5*N(Aliments!$J$4),0) -> 32 | E5: =ROUNDUP(Empoissonnement!C5*N(Aliments!$J$5),0) -> 72 | F5: =ROUNDUP(Empoissonnement!C5*N(Aliments!$J$6),0) -> 200 | G5: =ROUNDUP(Empoissonnement!C5*N(Aliments!$J$7),0) -> 0 | H5: =ROUNDUP(Empoissonnement!C5*N(Aliments!$J$8),0) -> 0 | I5: =ROUNDUP(Empoissonnement!C5*N(Aliments!$J$9),0) -> 0 | J5: =SUM(D5:I5) -> 304 | K5: =D5*N(Aliments!$C$4)+E5*N(Aliments!$C$5)+F5*N(Aliments!$C$6)+G5*N(Aliments!$C$7)+H5*N(Aliments!$C$8)+I5*N(Aliments!$C$9) -> 4560 | L5: =(D5*N(Aliments!$D$4)+E5*N(Aliments!$D$5)+F5*N(Aliments!$D$6)+G5*N(Aliments!$D$7)+H5*N(Aliments!$D$8)+I5*N(Aliments!$D$9))*(1-Empoissonnement!$G5) -> 4864000 | N5: =(D5*N(Aliments!$D$4)*N(Aliments!$F$4)+E5*N(Aliments!$D$5)*N(Aliments!$F$5)+F5*N(Aliments!$D$6)*N(Aliments!$F$6)+G5*N(Aliments!$D$7)*N(Aliments!$F$7)+H5*N(Aliments!$D$8)*N(Aliments!$F$8)+I5*N(Aliments!$D$9)*N(Aliments!$F$9))*(1-Empoissonnement!$G5) -> 698400 | O5: =(D5*N(Aliments!$D$4)*N(Aliments!$G$4)+E5*N(Aliments!$D$5)*N(Aliments!$G$5)+F5*N(Aliments!$D$6)*N(Aliments!$G$6)+G5*N(Aliments!$D$7)*N(Aliments!$G$7)+H5*N(Aliments!$D$8)*N(Aliments!$G$8)+I5*N(Aliments!$D$9)*N(Aliments!$G$9))*(1-Empoissonnement!$G5) -> 2305600 | P5: =(D5*N(Aliments!$D$4)*N(Aliments!$H$4)+E5*N(Aliments!$D$5)*N(Aliments!$H$5)+F5*N(Aliments!$D$6)*N(Aliments!$H$6)+G5*N(Aliments!$D$7)*N(Aliments!$H$7)+H5*N(Aliments!$D$8)*N(Aliments!$H$8)+I5*N(Aliments!$D$9)*N(Aliments!$H$9))*(1-Empoissonnement!$G5) -> 1860000 | Q5: =D5*N(Aliments!$C$4)*N(Aliments!$F$4)+E5*N(Aliments!$C$5)*N(Aliments!$F$5)+F5*N(Aliments!$C$6)*N(Aliments!$F$6)+G5*N(Aliments!$C$7)*N(Aliments!$F$7)+H5*N(Aliments!$C$8)*N(Aliments!$F$8)+I5*N(Aliments!$C$9)*N(Aliments!$F$9) -> 600 | R5: =D5*N(Aliments!$C$4)*N(Aliments!$G$4)+E5*N(Aliments!$C$5)*N(Aliments!$G$5)+F5*N(Aliments!$C$6)*N(Aliments!$G$6)+G5*N(Aliments!$C$7)*N(Aliments!$G$7)+H5*N(Aliments!$C$8)*N(Aliments!$G$8)+I5*N(Aliments!$C$9)*N(Aliments!$G$9) -> 2160 | S5: =D5*N(Aliments!$C$4)*N(Aliments!$H$4)+E5*N(Aliments!$C$5)*N(Aliments!$H$5)+F5*N(Aliments!$C$6)*N(Aliments!$H$6)+G5*N(Aliments!$C$7)*N(Aliments!$H$7)+H5*N(Aliments!$C$8)*N(Aliments!$H$8)+I5*N(Aliments!$C$9)*N(Aliments!$H$9) -> 1800 | T5: =IFERROR(Q5/INDEX('Besoins aliments'!$H$5:$H$25,MATCH(Empoissonnement!$B5,'Besoins aliments'!$A$5:$A$25,0))*INDEX(Dépenses!$B$31:$V$31,MATCH(Empoissonnement!$B5,Dépenses!$B$3:$V$3,0)),0) -> 232608.7 | U5: =IFERROR(R5/INDEX('Besoins aliments'!$H$5:$H$25,MATCH(EDATE(Empoissonnement!$B5,1),'Besoins aliments'!$A$5:$A$25,0))*INDEX(Dépenses!$B$31:$V$31,MATCH(EDATE(Empoissonnement!$B5,1),Dépenses!$B$3:$V$3,0)),0) -> 504418.6 | V5: =IFERROR(S5/INDEX('Besoins aliments'!$H$5:$H$25,MATCH(EDATE(Empoissonnement!$B5,2),'Besoins aliments'!$A$5:$A$25,0))*INDEX(Dépenses!$B$31:$V$31,MATCH(EDATE(Empoissonnement!$B5,2),Dépenses!$B$3:$V$3,0)),0) -> 307377.05 | W5: =T5+U5+V5 -> 1044404.3
A6: =Empoissonnement!A6 -> V3 | B6: =Empoissonnement!B6 -> 46296 | C6: =Empoissonnement!C6 -> 8 | D6: =ROUNDUP(Empoissonnement!C6*N(Aliments!$J$4),0) -> 64 | E6: =ROUNDUP(Empoissonnement!C6*N(Aliments!$J$5),0) -> 144 | F6: =ROUNDUP(Empoissonnement!C6*N(Aliments!$J$6),0) -> 400 | G6: =ROUNDUP(Empoissonnement!C6*N(Aliments!$J$7),0) -> 0 | H6: =ROUNDUP(Empoissonnement!C6*N(Aliments!$J$8),0) -> 0 | I6: =ROUNDUP(Empoissonnement!C6*N(Aliments!$J$9),0) -> 0 | J6: =SUM(D6:I6) -> 608 | K6: =D6*N(Aliments!$C$4)+E6*N(Aliments!$C$5)+F6*N(Aliments!$C$6)+G6*N(Aliments!$C$7)+H6*N(Aliments!$C$8)+I6*N(Aliments!$C$9) -> 9120 | L6: =(D6*N(Aliments!$D$4)+E6*N(Aliments!$D$5)+F6*N(Aliments!$D$6)+G6*N(Aliments!$D$7)+H6*N(Aliments!$D$8)+I6*N(Aliments!$D$9))*(1-Empoissonnement!$G6) -> 9533440 | N6: =(D6*N(Aliments!$D$4)*N(Aliments!$F$4)+E6*N(Aliments!$D$5)*N(Aliments!$F$5)+F6*N(Aliments!$D$6)*N(Aliments!$F$6)+G6*N(Aliments!$D$7)*N(Aliments!$F$7)+H6*N(Aliments!$D$8)*N(Aliments!$F$8)+I6*N(Aliments!$D$9)*N(Aliments!$F$9))*(1-Empoissonnement!$G6) -> 1368864 | O6: =(D6*N(Aliments!$D$4)*N(Aliments!$G$4)+E6*N(Aliments!$D$5)*N(Aliments!$G$5)+F6*N(Aliments!$D$6)*N(Aliments!$G$6)+G6*N(Aliments!$D$7)*N(Aliments!$G$7)+H6*N(Aliments!$D$8)*N(Aliments!$G$8)+I6*N(Aliments!$D$9)*N(Aliments!$G$9))*(1-Empoissonnement!$G6) -> 4518976 | P6: =(D6*N(Aliments!$D$4)*N(Aliments!$H$4)+E6*N(Aliments!$D$5)*N(Aliments!$H$5)+F6*N(Aliments!$D$6)*N(Aliments!$H$6)+G6*N(Aliments!$D$7)*N(Aliments!$H$7)+H6*N(Aliments!$D$8)*N(Aliments!$H$8)+I6*N(Aliments!$D$9)*N(Aliments!$H$9))*(1-Empoissonnement!$G6) -> 3645600 | Q6: =D6*N(Aliments!$C$4)*N(Aliments!$F$4)+E6*N(Aliments!$C$5)*N(Aliments!$F$5)+F6*N(Aliments!$C$6)*N(Aliments!$F$6)+G6*N(Aliments!$C$7)*N(Aliments!$F$7)+H6*N(Aliments!$C$8)*N(Aliments!$F$8)+I6*N(Aliments!$C$9)*N(Aliments!$F$9) -> 1200 | R6: =D6*N(Aliments!$C$4)*N(Aliments!$G$4)+E6*N(Aliments!$C$5)*N(Aliments!$G$5)+F6*N(Aliments!$C$6)*N(Aliments!$G$6)+G6*N(Aliments!$C$7)*N(Aliments!$G$7)+H6*N(Aliments!$C$8)*N(Aliments!$G$8)+I6*N(Aliments!$C$9)*N(Aliments!$G$9) -> 4320 | S6: =D6*N(Aliments!$C$4)*N(Aliments!$H$4)+E6*N(Aliments!$C$5)*N(Aliments!$H$5)+F6*N(Aliments!$C$6)*N(Aliments!$H$6)+G6*N(Aliments!$C$7)*N(Aliments!$H$7)+H6*N(Aliments!$C$8)*N(Aliments!$H$8)+I6*N(Aliments!$C$9)*N(Aliments!$H$9) -> 3600 | T6: =IFERROR(Q6/INDEX('Besoins aliments'!$H$5:$H$25,MATCH(Empoissonnement!$B6,'Besoins aliments'!$A$5:$A$25,0))*INDEX(Dépenses!$B$31:$V$31,MATCH(Empoissonnement!$B6,Dépenses!$B$3:$V$3,0)),0) -> 280232.56 | U6: =IFERROR(R6/INDEX('Besoins aliments'!$H$5:$H$25,MATCH(EDATE(Empoissonnement!$B6,1),'Besoins aliments'!$A$5:$A$25,0))*INDEX(Dépenses!$B$31:$V$31,MATCH(EDATE(Empoissonnement!$B6,1),Dépenses!$B$3:$V$3,0)),0) -> 737704.92 | V6: =IFERROR(S6/INDEX('Besoins aliments'!$H$5:$H$25,MATCH(EDATE(Empoissonnement!$B6,2),'Besoins aliments'!$A$5:$A$25,0))*INDEX(Dépenses!$B$31:$V$31,MATCH(EDATE(Empoissonnement!$B6,2),Dépenses!$B$3:$V$3,0)),0) -> 517834.39 | W6: =T6+U6+V6 -> 1535771.9
A7: =Empoissonnement!A7 -> V4 | B7: =Empoissonnement!B7 -> 46327 | C7: =Empoissonnement!C7 -> 8 | D7: =ROUNDUP(Empoissonnement!C7*N(Aliments!$J$4),0) -> 64 | E7: =ROUNDUP(Empoissonnement!C7*N(Aliments!$J$5),0) -> 144 | F7: =ROUNDUP(Empoissonnement!C7*N(Aliments!$J$6),0) -> 400 | G7: =ROUNDUP(Empoissonnement!C7*N(Aliments!$J$7),0) -> 0 | H7: =ROUNDUP(Empoissonnement!C7*N(Aliments!$J$8),0) -> 0 | I7: =ROUNDUP(Empoissonnement!C7*N(Aliments!$J$9),0) -> 0 | J7: =SUM(D7:I7) -> 608 | K7: =D7*N(Aliments!$C$4)+E7*N(Aliments!$C$5)+F7*N(Aliments!$C$6)+G7*N(Aliments!$C$7)+H7*N(Aliments!$C$8)+I7*N(Aliments!$C$9) -> 9120 | L7: =(D7*N(Aliments!$D$4)+E7*N(Aliments!$D$5)+F7*N(Aliments!$D$6)+G7*N(Aliments!$D$7)+H7*N(Aliments!$D$8)+I7*N(Aliments!$D$9))*(1-Empoissonnement!$G7) -> 9533440 | N7: =(D7*N(Aliments!$D$4)*N(Aliments!$F$4)+E7*N(Aliments!$D$5)*N(Aliments!$F$5)+F7*N(Aliments!$D$6)*N(Aliments!$F$6)+G7*N(Aliments!$D$7)*N(Aliments!$F$7)+H7*N(Aliments!$D$8)*N(Aliments!$F$8)+I7*N(Aliments!$D$9)*N(Aliments!$F$9))*(1-Empoissonnement!$G7) -> 1368864 | O7: =(D7*N(Aliments!$D$4)*N(Aliments!$G$4)+E7*N(Aliments!$D$5)*N(Aliments!$G$5)+F7*N(Aliments!$D$6)*N(Aliments!$G$6)+G7*N(Aliments!$D$7)*N(Aliments!$G$7)+H7*N(Aliments!$D$8)*N(Aliments!$G$8)+I7*N(Aliments!$D$9)*N(Aliments!$G$9))*(1-Empoissonnement!$G7) -> 4518976 | P7: =(D7*N(Aliments!$D$4)*N(Aliments!$H$4)+E7*N(Aliments!$D$5)*N(Aliments!$H$5)+F7*N(Aliments!$D$6)*N(Aliments!$H$6)+G7*N(Aliments!$D$7)*N(Aliments!$H$7)+H7*N(Aliments!$D$8)*N(Aliments!$H$8)+I7*N(Aliments!$D$9)*N(Aliments!$H$9))*(1-Empoissonnement!$G7) -> 3645600 | Q7: =D7*N(Aliments!$C$4)*N(Aliments!$F$4)+E7*N(Aliments!$C$5)*N(Aliments!$F$5)+F7*N(Aliments!$C$6)*N(Aliments!$F$6)+G7*N(Aliments!$C$7)*N(Aliments!$F$7)+H7*N(Aliments!$C$8)*N(Aliments!$F$8)+I7*N(Aliments!$C$9)*N(Aliments!$F$9) -> 1200 | R7: =D7*N(Aliments!$C$4)*N(Aliments!$G$4)+E7*N(Aliments!$C$5)*N(Aliments!$G$5)+F7*N(Aliments!$C$6)*N(Aliments!$G$6)+G7*N(Aliments!$C$7)*N(Aliments!$G$7)+H7*N(Aliments!$C$8)*N(Aliments!$G$8)+I7*N(Aliments!$C$9)*N(Aliments!$G$9) -> 4320 | S7: =D7*N(Aliments!$C$4)*N(Aliments!$H$4)+E7*N(Aliments!$C$5)*N(Aliments!$H$5)+F7*N(Aliments!$C$6)*N(Aliments!$H$6)+G7*N(Aliments!$C$7)*N(Aliments!$H$7)+H7*N(Aliments!$C$8)*N(Aliments!$H$8)+I7*N(Aliments!$C$9)*N(Aliments!$H$9) -> 3600 | T7: =IFERROR(Q7/INDEX('Besoins aliments'!$H$5:$H$25,MATCH(Empoissonnement!$B7,'Besoins aliments'!$A$5:$A$25,0))*INDEX(Dépenses!$B$31:$V$31,MATCH(Empoissonnement!$B7,Dépenses!$B$3:$V$3,0)),0) -> 204918.03 | U7: =IFERROR(R7/INDEX('Besoins aliments'!$H$5:$H$25,MATCH(EDATE(Empoissonnement!$B7,1),'Besoins aliments'!$A$5:$A$25,0))*INDEX(Dépenses!$B$31:$V$31,MATCH(EDATE(Empoissonnement!$B7,1),Dépenses!$B$3:$V$3,0)),0) -> 621401.27 | V7: =IFERROR(S7/INDEX('Besoins aliments'!$H$5:$H$25,MATCH(EDATE(Empoissonnement!$B7,2),'Besoins aliments'!$A$5:$A$25,0))*INDEX(Dépenses!$B$31:$V$31,MATCH(EDATE(Empoissonnement!$B7,2),Dépenses!$B$3:$V$3,0)),0) -> 461666.67 | W7: =T7+U7+V7 -> 1287986
A8: =Empoissonnement!A8 -> V5 | B8: =Empoissonnement!B8 -> 46357 | C8: =Empoissonnement!C8 -> 10 | D8: =ROUNDUP(Empoissonnement!C8*N(Aliments!$J$4),0) -> 80 | E8: =ROUNDUP(Empoissonnement!C8*N(Aliments!$J$5),0) -> 180 | F8: =ROUNDUP(Empoissonnement!C8*N(Aliments!$J$6),0) -> 500 | G8: =ROUNDUP(Empoissonnement!C8*N(Aliments!$J$7),0) -> 0 | H8: =ROUNDUP(Empoissonnement!C8*N(Aliments!$J$8),0) -> 0 | I8: =ROUNDUP(Empoissonnement!C8*N(Aliments!$J$9),0) -> 0 | J8: =SUM(D8:I8) -> 760 | K8: =D8*N(Aliments!$C$4)+E8*N(Aliments!$C$5)+F8*N(Aliments!$C$6)+G8*N(Aliments!$C$7)+H8*N(Aliments!$C$8)+I8*N(Aliments!$C$9) -> 11400 | L8: =(D8*N(Aliments!$D$4)+E8*N(Aliments!$D$5)+F8*N(Aliments!$D$6)+G8*N(Aliments!$D$7)+H8*N(Aliments!$D$8)+I8*N(Aliments!$D$9))*(1-Empoissonnement!$G8) -> 11673600 | N8: =(D8*N(Aliments!$D$4)*N(Aliments!$F$4)+E8*N(Aliments!$D$5)*N(Aliments!$F$5)+F8*N(Aliments!$D$6)*N(Aliments!$F$6)+G8*N(Aliments!$D$7)*N(Aliments!$F$7)+H8*N(Aliments!$D$8)*N(Aliments!$F$8)+I8*N(Aliments!$D$9)*N(Aliments!$F$9))*(1-Empoissonnement!$G8) -> 1676160 | O8: =(D8*N(Aliments!$D$4)*N(Aliments!$G$4)+E8*N(Aliments!$D$5)*N(Aliments!$G$5)+F8*N(Aliments!$D$6)*N(Aliments!$G$6)+G8*N(Aliments!$D$7)*N(Aliments!$G$7)+H8*N(Aliments!$D$8)*N(Aliments!$G$8)+I8*N(Aliments!$D$9)*N(Aliments!$G$9))*(1-Empoissonnement!$G8) -> 5533440 | P8: =(D8*N(Aliments!$D$4)*N(Aliments!$H$4)+E8*N(Aliments!$D$5)*N(Aliments!$H$5)+F8*N(Aliments!$D$6)*N(Aliments!$H$6)+G8*N(Aliments!$D$7)*N(Aliments!$H$7)+H8*N(Aliments!$D$8)*N(Aliments!$H$8)+I8*N(Aliments!$D$9)*N(Aliments!$H$9))*(1-Empoissonnement!$G8) -> 4464000 | Q8: =D8*N(Aliments!$C$4)*N(Aliments!$F$4)+E8*N(Aliments!$C$5)*N(Aliments!$F$5)+F8*N(Aliments!$C$6)*N(Aliments!$F$6)+G8*N(Aliments!$C$7)*N(Aliments!$F$7)+H8*N(Aliments!$C$8)*N(Aliments!$F$8)+I8*N(Aliments!$C$9)*N(Aliments!$F$9) -> 1500 | R8: =D8*N(Aliments!$C$4)*N(Aliments!$G$4)+E8*N(Aliments!$C$5)*N(Aliments!$G$5)+F8*N(Aliments!$C$6)*N(Aliments!$G$6)+G8*N(Aliments!$C$7)*N(Aliments!$G$7)+H8*N(Aliments!$C$8)*N(Aliments!$G$8)+I8*N(Aliments!$C$9)*N(Aliments!$G$9) -> 5400 | S8: =D8*N(Aliments!$C$4)*N(Aliments!$H$4)+E8*N(Aliments!$C$5)*N(Aliments!$H$5)+F8*N(Aliments!$C$6)*N(Aliments!$H$6)+G8*N(Aliments!$C$7)*N(Aliments!$H$7)+H8*N(Aliments!$C$8)*N(Aliments!$H$8)+I8*N(Aliments!$C$9)*N(Aliments!$H$9) -> 4500 | T8: =IFERROR(Q8/INDEX('Besoins aliments'!$H$5:$H$25,MATCH(Empoissonnement!$B8,'Besoins aliments'!$A$5:$A$25,0))*INDEX(Dépenses!$B$31:$V$31,MATCH(Empoissonnement!$B8,Dépenses!$B$3:$V$3,0)),0) -> 215764.33 | U8: =IFERROR(R8/INDEX('Besoins aliments'!$H$5:$H$25,MATCH(EDATE(Empoissonnement!$B8,1),'Besoins aliments'!$A$5:$A$25,0))*INDEX(Dépenses!$B$31:$V$31,MATCH(EDATE(Empoissonnement!$B8,1),Dépenses!$B$3:$V$3,0)),0) -> 692500 | V8: =IFERROR(S8/INDEX('Besoins aliments'!$H$5:$H$25,MATCH(EDATE(Empoissonnement!$B8,2),'Besoins aliments'!$A$5:$A$25,0))*INDEX(Dépenses!$B$31:$V$31,MATCH(EDATE(Empoissonnement!$B8,2),Dépenses!$B$3:$V$3,0)),0) -> 500000 | W8: =T8+U8+V8 -> 1408264.3
A9: =Empoissonnement!A9 -> V6 | B9: =Empoissonnement!B9 -> 46388 | C9: =Empoissonnement!C9 -> 12 | D9: =ROUNDUP(Empoissonnement!C9*N(Aliments!$J$4),0) -> 96 | E9: =ROUNDUP(Empoissonnement!C9*N(Aliments!$J$5),0) -> 216 | F9: =ROUNDUP(Empoissonnement!C9*N(Aliments!$J$6),0) -> 600 | G9: =ROUNDUP(Empoissonnement!C9*N(Aliments!$J$7),0) -> 0 | H9: =ROUNDUP(Empoissonnement!C9*N(Aliments!$J$8),0) -> 0 | I9: =ROUNDUP(Empoissonnement!C9*N(Aliments!$J$9),0) -> 0 | J9: =SUM(D9:I9) -> 912 | K9: =D9*N(Aliments!$C$4)+E9*N(Aliments!$C$5)+F9*N(Aliments!$C$6)+G9*N(Aliments!$C$7)+H9*N(Aliments!$C$8)+I9*N(Aliments!$C$9) -> 13680 | L9: =(D9*N(Aliments!$D$4)+E9*N(Aliments!$D$5)+F9*N(Aliments!$D$6)+G9*N(Aliments!$D$7)+H9*N(Aliments!$D$8)+I9*N(Aliments!$D$9))*(1-Empoissonnement!$G9) -> 14008320 | N9: =(D9*N(Aliments!$D$4)*N(Aliments!$F$4)+E9*N(Aliments!$D$5)*N(Aliments!$F$5)+F9*N(Aliments!$D$6)*N(Aliments!$F$6)+G9*N(Aliments!$D$7)*N(Aliments!$F$7)+H9*N(Aliments!$D$8)*N(Aliments!$F$8)+I9*N(Aliments!$D$9)*N(Aliments!$F$9))*(1-Empoissonnement!$G9) -> 2011392 | O9: =(D9*N(Aliments!$D$4)*N(Aliments!$G$4)+E9*N(Aliments!$D$5)*N(Aliments!$G$5)+F9*N(Aliments!$D$6)*N(Aliments!$G$6)+G9*N(Aliments!$D$7)*N(Aliments!$G$7)+H9*N(Aliments!$D$8)*N(Aliments!$G$8)+I9*N(Aliments!$D$9)*N(Aliments!$G$9))*(1-Empoissonnement!$G9) -> 6640128 | P9: =(D9*N(Aliments!$D$4)*N(Aliments!$H$4)+E9*N(Aliments!$D$5)*N(Aliments!$H$5)+F9*N(Aliments!$D$6)*N(Aliments!$H$6)+G9*N(Aliments!$D$7)*N(Aliments!$H$7)+H9*N(Aliments!$D$8)*N(Aliments!$H$8)+I9*N(Aliments!$D$9)*N(Aliments!$H$9))*(1-Empoissonnement!$G9) -> 5356800 | Q9: =D9*N(Aliments!$C$4)*N(Aliments!$F$4)+E9*N(Aliments!$C$5)*N(Aliments!$F$5)+F9*N(Aliments!$C$6)*N(Aliments!$F$6)+G9*N(Aliments!$C$7)*N(Aliments!$F$7)+H9*N(Aliments!$C$8)*N(Aliments!$F$8)+I9*N(Aliments!$C$9)*N(Aliments!$F$9) -> 1800 | R9: =D9*N(Aliments!$C$4)*N(Aliments!$G$4)+E9*N(Aliments!$C$5)*N(Aliments!$G$5)+F9*N(Aliments!$C$6)*N(Aliments!$G$6)+G9*N(Aliments!$C$7)*N(Aliments!$G$7)+H9*N(Aliments!$C$8)*N(Aliments!$G$8)+I9*N(Aliments!$C$9)*N(Aliments!$G$9) -> 6480 | S9: =D9*N(Aliments!$C$4)*N(Aliments!$H$4)+E9*N(Aliments!$C$5)*N(Aliments!$H$5)+F9*N(Aliments!$C$6)*N(Aliments!$H$6)+G9*N(Aliments!$C$7)*N(Aliments!$H$7)+H9*N(Aliments!$C$8)*N(Aliments!$H$8)+I9*N(Aliments!$C$9)*N(Aliments!$H$9) -> 5400 | T9: =IFERROR(Q9/INDEX('Besoins aliments'!$H$5:$H$25,MATCH(Empoissonnement!$B9,'Besoins aliments'!$A$5:$A$25,0))*INDEX(Dépenses!$B$31:$V$31,MATCH(Empoissonnement!$B9,Dépenses!$B$3:$V$3,0)),0) -> 230833.33 | U9: =IFERROR(R9/INDEX('Besoins aliments'!$H$5:$H$25,MATCH(EDATE(Empoissonnement!$B9,1),'Besoins aliments'!$A$5:$A$25,0))*INDEX(Dépenses!$B$31:$V$31,MATCH(EDATE(Empoissonnement!$B9,1),Dépenses!$B$3:$V$3,0)),0) -> 720000 | V9: =IFERROR(S9/INDEX('Besoins aliments'!$H$5:$H$25,MATCH(EDATE(Empoissonnement!$B9,2),'Besoins aliments'!$A$5:$A$25,0))*INDEX(Dépenses!$B$31:$V$31,MATCH(EDATE(Empoissonnement!$B9,2),Dépenses!$B$3:$V$3,0)),0) -> 528000 | W9: =T9+U9+V9 -> 1478833.3
A10: =Empoissonnement!A10 -> V7 | B10: =Empoissonnement!B10 -> 46419 | C10: =Empoissonnement!C10 -> 15 | D10: =ROUNDUP(Empoissonnement!C10*N(Aliments!$J$4),0) -> 120 | E10: =ROUNDUP(Empoissonnement!C10*N(Aliments!$J$5),0) -> 270 | F10: =ROUNDUP(Empoissonnement!C10*N(Aliments!$J$6),0) -> 750 | G10: =ROUNDUP(Empoissonnement!C10*N(Aliments!$J$7),0) -> 0 | H10: =ROUNDUP(Empoissonnement!C10*N(Aliments!$J$8),0) -> 0 | I10: =ROUNDUP(Empoissonnement!C10*N(Aliments!$J$9),0) -> 0 | J10: =SUM(D10:I10) -> 1140 | K10: =D10*N(Aliments!$C$4)+E10*N(Aliments!$C$5)+F10*N(Aliments!$C$6)+G10*N(Aliments!$C$7)+H10*N(Aliments!$C$8)+I10*N(Aliments!$C$9) -> 17100 | L10: =(D10*N(Aliments!$D$4)+E10*N(Aliments!$D$5)+F10*N(Aliments!$D$6)+G10*N(Aliments!$D$7)+H10*N(Aliments!$D$8)+I10*N(Aliments!$D$9))*(1-Empoissonnement!$G10) -> 17145600 | N10: =(D10*N(Aliments!$D$4)*N(Aliments!$F$4)+E10*N(Aliments!$D$5)*N(Aliments!$F$5)+F10*N(Aliments!$D$6)*N(Aliments!$F$6)+G10*N(Aliments!$D$7)*N(Aliments!$F$7)+H10*N(Aliments!$D$8)*N(Aliments!$F$8)+I10*N(Aliments!$D$9)*N(Aliments!$F$9))*(1-Empoissonnement!$G10) -> 2461860 | O10: =(D10*N(Aliments!$D$4)*N(Aliments!$G$4)+E10*N(Aliments!$D$5)*N(Aliments!$G$5)+F10*N(Aliments!$D$6)*N(Aliments!$G$6)+G10*N(Aliments!$D$7)*N(Aliments!$G$7)+H10*N(Aliments!$D$8)*N(Aliments!$G$8)+I10*N(Aliments!$D$9)*N(Aliments!$G$9))*(1-Empoissonnement!$G10) -> 8127240 | P10: =(D10*N(Aliments!$D$4)*N(Aliments!$H$4)+E10*N(Aliments!$D$5)*N(Aliments!$H$5)+F10*N(Aliments!$D$6)*N(Aliments!$H$6)+G10*N(Aliments!$D$7)*N(Aliments!$H$7)+H10*N(Aliments!$D$8)*N(Aliments!$H$8)+I10*N(Aliments!$D$9)*N(Aliments!$H$9))*(1-Empoissonnement!$G10) -> 6556500 | Q10: =D10*N(Aliments!$C$4)*N(Aliments!$F$4)+E10*N(Aliments!$C$5)*N(Aliments!$F$5)+F10*N(Aliments!$C$6)*N(Aliments!$F$6)+G10*N(Aliments!$C$7)*N(Aliments!$F$7)+H10*N(Aliments!$C$8)*N(Aliments!$F$8)+I10*N(Aliments!$C$9)*N(Aliments!$F$9) -> 2250 | R10: =D10*N(Aliments!$C$4)*N(Aliments!$G$4)+E10*N(Aliments!$C$5)*N(Aliments!$G$5)+F10*N(Aliments!$C$6)*N(Aliments!$G$6)+G10*N(Aliments!$C$7)*N(Aliments!$G$7)+H10*N(Aliments!$C$8)*N(Aliments!$G$8)+I10*N(Aliments!$C$9)*N(Aliments!$G$9) -> 8100 | S10: =D10*N(Aliments!$C$4)*N(Aliments!$H$4)+E10*N(Aliments!$C$5)*N(Aliments!$H$5)+F10*N(Aliments!$C$6)*N(Aliments!$H$6)+G10*N(Aliments!$C$7)*N(Aliments!$H$7)+H10*N(Aliments!$C$8)*N(Aliments!$H$8)+I10*N(Aliments!$C$9)*N(Aliments!$H$9) -> 6750 | T10: =IFERROR(Q10/INDEX('Besoins aliments'!$H$5:$H$25,MATCH(Empoissonnement!$B10,'Besoins aliments'!$A$5:$A$25,0))*INDEX(Dépenses!$B$31:$V$31,MATCH(Empoissonnement!$B10,Dépenses!$B$3:$V$3,0)),0) -> 250000 | U10: =IFERROR(R10/INDEX('Besoins aliments'!$H$5:$H$25,MATCH(EDATE(Empoissonnement!$B10,1),'Besoins aliments'!$A$5:$A$25,0))*INDEX(Dépenses!$B$31:$V$31,MATCH(EDATE(Empoissonnement!$B10,1),Dépenses!$B$3:$V$3,0)),0) -> 792000 | V10: =IFERROR(S10/INDEX('Besoins aliments'!$H$5:$H$25,MATCH(EDATE(Empoissonnement!$B10,2),'Besoins aliments'!$A$5:$A$25,0))*INDEX(Dépenses!$B$31:$V$31,MATCH(EDATE(Empoissonnement!$B10,2),Dépenses!$B$3:$V$3,0)),0) -> 633552.63 | W10: =T10+U10+V10 -> 1675552.6
A11: =Empoissonnement!A11 -> V8 | B11: =Empoissonnement!B11 -> 46447 | C11: =Empoissonnement!C11 -> 15 | D11: =ROUNDUP(Empoissonnement!C11*N(Aliments!$J$4),0) -> 120 | E11: =ROUNDUP(Empoissonnement!C11*N(Aliments!$J$5),0) -> 270 | F11: =ROUNDUP(Empoissonnement!C11*N(Aliments!$J$6),0) -> 750 | G11: =ROUNDUP(Empoissonnement!C11*N(Aliments!$J$7),0) -> 0 | H11: =ROUNDUP(Empoissonnement!C11*N(Aliments!$J$8),0) -> 0 | I11: =ROUNDUP(Empoissonnement!C11*N(Aliments!$J$9),0) -> 0 | J11: =SUM(D11:I11) -> 1140 | K11: =D11*N(Aliments!$C$4)+E11*N(Aliments!$C$5)+F11*N(Aliments!$C$6)+G11*N(Aliments!$C$7)+H11*N(Aliments!$C$8)+I11*N(Aliments!$C$9) -> 17100 | L11: =(D11*N(Aliments!$D$4)+E11*N(Aliments!$D$5)+F11*N(Aliments!$D$6)+G11*N(Aliments!$D$7)+H11*N(Aliments!$D$8)+I11*N(Aliments!$D$9))*(1-Empoissonnement!$G11) -> 17145600 | N11: =(D11*N(Aliments!$D$4)*N(Aliments!$F$4)+E11*N(Aliments!$D$5)*N(Aliments!$F$5)+F11*N(Aliments!$D$6)*N(Aliments!$F$6)+G11*N(Aliments!$D$7)*N(Aliments!$F$7)+H11*N(Aliments!$D$8)*N(Aliments!$F$8)+I11*N(Aliments!$D$9)*N(Aliments!$F$9))*(1-Empoissonnement!$G11) -> 2461860 | O11: =(D11*N(Aliments!$D$4)*N(Aliments!$G$4)+E11*N(Aliments!$D$5)*N(Aliments!$G$5)+F11*N(Aliments!$D$6)*N(Aliments!$G$6)+G11*N(Aliments!$D$7)*N(Aliments!$G$7)+H11*N(Aliments!$D$8)*N(Aliments!$G$8)+I11*N(Aliments!$D$9)*N(Aliments!$G$9))*(1-Empoissonnement!$G11) -> 8127240 | P11: =(D11*N(Aliments!$D$4)*N(Aliments!$H$4)+E11*N(Aliments!$D$5)*N(Aliments!$H$5)+F11*N(Aliments!$D$6)*N(Aliments!$H$6)+G11*N(Aliments!$D$7)*N(Aliments!$H$7)+H11*N(Aliments!$D$8)*N(Aliments!$H$8)+I11*N(Aliments!$D$9)*N(Aliments!$H$9))*(1-Empoissonnement!$G11) -> 6556500 | Q11: =D11*N(Aliments!$C$4)*N(Aliments!$F$4)+E11*N(Aliments!$C$5)*N(Aliments!$F$5)+F11*N(Aliments!$C$6)*N(Aliments!$F$6)+G11*N(Aliments!$C$7)*N(Aliments!$F$7)+H11*N(Aliments!$C$8)*N(Aliments!$F$8)+I11*N(Aliments!$C$9)*N(Aliments!$F$9) -> 2250 | R11: =D11*N(Aliments!$C$4)*N(Aliments!$G$4)+E11*N(Aliments!$C$5)*N(Aliments!$G$5)+F11*N(Aliments!$C$6)*N(Aliments!$G$6)+G11*N(Aliments!$C$7)*N(Aliments!$G$7)+H11*N(Aliments!$C$8)*N(Aliments!$G$8)+I11*N(Aliments!$C$9)*N(Aliments!$G$9) -> 8100 | S11: =D11*N(Aliments!$C$4)*N(Aliments!$H$4)+E11*N(Aliments!$C$5)*N(Aliments!$H$5)+F11*N(Aliments!$C$6)*N(Aliments!$H$6)+G11*N(Aliments!$C$7)*N(Aliments!$H$7)+H11*N(Aliments!$C$8)*N(Aliments!$H$8)+I11*N(Aliments!$C$9)*N(Aliments!$H$9) -> 6750 | T11: =IFERROR(Q11/INDEX('Besoins aliments'!$H$5:$H$25,MATCH(Empoissonnement!$B11,'Besoins aliments'!$A$5:$A$25,0))*INDEX(Dépenses!$B$31:$V$31,MATCH(Empoissonnement!$B11,Dépenses!$B$3:$V$3,0)),0) -> 220000 | U11: =IFERROR(R11/INDEX('Besoins aliments'!$H$5:$H$25,MATCH(EDATE(Empoissonnement!$B11,1),'Besoins aliments'!$A$5:$A$25,0))*INDEX(Dépenses!$B$31:$V$31,MATCH(EDATE(Empoissonnement!$B11,1),Dépenses!$B$3:$V$3,0)),0) -> 760263.16 | V11: =IFERROR(S11/INDEX('Besoins aliments'!$H$5:$H$25,MATCH(EDATE(Empoissonnement!$B11,2),'Besoins aliments'!$A$5:$A$25,0))*INDEX(Dépenses!$B$31:$V$31,MATCH(EDATE(Empoissonnement!$B11,2),Dépenses!$B$3:$V$3,0)),0) -> 633552.63 | W11: =T11+U11+V11 -> 1613815.8
A12: =Empoissonnement!A12 -> V9 | B12: =Empoissonnement!B12 -> 46478 | C12: =Empoissonnement!C12 -> 15 | D12: =ROUNDUP(Empoissonnement!C12*N(Aliments!$J$4),0) -> 120 | E12: =ROUNDUP(Empoissonnement!C12*N(Aliments!$J$5),0) -> 270 | F12: =ROUNDUP(Empoissonnement!C12*N(Aliments!$J$6),0) -> 750 | G12: =ROUNDUP(Empoissonnement!C12*N(Aliments!$J$7),0) -> 0 | H12: =ROUNDUP(Empoissonnement!C12*N(Aliments!$J$8),0) -> 0 | I12: =ROUNDUP(Empoissonnement!C12*N(Aliments!$J$9),0) -> 0 | J12: =SUM(D12:I12) -> 1140 | K12: =D12*N(Aliments!$C$4)+E12*N(Aliments!$C$5)+F12*N(Aliments!$C$6)+G12*N(Aliments!$C$7)+H12*N(Aliments!$C$8)+I12*N(Aliments!$C$9) -> 17100 | L12: =(D12*N(Aliments!$D$4)+E12*N(Aliments!$D$5)+F12*N(Aliments!$D$6)+G12*N(Aliments!$D$7)+H12*N(Aliments!$D$8)+I12*N(Aliments!$D$9))*(1-Empoissonnement!$G12) -> 17145600 | N12: =(D12*N(Aliments!$D$4)*N(Aliments!$F$4)+E12*N(Aliments!$D$5)*N(Aliments!$F$5)+F12*N(Aliments!$D$6)*N(Aliments!$F$6)+G12*N(Aliments!$D$7)*N(Aliments!$F$7)+H12*N(Aliments!$D$8)*N(Aliments!$F$8)+I12*N(Aliments!$D$9)*N(Aliments!$F$9))*(1-Empoissonnement!$G12) -> 2461860 | O12: =(D12*N(Aliments!$D$4)*N(Aliments!$G$4)+E12*N(Aliments!$D$5)*N(Aliments!$G$5)+F12*N(Aliments!$D$6)*N(Aliments!$G$6)+G12*N(Aliments!$D$7)*N(Aliments!$G$7)+H12*N(Aliments!$D$8)*N(Aliments!$G$8)+I12*N(Aliments!$D$9)*N(Aliments!$G$9))*(1-Empoissonnement!$G12) -> 8127240 | P12: =(D12*N(Aliments!$D$4)*N(Aliments!$H$4)+E12*N(Aliments!$D$5)*N(Aliments!$H$5)+F12*N(Aliments!$D$6)*N(Aliments!$H$6)+G12*N(Aliments!$D$7)*N(Aliments!$H$7)+H12*N(Aliments!$D$8)*N(Aliments!$H$8)+I12*N(Aliments!$D$9)*N(Aliments!$H$9))*(1-Empoissonnement!$G12) -> 6556500 | Q12: =D12*N(Aliments!$C$4)*N(Aliments!$F$4)+E12*N(Aliments!$C$5)*N(Aliments!$F$5)+F12*N(Aliments!$C$6)*N(Aliments!$F$6)+G12*N(Aliments!$C$7)*N(Aliments!$F$7)+H12*N(Aliments!$C$8)*N(Aliments!$F$8)+I12*N(Aliments!$C$9)*N(Aliments!$F$9) -> 2250 | R12: =D12*N(Aliments!$C$4)*N(Aliments!$G$4)+E12*N(Aliments!$C$5)*N(Aliments!$G$5)+F12*N(Aliments!$C$6)*N(Aliments!$G$6)+G12*N(Aliments!$C$7)*N(Aliments!$G$7)+H12*N(Aliments!$C$8)*N(Aliments!$G$8)+I12*N(Aliments!$C$9)*N(Aliments!$G$9) -> 8100 | S12: =D12*N(Aliments!$C$4)*N(Aliments!$H$4)+E12*N(Aliments!$C$5)*N(Aliments!$H$5)+F12*N(Aliments!$C$6)*N(Aliments!$H$6)+G12*N(Aliments!$C$7)*N(Aliments!$H$7)+H12*N(Aliments!$C$8)*N(Aliments!$H$8)+I12*N(Aliments!$C$9)*N(Aliments!$H$9) -> 6750 | T12: =IFERROR(Q12/INDEX('Besoins aliments'!$H$5:$H$25,MATCH(Empoissonnement!$B12,'Besoins aliments'!$A$5:$A$25,0))*INDEX(Dépenses!$B$31:$V$31,MATCH(Empoissonnement!$B12,Dépenses!$B$3:$V$3,0)),0) -> 211184.21 | U12: =IFERROR(R12/INDEX('Besoins aliments'!$H$5:$H$25,MATCH(EDATE(Empoissonnement!$B12,1),'Besoins aliments'!$A$5:$A$25,0))*INDEX(Dépenses!$B$31:$V$31,MATCH(EDATE(Empoissonnement!$B12,1),Dépenses!$B$3:$V$3,0)),0) -> 760263.16 | V12: =IFERROR(S12/INDEX('Besoins aliments'!$H$5:$H$25,MATCH(EDATE(Empoissonnement!$B12,2),'Besoins aliments'!$A$5:$A$25,0))*INDEX(Dépenses!$B$31:$V$31,MATCH(EDATE(Empoissonnement!$B12,2),Dépenses!$B$3:$V$3,0)),0) -> 633552.63 | W12: =T12+U12+V12 -> 1605000
A13: =Empoissonnement!A13 -> V10 | B13: =Empoissonnement!B13 -> 46508 | C13: =Empoissonnement!C13 -> 15 | D13: =ROUNDUP(Empoissonnement!C13*N(Aliments!$J$4),0) -> 120 | E13: =ROUNDUP(Empoissonnement!C13*N(Aliments!$J$5),0) -> 270 | F13: =ROUNDUP(Empoissonnement!C13*N(Aliments!$J$6),0) -> 750 | G13: =ROUNDUP(Empoissonnement!C13*N(Aliments!$J$7),0) -> 0 | H13: =ROUNDUP(Empoissonnement!C13*N(Aliments!$J$8),0) -> 0 | I13: =ROUNDUP(Empoissonnement!C13*N(Aliments!$J$9),0) -> 0 | J13: =SUM(D13:I13) -> 1140 | K13: =D13*N(Aliments!$C$4)+E13*N(Aliments!$C$5)+F13*N(Aliments!$C$6)+G13*N(Aliments!$C$7)+H13*N(Aliments!$C$8)+I13*N(Aliments!$C$9) -> 17100 | L13: =(D13*N(Aliments!$D$4)+E13*N(Aliments!$D$5)+F13*N(Aliments!$D$6)+G13*N(Aliments!$D$7)+H13*N(Aliments!$D$8)+I13*N(Aliments!$D$9))*(1-Empoissonnement!$G13) -> 17145600 | N13: =(D13*N(Aliments!$D$4)*N(Aliments!$F$4)+E13*N(Aliments!$D$5)*N(Aliments!$F$5)+F13*N(Aliments!$D$6)*N(Aliments!$F$6)+G13*N(Aliments!$D$7)*N(Aliments!$F$7)+H13*N(Aliments!$D$8)*N(Aliments!$F$8)+I13*N(Aliments!$D$9)*N(Aliments!$F$9))*(1-Empoissonnement!$G13) -> 2461860 | O13: =(D13*N(Aliments!$D$4)*N(Aliments!$G$4)+E13*N(Aliments!$D$5)*N(Aliments!$G$5)+F13*N(Aliments!$D$6)*N(Aliments!$G$6)+G13*N(Aliments!$D$7)*N(Aliments!$G$7)+H13*N(Aliments!$D$8)*N(Aliments!$G$8)+I13*N(Aliments!$D$9)*N(Aliments!$G$9))*(1-Empoissonnement!$G13) -> 8127240 | P13: =(D13*N(Aliments!$D$4)*N(Aliments!$H$4)+E13*N(Aliments!$D$5)*N(Aliments!$H$5)+F13*N(Aliments!$D$6)*N(Aliments!$H$6)+G13*N(Aliments!$D$7)*N(Aliments!$H$7)+H13*N(Aliments!$D$8)*N(Aliments!$H$8)+I13*N(Aliments!$D$9)*N(Aliments!$H$9))*(1-Empoissonnement!$G13) -> 6556500 | Q13: =D13*N(Aliments!$C$4)*N(Aliments!$F$4)+E13*N(Aliments!$C$5)*N(Aliments!$F$5)+F13*N(Aliments!$C$6)*N(Aliments!$F$6)+G13*N(Aliments!$C$7)*N(Aliments!$F$7)+H13*N(Aliments!$C$8)*N(Aliments!$F$8)+I13*N(Aliments!$C$9)*N(Aliments!$F$9) -> 2250 | R13: =D13*N(Aliments!$C$4)*N(Aliments!$G$4)+E13*N(Aliments!$C$5)*N(Aliments!$G$5)+F13*N(Aliments!$C$6)*N(Aliments!$G$6)+G13*N(Aliments!$C$7)*N(Aliments!$G$7)+H13*N(Aliments!$C$8)*N(Aliments!$G$8)+I13*N(Aliments!$C$9)*N(Aliments!$G$9) -> 8100 | S13: =D13*N(Aliments!$C$4)*N(Aliments!$H$4)+E13*N(Aliments!$C$5)*N(Aliments!$H$5)+F13*N(Aliments!$C$6)*N(Aliments!$H$6)+G13*N(Aliments!$C$7)*N(Aliments!$H$7)+H13*N(Aliments!$C$8)*N(Aliments!$H$8)+I13*N(Aliments!$C$9)*N(Aliments!$H$9) -> 6750 | T13: =IFERROR(Q13/INDEX('Besoins aliments'!$H$5:$H$25,MATCH(Empoissonnement!$B13,'Besoins aliments'!$A$5:$A$25,0))*INDEX(Dépenses!$B$31:$V$31,MATCH(Empoissonnement!$B13,Dépenses!$B$3:$V$3,0)),0) -> 211184.21 | U13: =IFERROR(R13/INDEX('Besoins aliments'!$H$5:$H$25,MATCH(EDATE(Empoissonnement!$B13,1),'Besoins aliments'!$A$5:$A$25,0))*INDEX(Dépenses!$B$31:$V$31,MATCH(EDATE(Empoissonnement!$B13,1),Dépenses!$B$3:$V$3,0)),0) -> 760263.16 | V13: =IFERROR(S13/INDEX('Besoins aliments'!$H$5:$H$25,MATCH(EDATE(Empoissonnement!$B13,2),'Besoins aliments'!$A$5:$A$25,0))*INDEX(Dépenses!$B$31:$V$31,MATCH(EDATE(Empoissonnement!$B13,2),Dépenses!$B$3:$V$3,0)),0) -> 633552.63 | W13: =T13+U13+V13 -> 1605000
A14: =Empoissonnement!A14 -> V11 | B14: =Empoissonnement!B14 -> 46539 | C14: =Empoissonnement!C14 -> 15 | D14: =ROUNDUP(Empoissonnement!C14*N(Aliments!$J$4),0) -> 120 | E14: =ROUNDUP(Empoissonnement!C14*N(Aliments!$J$5),0) -> 270 | F14: =ROUNDUP(Empoissonnement!C14*N(Aliments!$J$6),0) -> 750 | G14: =ROUNDUP(Empoissonnement!C14*N(Aliments!$J$7),0) -> 0 | H14: =ROUNDUP(Empoissonnement!C14*N(Aliments!$J$8),0) -> 0 | I14: =ROUNDUP(Empoissonnement!C14*N(Aliments!$J$9),0) -> 0 | J14: =SUM(D14:I14) -> 1140 | K14: =D14*N(Aliments!$C$4)+E14*N(Aliments!$C$5)+F14*N(Aliments!$C$6)+G14*N(Aliments!$C$7)+H14*N(Aliments!$C$8)+I14*N(Aliments!$C$9) -> 17100 | L14: =(D14*N(Aliments!$D$4)+E14*N(Aliments!$D$5)+F14*N(Aliments!$D$6)+G14*N(Aliments!$D$7)+H14*N(Aliments!$D$8)+I14*N(Aliments!$D$9))*(1-Empoissonnement!$G14) -> 17145600 | N14: =(D14*N(Aliments!$D$4)*N(Aliments!$F$4)+E14*N(Aliments!$D$5)*N(Aliments!$F$5)+F14*N(Aliments!$D$6)*N(Aliments!$F$6)+G14*N(Aliments!$D$7)*N(Aliments!$F$7)+H14*N(Aliments!$D$8)*N(Aliments!$F$8)+I14*N(Aliments!$D$9)*N(Aliments!$F$9))*(1-Empoissonnement!$G14) -> 2461860 | O14: =(D14*N(Aliments!$D$4)*N(Aliments!$G$4)+E14*N(Aliments!$D$5)*N(Aliments!$G$5)+F14*N(Aliments!$D$6)*N(Aliments!$G$6)+G14*N(Aliments!$D$7)*N(Aliments!$G$7)+H14*N(Aliments!$D$8)*N(Aliments!$G$8)+I14*N(Aliments!$D$9)*N(Aliments!$G$9))*(1-Empoissonnement!$G14) -> 8127240 | P14: =(D14*N(Aliments!$D$4)*N(Aliments!$H$4)+E14*N(Aliments!$D$5)*N(Aliments!$H$5)+F14*N(Aliments!$D$6)*N(Aliments!$H$6)+G14*N(Aliments!$D$7)*N(Aliments!$H$7)+H14*N(Aliments!$D$8)*N(Aliments!$H$8)+I14*N(Aliments!$D$9)*N(Aliments!$H$9))*(1-Empoissonnement!$G14) -> 6556500 | Q14: =D14*N(Aliments!$C$4)*N(Aliments!$F$4)+E14*N(Aliments!$C$5)*N(Aliments!$F$5)+F14*N(Aliments!$C$6)*N(Aliments!$F$6)+G14*N(Aliments!$C$7)*N(Aliments!$F$7)+H14*N(Aliments!$C$8)*N(Aliments!$F$8)+I14*N(Aliments!$C$9)*N(Aliments!$F$9) -> 2250 | R14: =D14*N(Aliments!$C$4)*N(Aliments!$G$4)+E14*N(Aliments!$C$5)*N(Aliments!$G$5)+F14*N(Aliments!$C$6)*N(Aliments!$G$6)+G14*N(Aliments!$C$7)*N(Aliments!$G$7)+H14*N(Aliments!$C$8)*N(Aliments!$G$8)+I14*N(Aliments!$C$9)*N(Aliments!$G$9) -> 8100 | S14: =D14*N(Aliments!$C$4)*N(Aliments!$H$4)+E14*N(Aliments!$C$5)*N(Aliments!$H$5)+F14*N(Aliments!$C$6)*N(Aliments!$H$6)+G14*N(Aliments!$C$7)*N(Aliments!$H$7)+H14*N(Aliments!$C$8)*N(Aliments!$H$8)+I14*N(Aliments!$C$9)*N(Aliments!$H$9) -> 6750 | T14: =IFERROR(Q14/INDEX('Besoins aliments'!$H$5:$H$25,MATCH(Empoissonnement!$B14,'Besoins aliments'!$A$5:$A$25,0))*INDEX(Dépenses!$B$31:$V$31,MATCH(Empoissonnement!$B14,Dépenses!$B$3:$V$3,0)),0) -> 211184.21 | U14: =IFERROR(R14/INDEX('Besoins aliments'!$H$5:$H$25,MATCH(EDATE(Empoissonnement!$B14,1),'Besoins aliments'!$A$5:$A$25,0))*INDEX(Dépenses!$B$31:$V$31,MATCH(EDATE(Empoissonnement!$B14,1),Dépenses!$B$3:$V$3,0)),0) -> 760263.16 | V14: =IFERROR(S14/INDEX('Besoins aliments'!$H$5:$H$25,MATCH(EDATE(Empoissonnement!$B14,2),'Besoins aliments'!$A$5:$A$25,0))*INDEX(Dépenses!$B$31:$V$31,MATCH(EDATE(Empoissonnement!$B14,2),Dépenses!$B$3:$V$3,0)),0) -> 633552.63 | W14: =T14+U14+V14 -> 1605000
A15: =Empoissonnement!A15 -> V12 | B15: =Empoissonnement!B15 -> 46569 | C15: =Empoissonnement!C15 -> 15 | D15: =ROUNDUP(Empoissonnement!C15*N(Aliments!$J$4),0) -> 120 | E15: =ROUNDUP(Empoissonnement!C15*N(Aliments!$J$5),0) -> 270 | F15: =ROUNDUP(Empoissonnement!C15*N(Aliments!$J$6),0) -> 750 | G15: =ROUNDUP(Empoissonnement!C15*N(Aliments!$J$7),0) -> 0 | H15: =ROUNDUP(Empoissonnement!C15*N(Aliments!$J$8),0) -> 0 | I15: =ROUNDUP(Empoissonnement!C15*N(Aliments!$J$9),0) -> 0 | J15: =SUM(D15:I15) -> 1140 | K15: =D15*N(Aliments!$C$4)+E15*N(Aliments!$C$5)+F15*N(Aliments!$C$6)+G15*N(Aliments!$C$7)+H15*N(Aliments!$C$8)+I15*N(Aliments!$C$9) -> 17100 | L15: =(D15*N(Aliments!$D$4)+E15*N(Aliments!$D$5)+F15*N(Aliments!$D$6)+G15*N(Aliments!$D$7)+H15*N(Aliments!$D$8)+I15*N(Aliments!$D$9))*(1-Empoissonnement!$G15) -> 17145600 | N15: =(D15*N(Aliments!$D$4)*N(Aliments!$F$4)+E15*N(Aliments!$D$5)*N(Aliments!$F$5)+F15*N(Aliments!$D$6)*N(Aliments!$F$6)+G15*N(Aliments!$D$7)*N(Aliments!$F$7)+H15*N(Aliments!$D$8)*N(Aliments!$F$8)+I15*N(Aliments!$D$9)*N(Aliments!$F$9))*(1-Empoissonnement!$G15) -> 2461860 | O15: =(D15*N(Aliments!$D$4)*N(Aliments!$G$4)+E15*N(Aliments!$D$5)*N(Aliments!$G$5)+F15*N(Aliments!$D$6)*N(Aliments!$G$6)+G15*N(Aliments!$D$7)*N(Aliments!$G$7)+H15*N(Aliments!$D$8)*N(Aliments!$G$8)+I15*N(Aliments!$D$9)*N(Aliments!$G$9))*(1-Empoissonnement!$G15) -> 8127240 | P15: =(D15*N(Aliments!$D$4)*N(Aliments!$H$4)+E15*N(Aliments!$D$5)*N(Aliments!$H$5)+F15*N(Aliments!$D$6)*N(Aliments!$H$6)+G15*N(Aliments!$D$7)*N(Aliments!$H$7)+H15*N(Aliments!$D$8)*N(Aliments!$H$8)+I15*N(Aliments!$D$9)*N(Aliments!$H$9))*(1-Empoissonnement!$G15) -> 6556500 | Q15: =D15*N(Aliments!$C$4)*N(Aliments!$F$4)+E15*N(Aliments!$C$5)*N(Aliments!$F$5)+F15*N(Aliments!$C$6)*N(Aliments!$F$6)+G15*N(Aliments!$C$7)*N(Aliments!$F$7)+H15*N(Aliments!$C$8)*N(Aliments!$F$8)+I15*N(Aliments!$C$9)*N(Aliments!$F$9) -> 2250 | R15: =D15*N(Aliments!$C$4)*N(Aliments!$G$4)+E15*N(Aliments!$C$5)*N(Aliments!$G$5)+F15*N(Aliments!$C$6)*N(Aliments!$G$6)+G15*N(Aliments!$C$7)*N(Aliments!$G$7)+H15*N(Aliments!$C$8)*N(Aliments!$G$8)+I15*N(Aliments!$C$9)*N(Aliments!$G$9) -> 8100 | S15: =D15*N(Aliments!$C$4)*N(Aliments!$H$4)+E15*N(Aliments!$C$5)*N(Aliments!$H$5)+F15*N(Aliments!$C$6)*N(Aliments!$H$6)+G15*N(Aliments!$C$7)*N(Aliments!$H$7)+H15*N(Aliments!$C$8)*N(Aliments!$H$8)+I15*N(Aliments!$C$9)*N(Aliments!$H$9) -> 6750 | T15: =IFERROR(Q15/INDEX('Besoins aliments'!$H$5:$H$25,MATCH(Empoissonnement!$B15,'Besoins aliments'!$A$5:$A$25,0))*INDEX(Dépenses!$B$31:$V$31,MATCH(Empoissonnement!$B15,Dépenses!$B$3:$V$3,0)),0) -> 211184.21 | U15: =IFERROR(R15/INDEX('Besoins aliments'!$H$5:$H$25,MATCH(EDATE(Empoissonnement!$B15,1),'Besoins aliments'!$A$5:$A$25,0))*INDEX(Dépenses!$B$31:$V$31,MATCH(EDATE(Empoissonnement!$B15,1),Dépenses!$B$3:$V$3,0)),0) -> 760263.16 | V15: =IFERROR(S15/INDEX('Besoins aliments'!$H$5:$H$25,MATCH(EDATE(Empoissonnement!$B15,2),'Besoins aliments'!$A$5:$A$25,0))*INDEX(Dépenses!$B$31:$V$31,MATCH(EDATE(Empoissonnement!$B15,2),Dépenses!$B$3:$V$3,0)),0) -> 633552.63 | W15: =T15+U15+V15 -> 1605000
... A22: =Empoissonnement!A22 -> V19 | B22: =Empoissonnement!B22 -> 46784 | C22: =Empoissonnement!C22 -> 15 | D22: =ROUNDUP(Empoissonnement!C22*N(Aliments!$J$4),0) -> 120 | E22: =ROUNDUP(Empoissonnement!C22*N(Aliments!$J$5),0) -> 270 | F22: =ROUNDUP(Empoissonnement!C22*N(Aliments!$J$6),0) -> 750 | G22: =ROUNDUP(Empoissonnement!C22*N(Aliments!$J$7),0) -> 0 | H22: =ROUNDUP(Empoissonnement!C22*N(Aliments!$J$8),0) -> 0 | I22: =ROUNDUP(Empoissonnement!C22*N(Aliments!$J$9),0) -> 0 | J22: =SUM(D22:I22) -> 1140 | K22: =D22*N(Aliments!$C$4)+E22*N(Aliments!$C$5)+F22*N(Aliments!$C$6)+G22*N(Aliments!$C$7)+H22*N(Aliments!$C$8)+I22*N(Aliments!$C$9) -> 17100 | L22: =(D22*N(Aliments!$D$4)+E22*N(Aliments!$D$5)+F22*N(Aliments!$D$6)+G22*N(Aliments!$D$7)+H22*N(Aliments!$D$8)+I22*N(Aliments!$D$9))*(1-Empoissonnement!$G22) -> 17145600 | N22: =(D22*N(Aliments!$D$4)*N(Aliments!$F$4)+E22*N(Aliments!$D$5)*N(Aliments!$F$5)+F22*N(Aliments!$D$6)*N(Aliments!$F$6)+G22*N(Aliments!$D$7)*N(Aliments!$F$7)+H22*N(Aliments!$D$8)*N(Aliments!$F$8)+I22*N(Aliments!$D$9)*N(Aliments!$F$9))*(1-Empoissonnement!$G22) -> 2461860 | O22: =(D22*N(Aliments!$D$4)*N(Aliments!$G$4)+E22*N(Aliments!$D$5)*N(Aliments!$G$5)+F22*N(Aliments!$D$6)*N(Aliments!$G$6)+G22*N(Aliments!$D$7)*N(Aliments!$G$7)+H22*N(Aliments!$D$8)*N(Aliments!$G$8)+I22*N(Aliments!$D$9)*N(Aliments!$G$9))*(1-Empoissonnement!$G22) -> 8127240 | P22: =(D22*N(Aliments!$D$4)*N(Aliments!$H$4)+E22*N(Aliments!$D$5)*N(Aliments!$H$5)+F22*N(Aliments!$D$6)*N(Aliments!$H$6)+G22*N(Aliments!$D$7)*N(Aliments!$H$7)+H22*N(Aliments!$D$8)*N(Aliments!$H$8)+I22*N(Aliments!$D$9)*N(Aliments!$H$9))*(1-Empoissonnement!$G22) -> 6556500 | Q22: =D22*N(Aliments!$C$4)*N(Aliments!$F$4)+E22*N(Aliments!$C$5)*N(Aliments!$F$5)+F22*N(Aliments!$C$6)*N(Aliments!$F$6)+G22*N(Aliments!$C$7)*N(Aliments!$F$7)+H22*N(Aliments!$C$8)*N(Aliments!$F$8)+I22*N(Aliments!$C$9)*N(Aliments!$F$9) -> 2250 | R22: =D22*N(Aliments!$C$4)*N(Aliments!$G$4)+E22*N(Aliments!$C$5)*N(Aliments!$G$5)+F22*N(Aliments!$C$6)*N(Aliments!$G$6)+G22*N(Aliments!$C$7)*N(Aliments!$G$7)+H22*N(Aliments!$C$8)*N(Aliments!$G$8)+I22*N(Aliments!$C$9)*N(Aliments!$G$9) -> 8100 | S22: =D22*N(Aliments!$C$4)*N(Aliments!$H$4)+E22*N(Aliments!$C$5)*N(Aliments!$H$5)+F22*N(Aliments!$C$6)*N(Aliments!$H$6)+G22*N(Aliments!$C$7)*N(Aliments!$H$7)+H22*N(Aliments!$C$8)*N(Aliments!$H$8)+I22*N(Aliments!$C$9)*N(Aliments!$H$9) -> 6750 | T22: =IFERROR(Q22/INDEX('Besoins aliments'!$H$5:$H$25,MATCH(Empoissonnement!$B22,'Besoins aliments'!$A$5:$A$25,0))*INDEX(Dépenses!$B$31:$V$31,MATCH(Empoissonnement!$B22,Dépenses!$B$3:$V$3,0)),0) -> 211184.21 | U22: =IFERROR(R22/INDEX('Besoins aliments'!$H$5:$H$25,MATCH(EDATE(Empoissonnement!$B22,1),'Besoins aliments'!$A$5:$A$25,0))*INDEX(Dépenses!$B$31:$V$31,MATCH(EDATE(Empoissonnement!$B22,1),Dépenses!$B$3:$V$3,0)),0) -> 810000 | V22: =IFERROR(S22/INDEX('Besoins aliments'!$H$5:$H$25,MATCH(EDATE(Empoissonnement!$B22,2),'Besoins aliments'!$A$5:$A$25,0))*INDEX(Dépenses!$B$31:$V$31,MATCH(EDATE(Empoissonnement!$B22,2),Dépenses!$B$3:$V$3,0)),0) -> 1350000 | W22: =T22+U22+V22 -> 2371184.2
A23: TOTAL | D23: =SUM(D4:D22) -> 1928 | E23: =SUM(E4:E22) -> 4338 | F23: =SUM(F4:F22) -> 12050 | G23: =SUM(G4:G22) -> 0 | H23: =SUM(H4:H22) -> 0 | I23: =SUM(I4:I22) -> 0 | J23: =SUM(J4:J22) -> 18316 | K23: =SUM(K4:K22) -> 274740 | L23: =SUM(L4:L22) -> 277369600 | N23: =SUM(N4:N22) -> 39826260 | O23: =SUM(O4:O22) -> 131476840 | P23: =SUM(P4:P22) -> 106066500

Sheet Besoins aliments
A1: BESOINS EN ALIMENTS PAR MOIS ET PAR GRANULOMÉTRIE
A2: Détail par granulomètrie, calculé à partir de VOTRE saisie de la feuille « Aliment par vague », répartie entre granulométries selon la feuille Aliments. Le coût d'achat est au prix catalogue (avant remise fournisseur) ; la dépense réelle, remise déduite, est calculée dans les Prévisions.
B3: Quantités à prévoir (kg) | I3: Sacs à commander (nb)
A4: Mois | B4: =Aliments!$A$4 -> 2 mm | C4: =Aliments!$A$5 -> 3 mm | D4: =Aliments!$A$6 -> 4 mm | E4: =Aliments!$A$7 -> 0 | F4: =Aliments!$A$8 -> 0 | G4: =Aliments!$A$9 -> 0 | H4: TOTAL (kg) | I4: =Aliments!$A$4 -> 2 mm | J4: =Aliments!$A$5 -> 3 mm | K4: =Aliments!$A$6 -> 4 mm | L4: =Aliments!$A$7 -> 0 | M4: =Aliments!$A$8 -> 0 | N4: =Aliments!$A$9 -> 0 | O4: Coût d'achat du mois (FCFA)
A5: 46235 | B5: =N(Aliments!$C$4)*(N(Aliments!$F$4)*SUMIFS('Aliment par vague'!$D$4:$D$22,Empoissonnement!$B$4:$B$22,$A5)+N(Aliments!$G$4)*SUMIFS('Aliment par vague'!$D$4:$D$22,Empoissonnement!$B$4:$B$22,$Q5)+N(Aliments!$H$4)*SUMIFS('Aliment par vague'!$D$4:$D$22,Empoissonnement!$B$4:$B$22,$R5)) -> 384 | C5: =N(Aliments!$C$5)*(N(Aliments!$F$5)*SUMIFS('Aliment par vague'!$E$4:$E$22,Empoissonnement!$B$4:$B$22,$A5)+N(Aliments!$G$5)*SUMIFS('Aliment par vague'!$E$4:$E$22,Empoissonnement!$B$4:$B$22,$Q5)+N(Aliments!$H$5)*SUMIFS('Aliment par vague'!$E$4:$E$22,Empoissonnement!$B$4:$B$22,$R5)) -> 216 | D5: =N(Aliments!$C$6)*(N(Aliments!$F$6)*SUMIFS('Aliment par vague'!$F$4:$F$22,Empoissonnement!$B$4:$B$22,$A5)+N(Aliments!$G$6)*SUMIFS('Aliment par vague'!$F$4:$F$22,Empoissonnement!$B$4:$B$22,$Q5)+N(Aliments!$H$6)*SUMIFS('Aliment par vague'!$F$4:$F$22,Empoissonnement!$B$4:$B$22,$R5)) -> 0 | E5: =N(Aliments!$C$7)*(N(Aliments!$F$7)*SUMIFS('Aliment par vague'!$G$4:$G$22,Empoissonnement!$B$4:$B$22,$A5)+N(Aliments!$G$7)*SUMIFS('Aliment par vague'!$G$4:$G$22,Empoissonnement!$B$4:$B$22,$Q5)+N(Aliments!$H$7)*SUMIFS('Aliment par vague'!$G$4:$G$22,Empoissonnement!$B$4:$B$22,$R5)) -> 0 | F5: =N(Aliments!$C$8)*(N(Aliments!$F$8)*SUMIFS('Aliment par vague'!$H$4:$H$22,Empoissonnement!$B$4:$B$22,$A5)+N(Aliments!$G$8)*SUMIFS('Aliment par vague'!$H$4:$H$22,Empoissonnement!$B$4:$B$22,$Q5)+N(Aliments!$H$8)*SUMIFS('Aliment par vague'!$H$4:$H$22,Empoissonnement!$B$4:$B$22,$R5)) -> 0 | G5: =N(Aliments!$C$9)*(N(Aliments!$F$9)*SUMIFS('Aliment par vague'!$I$4:$I$22,Empoissonnement!$B$4:$B$22,$A5)+N(Aliments!$G$9)*SUMIFS('Aliment par vague'!$I$4:$I$22,Empoissonnement!$B$4:$B$22,$Q5)+N(Aliments!$H$9)*SUMIFS('Aliment par vague'!$I$4:$I$22,Empoissonnement!$B$4:$B$22,$R5)) -> 0 | H5: =SUM(B5:G5) -> 600 | I5: =IF(Aliments!$C$4=0,0,IF(Aliments!$C$4="",0,ROUNDUP(B5/Aliments!$C$4,0))) -> 26 | J5: =IF(Aliments!$C$5=0,0,IF(Aliments!$C$5="",0,ROUNDUP(C5/Aliments!$C$5,0))) -> 15 | K5: =IF(Aliments!$C$6=0,0,IF(Aliments!$C$6="",0,ROUNDUP(D5/Aliments!$C$6,0))) -> 0 | L5: =IF(Aliments!$C$7=0,0,IF(Aliments!$C$7="",0,ROUNDUP(E5/Aliments!$C$7,0))) -> 0 | M5: =IF(Aliments!$C$8=0,0,IF(Aliments!$C$8="",0,ROUNDUP(F5/Aliments!$C$8,0))) -> 0 | N5: =IF(Aliments!$C$9=0,0,IF(Aliments!$C$9="",0,ROUNDUP(G5/Aliments!$C$9,0))) -> 0 | O5: =B5*Aliments!$E$4+C5*Aliments!$E$5+D5*Aliments!$E$6+E5*Aliments!$E$7+F5*Aliments!$E$8+G5*Aliments!$E$9 -> 698400 | Q5: =EDATE($A5,-1) -> 46204 | R5: =EDATE($A5,-2) -> 46174
A6: 46266 | B6: =N(Aliments!$C$4)*(N(Aliments!$F$4)*SUMIFS('Aliment par vague'!$D$4:$D$22,Empoissonnement!$B$4:$B$22,$A6)+N(Aliments!$G$4)*SUMIFS('Aliment par vague'!$D$4:$D$22,Empoissonnement!$B$4:$B$22,$Q6)+N(Aliments!$H$4)*SUMIFS('Aliment par vague'!$D$4:$D$22,Empoissonnement!$B$4:$B$22,$R6)) -> 480 | C6: =N(Aliments!$C$5)*(N(Aliments!$F$5)*SUMIFS('Aliment par vague'!$E$4:$E$22,Empoissonnement!$B$4:$B$22,$A6)+N(Aliments!$G$5)*SUMIFS('Aliment par vague'!$E$4:$E$22,Empoissonnement!$B$4:$B$22,$Q6)+N(Aliments!$H$5)*SUMIFS('Aliment par vague'!$E$4:$E$22,Empoissonnement!$B$4:$B$22,$R6)) -> 1080 | D6: =N(Aliments!$C$6)*(N(Aliments!$F$6)*SUMIFS('Aliment par vague'!$F$4:$F$22,Empoissonnement!$B$4:$B$22,$A6)+N(Aliments!$G$6)*SUMIFS('Aliment par vague'!$F$4:$F$22,Empoissonnement!$B$4:$B$22,$Q6)+N(Aliments!$H$6)*SUMIFS('Aliment par vague'!$F$4:$F$22,Empoissonnement!$B$4:$B$22,$R6)) -> 1200 | E6: =N(Aliments!$C$7)*(N(Aliments!$F$7)*SUMIFS('Aliment par vague'!$G$4:$G$22,Empoissonnement!$B$4:$B$22,$A6)+N(Aliments!$G$7)*SUMIFS('Aliment par vague'!$G$4:$G$22,Empoissonnement!$B$4:$B$22,$Q6)+N(Aliments!$H$7)*SUMIFS('Aliment par vague'!$G$4:$G$22,Empoissonnement!$B$4:$B$22,$R6)) -> 0 | F6: =N(Aliments!$C$8)*(N(Aliments!$F$8)*SUMIFS('Aliment par vague'!$H$4:$H$22,Empoissonnement!$B$4:$B$22,$A6)+N(Aliments!$G$8)*SUMIFS('Aliment par vague'!$H$4:$H$22,Empoissonnement!$B$4:$B$22,$Q6)+N(Aliments!$H$8)*SUMIFS('Aliment par vague'!$H$4:$H$22,Empoissonnement!$B$4:$B$22,$R6)) -> 0 | G6: =N(Aliments!$C$9)*(N(Aliments!$F$9)*SUMIFS('Aliment par vague'!$I$4:$I$22,Empoissonnement!$B$4:$B$22,$A6)+N(Aliments!$G$9)*SUMIFS('Aliment par vague'!$I$4:$I$22,Empoissonnement!$B$4:$B$22,$Q6)+N(Aliments!$H$9)*SUMIFS('Aliment par vague'!$I$4:$I$22,Empoissonnement!$B$4:$B$22,$R6)) -> 0 | H6: =SUM(B6:G6) -> 2760 | I6: =IF(Aliments!$C$4=0,0,IF(Aliments!$C$4="",0,ROUNDUP(B6/Aliments!$C$4,0))) -> 32 | J6: =IF(Aliments!$C$5=0,0,IF(Aliments!$C$5="",0,ROUNDUP(C6/Aliments!$C$5,0))) -> 72 | K6: =IF(Aliments!$C$6=0,0,IF(Aliments!$C$6="",0,ROUNDUP(D6/Aliments!$C$6,0))) -> 80 | L6: =IF(Aliments!$C$7=0,0,IF(Aliments!$C$7="",0,ROUNDUP(E6/Aliments!$C$7,0))) -> 0 | M6: =IF(Aliments!$C$8=0,0,IF(Aliments!$C$8="",0,ROUNDUP(F6/Aliments!$C$8,0))) -> 0 | N6: =IF(Aliments!$C$9=0,0,IF(Aliments!$C$9="",0,ROUNDUP(G6/Aliments!$C$9,0))) -> 0 | O6: =B6*Aliments!$E$4+C6*Aliments!$E$5+D6*Aliments!$E$6+E6*Aliments!$E$7+F6*Aliments!$E$8+G6*Aliments!$E$9 -> 3004000 | Q6: =EDATE($A6,-1) -> 46235 | R6: =EDATE($A6,-2) -> 46204
A7: 46296 | B7: =N(Aliments!$C$4)*(N(Aliments!$F$4)*SUMIFS('Aliment par vague'!$D$4:$D$22,Empoissonnement!$B$4:$B$22,$A7)+N(Aliments!$G$4)*SUMIFS('Aliment par vague'!$D$4:$D$22,Empoissonnement!$B$4:$B$22,$Q7)+N(Aliments!$H$4)*SUMIFS('Aliment par vague'!$D$4:$D$22,Empoissonnement!$B$4:$B$22,$R7)) -> 864 | C7: =N(Aliments!$C$5)*(N(Aliments!$F$5)*SUMIFS('Aliment par vague'!$E$4:$E$22,Empoissonnement!$B$4:$B$22,$A7)+N(Aliments!$G$5)*SUMIFS('Aliment par vague'!$E$4:$E$22,Empoissonnement!$B$4:$B$22,$Q7)+N(Aliments!$H$5)*SUMIFS('Aliment par vague'!$E$4:$E$22,Empoissonnement!$B$4:$B$22,$R7)) -> 1296 | D7: =N(Aliments!$C$6)*(N(Aliments!$F$6)*SUMIFS('Aliment par vague'!$F$4:$F$22,Empoissonnement!$B$4:$B$22,$A7)+N(Aliments!$G$6)*SUMIFS('Aliment par vague'!$F$4:$F$22,Empoissonnement!$B$4:$B$22,$Q7)+N(Aliments!$H$6)*SUMIFS('Aliment par vague'!$F$4:$F$22,Empoissonnement!$B$4:$B$22,$R7)) -> 3000 | E7: =N(Aliments!$C$7)*(N(Aliments!$F$7)*SUMIFS('Aliment par vague'!$G$4:$G$22,Empoissonnement!$B$4:$B$22,$A7)+N(Aliments!$G$7)*SUMIFS('Aliment par vague'!$G$4:$G$22,Empoissonnement!$B$4:$B$22,$Q7)+N(Aliments!$H$7)*SUMIFS('Aliment par vague'!$G$4:$G$22,Empoissonnement!$B$4:$B$22,$R7)) -> 0 | F7: =N(Aliments!$C$8)*(N(Aliments!$F$8)*SUMIFS('Aliment par vague'!$H$4:$H$22,Empoissonnement!$B$4:$B$22,$A7)+N(Aliments!$G$8)*SUMIFS('Aliment par vague'!$H$4:$H$22,Empoissonnement!$B$4:$B$22,$Q7)+N(Aliments!$H$8)*SUMIFS('Aliment par vague'!$H$4:$H$22,Empoissonnement!$B$4:$B$22,$R7)) -> 0 | G7: =N(Aliments!$C$9)*(N(Aliments!$F$9)*SUMIFS('Aliment par vague'!$I$4:$I$22,Empoissonnement!$B$4:$B$22,$A7)+N(Aliments!$G$9)*SUMIFS('Aliment par vague'!$I$4:$I$22,Empoissonnement!$B$4:$B$22,$Q7)+N(Aliments!$H$9)*SUMIFS('Aliment par vague'!$I$4:$I$22,Empoissonnement!$B$4:$B$22,$R7)) -> 0 | H7: =SUM(B7:G7) -> 5160 | I7: =IF(Aliments!$C$4=0,0,IF(Aliments!$C$4="",0,ROUNDUP(B7/Aliments!$C$4,0))) -> 58 | J7: =IF(Aliments!$C$5=0,0,IF(Aliments!$C$5="",0,ROUNDUP(C7/Aliments!$C$5,0))) -> 87 | K7: =IF(Aliments!$C$6=0,0,IF(Aliments!$C$6="",0,ROUNDUP(D7/Aliments!$C$6,0))) -> 200 | L7: =IF(Aliments!$C$7=0,0,IF(Aliments!$C$7="",0,ROUNDUP(E7/Aliments!$C$7,0))) -> 0 | M7: =IF(Aliments!$C$8=0,0,IF(Aliments!$C$8="",0,ROUNDUP(F7/Aliments!$C$8,0))) -> 0 | N7: =IF(Aliments!$C$9=0,0,IF(Aliments!$C$9="",0,ROUNDUP(G7/Aliments!$C$9,0))) -> 0 | O7: =B7*Aliments!$E$4+C7*Aliments!$E$5+D7*Aliments!$E$6+E7*Aliments!$E$7+F7*Aliments!$E$8+G7*Aliments!$E$9 -> 5562400 | Q7: =EDATE($A7,-1) -> 46266 | R7: =EDATE($A7,-2) -> 46235
A8: 46327 | B8: =N(Aliments!$C$4)*(N(Aliments!$F$4)*SUMIFS('Aliment par vague'!$D$4:$D$22,Empoissonnement!$B$4:$B$22,$A8)+N(Aliments!$G$4)*SUMIFS('Aliment par vague'!$D$4:$D$22,Empoissonnement!$B$4:$B$22,$Q8)+N(Aliments!$H$4)*SUMIFS('Aliment par vague'!$D$4:$D$22,Empoissonnement!$B$4:$B$22,$R8)) -> 960 | C8: =N(Aliments!$C$5)*(N(Aliments!$F$5)*SUMIFS('Aliment par vague'!$E$4:$E$22,Empoissonnement!$B$4:$B$22,$A8)+N(Aliments!$G$5)*SUMIFS('Aliment par vague'!$E$4:$E$22,Empoissonnement!$B$4:$B$22,$Q8)+N(Aliments!$H$5)*SUMIFS('Aliment par vague'!$E$4:$E$22,Empoissonnement!$B$4:$B$22,$R8)) -> 2160 | D8: =N(Aliments!$C$6)*(N(Aliments!$F$6)*SUMIFS('Aliment par vague'!$F$4:$F$22,Empoissonnement!$B$4:$B$22,$A8)+N(Aliments!$G$6)*SUMIFS('Aliment par vague'!$F$4:$F$22,Empoissonnement!$B$4:$B$22,$Q8)+N(Aliments!$H$6)*SUMIFS('Aliment par vague'!$F$4:$F$22,Empoissonnement!$B$4:$B$22,$R8)) -> 4200 | E8: =N(Aliments!$C$7)*(N(Aliments!$F$7)*SUMIFS('Aliment par vague'!$G$4:$G$22,Empoissonnement!$B$4:$B$22,$A8)+N(Aliments!$G$7)*SUMIFS('Aliment par vague'!$G$4:$G$22,Empoissonnement!$B$4:$B$22,$Q8)+N(Aliments!$H$7)*SUMIFS('Aliment par vague'!$G$4:$G$22,Empoissonnement!$B$4:$B$22,$R8)) -> 0 | F8: =N(Aliments!$C$8)*(N(Aliments!$F$8)*SUMIFS('Aliment par vague'!$H$4:$H$22,Empoissonnement!$B$4:$B$22,$A8)+N(Aliments!$G$8)*SUMIFS('Aliment par vague'!$H$4:$H$22,Empoissonnement!$B$4:$B$22,$Q8)+N(Aliments!$H$8)*SUMIFS('Aliment par vague'!$H$4:$H$22,Empoissonnement!$B$4:$B$22,$R8)) -> 0 | G8: =N(Aliments!$C$9)*(N(Aliments!$F$9)*SUMIFS('Aliment par vague'!$I$4:$I$22,Empoissonnement!$B$4:$B$22,$A8)+N(Aliments!$G$9)*SUMIFS('Aliment par vague'!$I$4:$I$22,Empoissonnement!$B$4:$B$22,$Q8)+N(Aliments!$H$9)*SUMIFS('Aliment par vague'!$I$4:$I$22,Empoissonnement!$B$4:$B$22,$R8)) -> 0 | H8: =SUM(B8:G8) -> 7320 | I8: =IF(Aliments!$C$4=0,0,IF(Aliments!$C$4="",0,ROUNDUP(B8/Aliments!$C$4,0))) -> 64 | J8: =IF(Aliments!$C$5=0,0,IF(Aliments!$C$5="",0,ROUNDUP(C8/Aliments!$C$5,0))) -> 144 | K8: =IF(Aliments!$C$6=0,0,IF(Aliments!$C$6="",0,ROUNDUP(D8/Aliments!$C$6,0))) -> 280 | L8: =IF(Aliments!$C$7=0,0,IF(Aliments!$C$7="",0,ROUNDUP(E8/Aliments!$C$7,0))) -> 0 | M8: =IF(Aliments!$C$8=0,0,IF(Aliments!$C$8="",0,ROUNDUP(F8/Aliments!$C$8,0))) -> 0 | N8: =IF(Aliments!$C$9=0,0,IF(Aliments!$C$9="",0,ROUNDUP(G8/Aliments!$C$9,0))) -> 0 | O8: =B8*Aliments!$E$4+C8*Aliments!$E$5+D8*Aliments!$E$6+E8*Aliments!$E$7+F8*Aliments!$E$8+G8*Aliments!$E$9 -> 7868000 | Q8: =EDATE($A8,-1) -> 46296 | R8: =EDATE($A8,-2) -> 46266
A9: 46357 | B9: =N(Aliments!$C$4)*(N(Aliments!$F$4)*SUMIFS('Aliment par vague'!$D$4:$D$22,Empoissonnement!$B$4:$B$22,$A9)+N(Aliments!$G$4)*SUMIFS('Aliment par vague'!$D$4:$D$22,Empoissonnement!$B$4:$B$22,$Q9)+N(Aliments!$H$4)*SUMIFS('Aliment par vague'!$D$4:$D$22,Empoissonnement!$B$4:$B$22,$R9)) -> 1152 | C9: =N(Aliments!$C$5)*(N(Aliments!$F$5)*SUMIFS('Aliment par vague'!$E$4:$E$22,Empoissonnement!$B$4:$B$22,$A9)+N(Aliments!$G$5)*SUMIFS('Aliment par vague'!$E$4:$E$22,Empoissonnement!$B$4:$B$22,$Q9)+N(Aliments!$H$5)*SUMIFS('Aliment par vague'!$E$4:$E$22,Empoissonnement!$B$4:$B$22,$R9)) -> 2268 | D9: =N(Aliments!$C$6)*(N(Aliments!$F$6)*SUMIFS('Aliment par vague'!$F$4:$F$22,Empoissonnement!$B$4:$B$22,$A9)+N(Aliments!$G$6)*SUMIFS('Aliment par vague'!$F$4:$F$22,Empoissonnement!$B$4:$B$22,$Q9)+N(Aliments!$H$6)*SUMIFS('Aliment par vague'!$F$4:$F$22,Empoissonnement!$B$4:$B$22,$R9)) -> 6000 | E9: =N(Aliments!$C$7)*(N(Aliments!$F$7)*SUMIFS('Aliment par vague'!$G$4:$G$22,Empoissonnement!$B$4:$B$22,$A9)+N(Aliments!$G$7)*SUMIFS('Aliment par vague'!$G$4:$G$22,Empoissonnement!$B$4:$B$22,$Q9)+N(Aliments!$H$7)*SUMIFS('Aliment par vague'!$G$4:$G$22,Empoissonnement!$B$4:$B$22,$R9)) -> 0 | F9: =N(Aliments!$C$8)*(N(Aliments!$F$8)*SUMIFS('Aliment par vague'!$H$4:$H$22,Empoissonnement!$B$4:$B$22,$A9)+N(Aliments!$G$8)*SUMIFS('Aliment par vague'!$H$4:$H$22,Empoissonnement!$B$4:$B$22,$Q9)+N(Aliments!$H$8)*SUMIFS('Aliment par vague'!$H$4:$H$22,Empoissonnement!$B$4:$B$22,$R9)) -> 0 | G9: =N(Aliments!$C$9)*(N(Aliments!$F$9)*SUMIFS('Aliment par vague'!$I$4:$I$22,Empoissonnement!$B$4:$B$22,$A9)+N(Aliments!$G$9)*SUMIFS('Aliment par vague'!$I$4:$I$22,Empoissonnement!$B$4:$B$22,$Q9)+N(Aliments!$H$9)*SUMIFS('Aliment par vague'!$I$4:$I$22,Empoissonnement!$B$4:$B$22,$R9)) -> 0 | H9: =SUM(B9:G9) -> 9420 | I9: =IF(Aliments!$C$4=0,0,IF(Aliments!$C$4="",0,ROUNDUP(B9/Aliments!$C$4,0))) -> 77 | J9: =IF(Aliments!$C$5=0,0,IF(Aliments!$C$5="",0,ROUNDUP(C9/Aliments!$C$5,0))) -> 152 | K9: =IF(Aliments!$C$6=0,0,IF(Aliments!$C$6="",0,ROUNDUP(D9/Aliments!$C$6,0))) -> 400 | L9: =IF(Aliments!$C$7=0,0,IF(Aliments!$C$7="",0,ROUNDUP(E9/Aliments!$C$7,0))) -> 0 | M9: =IF(Aliments!$C$8=0,0,IF(Aliments!$C$8="",0,ROUNDUP(F9/Aliments!$C$8,0))) -> 0 | N9: =IF(Aliments!$C$9=0,0,IF(Aliments!$C$9="",0,ROUNDUP(G9/Aliments!$C$9,0))) -> 0 | O9: =B9*Aliments!$E$4+C9*Aliments!$E$5+D9*Aliments!$E$6+E9*Aliments!$E$7+F9*Aliments!$E$8+G9*Aliments!$E$9 -> 10077200 | Q9: =EDATE($A9,-1) -> 46327 | R9: =EDATE($A9,-2) -> 46296
A10: 46388 | B10: =N(Aliments!$C$4)*(N(Aliments!$F$4)*SUMIFS('Aliment par vague'!$D$4:$D$22,Empoissonnement!$B$4:$B$22,$A10)+N(Aliments!$G$4)*SUMIFS('Aliment par vague'!$D$4:$D$22,Empoissonnement!$B$4:$B$22,$Q10)+N(Aliments!$H$4)*SUMIFS('Aliment par vague'!$D$4:$D$22,Empoissonnement!$B$4:$B$22,$R10)) -> 1392 | C10: =N(Aliments!$C$5)*(N(Aliments!$F$5)*SUMIFS('Aliment par vague'!$E$4:$E$22,Empoissonnement!$B$4:$B$22,$A10)+N(Aliments!$G$5)*SUMIFS('Aliment par vague'!$E$4:$E$22,Empoissonnement!$B$4:$B$22,$Q10)+N(Aliments!$H$5)*SUMIFS('Aliment par vague'!$E$4:$E$22,Empoissonnement!$B$4:$B$22,$R10)) -> 2808 | D10: =N(Aliments!$C$6)*(N(Aliments!$F$6)*SUMIFS('Aliment par vague'!$F$4:$F$22,Empoissonnement!$B$4:$B$22,$A10)+N(Aliments!$G$6)*SUMIFS('Aliment par vague'!$F$4:$F$22,Empoissonnement!$B$4:$B$22,$Q10)+N(Aliments!$H$6)*SUMIFS('Aliment par vague'!$F$4:$F$22,Empoissonnement!$B$4:$B$22,$R10)) -> 6600 | E10: =N(Aliments!$C$7)*(N(Aliments!$F$7)*SUMIFS('Aliment par vague'!$G$4:$G$22,Empoissonnement!$B$4:$B$22,$A10)+N(Aliments!$G$7)*SUMIFS('Aliment par vague'!$G$4:$G$22,Empoissonnement!$B$4:$B$22,$Q10)+N(Aliments!$H$7)*SUMIFS('Aliment par vague'!$G$4:$G$22,Empoissonnement!$B$4:$B$22,$R10)) -> 0 | F10: =N(Aliments!$C$8)*(N(Aliments!$F$8)*SUMIFS('Aliment par vague'!$H$4:$H$22,Empoissonnement!$B$4:$B$22,$A10)+N(Aliments!$G$8)*SUMIFS('Aliment par vague'!$H$4:$H$22,Empoissonnement!$B$4:$B$22,$Q10)+N(Aliments!$H$8)*SUMIFS('Aliment par vague'!$H$4:$H$22,Empoissonnement!$B$4:$B$22,$R10)) -> 0 | G10: =N(Aliments!$C$9)*(N(Aliments!$F$9)*SUMIFS('Aliment par vague'!$I$4:$I$22,Empoissonnement!$B$4:$B$22,$A10)+N(Aliments!$G$9)*SUMIFS('Aliment par vague'!$I$4:$I$22,Empoissonnement!$B$4:$B$22,$Q10)+N(Aliments!$H$9)*SUMIFS('Aliment par vague'!$I$4:$I$22,Empoissonnement!$B$4:$B$22,$R10)) -> 0 | H10: =SUM(B10:G10) -> 10800 | I10: =IF(Aliments!$C$4=0,0,IF(Aliments!$C$4="",0,ROUNDUP(B10/Aliments!$C$4,0))) -> 93 | J10: =IF(Aliments!$C$5=0,0,IF(Aliments!$C$5="",0,ROUNDUP(C10/Aliments!$C$5,0))) -> 188 | K10: =IF(Aliments!$C$6=0,0,IF(Aliments!$C$6="",0,ROUNDUP(D10/Aliments!$C$6,0))) -> 440 | L10: =IF(Aliments!$C$7=0,0,IF(Aliments!$C$7="",0,ROUNDUP(E10/Aliments!$C$7,0))) -> 0 | M10: =IF(Aliments!$C$8=0,0,IF(Aliments!$C$8="",0,ROUNDUP(F10/Aliments!$C$8,0))) -> 0 | N10: =IF(Aliments!$C$9=0,0,IF(Aliments!$C$9="",0,ROUNDUP(G10/Aliments!$C$9,0))) -> 0 | O10: =B10*Aliments!$E$4+C10*Aliments!$E$5+D10*Aliments!$E$6+E10*Aliments!$E$7+F10*Aliments!$E$8+G10*Aliments!$E$9 -> 11579200 | Q10: =EDATE($A10,-1) -> 46357 | R10: =EDATE($A10,-2) -> 46327
A11: 46419 | B11: =N(Aliments!$C$4)*(N(Aliments!$F$4)*SUMIFS('Aliment par vague'!$D$4:$D$22,Empoissonnement!$B$4:$B$22,$A11)+N(Aliments!$G$4)*SUMIFS('Aliment par vague'!$D$4:$D$22,Empoissonnement!$B$4:$B$22,$Q11)+N(Aliments!$H$4)*SUMIFS('Aliment par vague'!$D$4:$D$22,Empoissonnement!$B$4:$B$22,$R11)) -> 1728 | C11: =N(Aliments!$C$5)*(N(Aliments!$F$5)*SUMIFS('Aliment par vague'!$E$4:$E$22,Empoissonnement!$B$4:$B$22,$A11)+N(Aliments!$G$5)*SUMIFS('Aliment par vague'!$E$4:$E$22,Empoissonnement!$B$4:$B$22,$Q11)+N(Aliments!$H$5)*SUMIFS('Aliment par vague'!$E$4:$E$22,Empoissonnement!$B$4:$B$22,$R11)) -> 3402 | D11: =N(Aliments!$C$6)*(N(Aliments!$F$6)*SUMIFS('Aliment par vague'!$F$4:$F$22,Empoissonnement!$B$4:$B$22,$A11)+N(Aliments!$G$6)*SUMIFS('Aliment par vague'!$F$4:$F$22,Empoissonnement!$B$4:$B$22,$Q11)+N(Aliments!$H$6)*SUMIFS('Aliment par vague'!$F$4:$F$22,Empoissonnement!$B$4:$B$22,$R11)) -> 8100 | E11: =N(Aliments!$C$7)*(N(Aliments!$F$7)*SUMIFS('Aliment par vague'!$G$4:$G$22,Empoissonnement!$B$4:$B$22,$A11)+N(Aliments!$G$7)*SUMIFS('Aliment par vague'!$G$4:$G$22,Empoissonnement!$B$4:$B$22,$Q11)+N(Aliments!$H$7)*SUMIFS('Aliment par vague'!$G$4:$G$22,Empoissonnement!$B$4:$B$22,$R11)) -> 0 | F11: =N(Aliments!$C$8)*(N(Aliments!$F$8)*SUMIFS('Aliment par vague'!$H$4:$H$22,Empoissonnement!$B$4:$B$22,$A11)+N(Aliments!$G$8)*SUMIFS('Aliment par vague'!$H$4:$H$22,Empoissonnement!$B$4:$B$22,$Q11)+N(Aliments!$H$8)*SUMIFS('Aliment par vague'!$H$4:$H$22,Empoissonnement!$B$4:$B$22,$R11)) -> 0 | G11: =N(Aliments!$C$9)*(N(Aliments!$F$9)*SUMIFS('Aliment par vague'!$I$4:$I$22,Empoissonnement!$B$4:$B$22,$A11)+N(Aliments!$G$9)*SUMIFS('Aliment par vague'!$I$4:$I$22,Empoissonnement!$B$4:$B$22,$Q11)+N(Aliments!$H$9)*SUMIFS('Aliment par vague'!$I$4:$I$22,Empoissonnement!$B$4:$B$22,$R11)) -> 0 | H11: =SUM(B11:G11) -> 13230 | I11: =IF(Aliments!$C$4=0,0,IF(Aliments!$C$4="",0,ROUNDUP(B11/Aliments!$C$4,0))) -> 116 | J11: =IF(Aliments!$C$5=0,0,IF(Aliments!$C$5="",0,ROUNDUP(C11/Aliments!$C$5,0))) -> 227 | K11: =IF(Aliments!$C$6=0,0,IF(Aliments!$C$6="",0,ROUNDUP(D11/Aliments!$C$6,0))) -> 540 | L11: =IF(Aliments!$C$7=0,0,IF(Aliments!$C$7="",0,ROUNDUP(E11/Aliments!$C$7,0))) -> 0 | M11: =IF(Aliments!$C$8=0,0,IF(Aliments!$C$8="",0,ROUNDUP(F11/Aliments!$C$8,0))) -> 0 | N11: =IF(Aliments!$C$9=0,0,IF(Aliments!$C$9="",0,ROUNDUP(G11/Aliments!$C$9,0))) -> 0 | O11: =B11*Aliments!$E$4+C11*Aliments!$E$5+D11*Aliments!$E$6+E11*Aliments!$E$7+F11*Aliments!$E$8+G11*Aliments!$E$9 -> 14185800 | Q11: =EDATE($A11,-1) -> 46388 | R11: =EDATE($A11,-2) -> 46357
A12: 46447 | B12: =N(Aliments!$C$4)*(N(Aliments!$F$4)*SUMIFS('Aliment par vague'!$D$4:$D$22,Empoissonnement!$B$4:$B$22,$A12)+N(Aliments!$G$4)*SUMIFS('Aliment par vague'!$D$4:$D$22,Empoissonnement!$B$4:$B$22,$Q12)+N(Aliments!$H$4)*SUMIFS('Aliment par vague'!$D$4:$D$22,Empoissonnement!$B$4:$B$22,$R12)) -> 1800 | C12: =N(Aliments!$C$5)*(N(Aliments!$F$5)*SUMIFS('Aliment par vague'!$E$4:$E$22,Empoissonnement!$B$4:$B$22,$A12)+N(Aliments!$G$5)*SUMIFS('Aliment par vague'!$E$4:$E$22,Empoissonnement!$B$4:$B$22,$Q12)+N(Aliments!$H$5)*SUMIFS('Aliment par vague'!$E$4:$E$22,Empoissonnement!$B$4:$B$22,$R12)) -> 4050 | D12: =N(Aliments!$C$6)*(N(Aliments!$F$6)*SUMIFS('Aliment par vague'!$F$4:$F$22,Empoissonnement!$B$4:$B$22,$A12)+N(Aliments!$G$6)*SUMIFS('Aliment par vague'!$F$4:$F$22,Empoissonnement!$B$4:$B$22,$Q12)+N(Aliments!$H$6)*SUMIFS('Aliment par vague'!$F$4:$F$22,Empoissonnement!$B$4:$B$22,$R12)) -> 9900 | E12: =N(Aliments!$C$7)*(N(Aliments!$F$7)*SUMIFS('Aliment par vague'!$G$4:$G$22,Empoissonnement!$B$4:$B$22,$A12)+N(Aliments!$G$7)*SUMIFS('Aliment par vague'!$G$4:$G$22,Empoissonnement!$B$4:$B$22,$Q12)+N(Aliments!$H$7)*SUMIFS('Aliment par vague'!$G$4:$G$22,Empoissonnement!$B$4:$B$22,$R12)) -> 0 | F12: =N(Aliments!$C$8)*(N(Aliments!$F$8)*SUMIFS('Aliment par vague'!$H$4:$H$22,Empoissonnement!$B$4:$B$22,$A12)+N(Aliments!$G$8)*SUMIFS('Aliment par vague'!$H$4:$H$22,Empoissonnement!$B$4:$B$22,$Q12)+N(Aliments!$H$8)*SUMIFS('Aliment par vague'!$H$4:$H$22,Empoissonnement!$B$4:$B$22,$R12)) -> 0 | G12: =N(Aliments!$C$9)*(N(Aliments!$F$9)*SUMIFS('Aliment par vague'!$I$4:$I$22,Empoissonnement!$B$4:$B$22,$A12)+N(Aliments!$G$9)*SUMIFS('Aliment par vague'!$I$4:$I$22,Empoissonnement!$B$4:$B$22,$Q12)+N(Aliments!$H$9)*SUMIFS('Aliment par vague'!$I$4:$I$22,Empoissonnement!$B$4:$B$22,$R12)) -> 0 | H12: =SUM(B12:G12) -> 15750 | I12: =IF(Aliments!$C$4=0,0,IF(Aliments!$C$4="",0,ROUNDUP(B12/Aliments!$C$4,0))) -> 120 | J12: =IF(Aliments!$C$5=0,0,IF(Aliments!$C$5="",0,ROUNDUP(C12/Aliments!$C$5,0))) -> 270 | K12: =IF(Aliments!$C$6=0,0,IF(Aliments!$C$6="",0,ROUNDUP(D12/Aliments!$C$6,0))) -> 660 | L12: =IF(Aliments!$C$7=0,0,IF(Aliments!$C$7="",0,ROUNDUP(E12/Aliments!$C$7,0))) -> 0 | M12: =IF(Aliments!$C$8=0,0,IF(Aliments!$C$8="",0,ROUNDUP(F12/Aliments!$C$8,0))) -> 0 | N12: =IF(Aliments!$C$9=0,0,IF(Aliments!$C$9="",0,ROUNDUP(G12/Aliments!$C$9,0))) -> 0 | O12: =B12*Aliments!$E$4+C12*Aliments!$E$5+D12*Aliments!$E$6+E12*Aliments!$E$7+F12*Aliments!$E$8+G12*Aliments!$E$9 -> 16845000 | Q12: =EDATE($A12,-1) -> 46419 | R12: =EDATE($A12,-2) -> 46388
A13: 46478 | B13: =N(Aliments!$C$4)*(N(Aliments!$F$4)*SUMIFS('Aliment par vague'!$D$4:$D$22,Empoissonnement!$B$4:$B$22,$A13)+N(Aliments!$G$4)*SUMIFS('Aliment par vague'!$D$4:$D$22,Empoissonnement!$B$4:$B$22,$Q13)+N(Aliments!$H$4)*SUMIFS('Aliment par vague'!$D$4:$D$22,Empoissonnement!$B$4:$B$22,$R13)) -> 1800 | C13: =N(Aliments!$C$5)*(N(Aliments!$F$5)*SUMIFS('Aliment par vague'!$E$4:$E$22,Empoissonnement!$B$4:$B$22,$A13)+N(Aliments!$G$5)*SUMIFS('Aliment par vague'!$E$4:$E$22,Empoissonnement!$B$4:$B$22,$Q13)+N(Aliments!$H$5)*SUMIFS('Aliment par vague'!$E$4:$E$22,Empoissonnement!$B$4:$B$22,$R13)) -> 4050 | D13: =N(Aliments!$C$6)*(N(Aliments!$F$6)*SUMIFS('Aliment par vague'!$F$4:$F$22,Empoissonnement!$B$4:$B$22,$A13)+N(Aliments!$G$6)*SUMIFS('Aliment par vague'!$F$4:$F$22,Empoissonnement!$B$4:$B$22,$Q13)+N(Aliments!$H$6)*SUMIFS('Aliment par vague'!$F$4:$F$22,Empoissonnement!$B$4:$B$22,$R13)) -> 11250 | E13: =N(Aliments!$C$7)*(N(Aliments!$F$7)*SUMIFS('Aliment par vague'!$G$4:$G$22,Empoissonnement!$B$4:$B$22,$A13)+N(Aliments!$G$7)*SUMIFS('Aliment par vague'!$G$4:$G$22,Empoissonnement!$B$4:$B$22,$Q13)+N(Aliments!$H$7)*SUMIFS('Aliment par vague'!$G$4:$G$22,Empoissonnement!$B$4:$B$22,$R13)) -> 0 | F13: =N(Aliments!$C$8)*(N(Aliments!$F$8)*SUMIFS('Aliment par vague'!$H$4:$H$22,Empoissonnement!$B$4:$B$22,$A13)+N(Aliments!$G$8)*SUMIFS('Aliment par vague'!$H$4:$H$22,Empoissonnement!$B$4:$B$22,$Q13)+N(Aliments!$H$8)*SUMIFS('Aliment par vague'!$H$4:$H$22,Empoissonnement!$B$4:$B$22,$R13)) -> 0 | G13: =N(Aliments!$C$9)*(N(Aliments!$F$9)*SUMIFS('Aliment par vague'!$I$4:$I$22,Empoissonnement!$B$4:$B$22,$A13)+N(Aliments!$G$9)*SUMIFS('Aliment par vague'!$I$4:$I$22,Empoissonnement!$B$4:$B$22,$Q13)+N(Aliments!$H$9)*SUMIFS('Aliment par vague'!$I$4:$I$22,Empoissonnement!$B$4:$B$22,$R13)) -> 0 | H13: =SUM(B13:G13) -> 17100 | I13: =IF(Aliments!$C$4=0,0,IF(Aliments!$C$4="",0,ROUNDUP(B13/Aliments!$C$4,0))) -> 120 | J13: =IF(Aliments!$C$5=0,0,IF(Aliments!$C$5="",0,ROUNDUP(C13/Aliments!$C$5,0))) -> 270 | K13: =IF(Aliments!$C$6=0,0,IF(Aliments!$C$6="",0,ROUNDUP(D13/Aliments!$C$6,0))) -> 750 | L13: =IF(Aliments!$C$7=0,0,IF(Aliments!$C$7="",0,ROUNDUP(E13/Aliments!$C$7,0))) -> 0 | M13: =IF(Aliments!$C$8=0,0,IF(Aliments!$C$8="",0,ROUNDUP(F13/Aliments!$C$8,0))) -> 0 | N13: =IF(Aliments!$C$9=0,0,IF(Aliments!$C$9="",0,ROUNDUP(G13/Aliments!$C$9,0))) -> 0 | O13: =B13*Aliments!$E$4+C13*Aliments!$E$5+D13*Aliments!$E$6+E13*Aliments!$E$7+F13*Aliments!$E$8+G13*Aliments!$E$9 -> 18240000 | Q13: =EDATE($A13,-1) -> 46447 | R13: =EDATE($A13,-2) -> 46419
A14: 46508 | B14: =N(Aliments!$C$4)*(N(Aliments!$F$4)*SUMIFS('Aliment par vague'!$D$4:$D$22,Empoissonnement!$B$4:$B$22,$A14)+N(Aliments!$G$4)*SUMIFS('Aliment par vague'!$D$4:$D$22,Empoissonnement!$B$4:$B$22,$Q14)+N(Aliments!$H$4)*SUMIFS('Aliment par vague'!$D$4:$D$22,Empoissonnement!$B$4:$B$22,$R14)) -> 1800 | C14: =N(Aliments!$C$5)*(N(Aliments!$F$5)*SUMIFS('Aliment par vague'!$E$4:$E$22,Empoissonnement!$B$4:$B$22,$A14)+N(Aliments!$G$5)*SUMIFS('Aliment par vague'!$E$4:$E$22,Empoissonnement!$B$4:$B$22,$Q14)+N(Aliments!$H$5)*SUMIFS('Aliment par vague'!$E$4:$E$22,Empoissonnement!$B$4:$B$22,$R14)) -> 4050 | D14: =N(Aliments!$C$6)*(N(Aliments!$F$6)*SUMIFS('Aliment par vague'!$F$4:$F$22,Empoissonnement!$B$4:$B$22,$A14)+N(Aliments!$G$6)*SUMIFS('Aliment par vague'!$F$4:$F$22,Empoissonnement!$B$4:$B$22,$Q14)+N(Aliments!$H$6)*SUMIFS('Aliment par vague'!$F$4:$F$22,Empoissonnement!$B$4:$B$22,$R14)) -> 11250 | E14: =N(Aliments!$C$7)*(N(Aliments!$F$7)*SUMIFS('Aliment par vague'!$G$4:$G$22,Empoissonnement!$B$4:$B$22,$A14)+N(Aliments!$G$7)*SUMIFS('Aliment par vague'!$G$4:$G$22,Empoissonnement!$B$4:$B$22,$Q14)+N(Aliments!$H$7)*SUMIFS('Aliment par vague'!$G$4:$G$22,Empoissonnement!$B$4:$B$22,$R14)) -> 0 | F14: =N(Aliments!$C$8)*(N(Aliments!$F$8)*SUMIFS('Aliment par vague'!$H$4:$H$22,Empoissonnement!$B$4:$B$22,$A14)+N(Aliments!$G$8)*SUMIFS('Aliment par vague'!$H$4:$H$22,Empoissonnement!$B$4:$B$22,$Q14)+N(Aliments!$H$8)*SUMIFS('Aliment par vague'!$H$4:$H$22,Empoissonnement!$B$4:$B$22,$R14)) -> 0 | G14: =N(Aliments!$C$9)*(N(Aliments!$F$9)*SUMIFS('Aliment par vague'!$I$4:$I$22,Empoissonnement!$B$4:$B$22,$A14)+N(Aliments!$G$9)*SUMIFS('Aliment par vague'!$I$4:$I$22,Empoissonnement!$B$4:$B$22,$Q14)+N(Aliments!$H$9)*SUMIFS('Aliment par vague'!$I$4:$I$22,Empoissonnement!$B$4:$B$22,$R14)) -> 0 | H14: =SUM(B14:G14) -> 17100 | I14: =IF(Aliments!$C$4=0,0,IF(Aliments!$C$4="",0,ROUNDUP(B14/Aliments!$C$4,0))) -> 120 | J14: =IF(Aliments!$C$5=0,0,IF(Aliments!$C$5="",0,ROUNDUP(C14/Aliments!$C$5,0))) -> 270 | K14: =IF(Aliments!$C$6=0,0,IF(Aliments!$C$6="",0,ROUNDUP(D14/Aliments!$C$6,0))) -> 750 | L14: =IF(Aliments!$C$7=0,0,IF(Aliments!$C$7="",0,ROUNDUP(E14/Aliments!$C$7,0))) -> 0 | M14: =IF(Aliments!$C$8=0,0,IF(Aliments!$C$8="",0,ROUNDUP(F14/Aliments!$C$8,0))) -> 0 | N14: =IF(Aliments!$C$9=0,0,IF(Aliments!$C$9="",0,ROUNDUP(G14/Aliments!$C$9,0))) -> 0 | O14: =B14*Aliments!$E$4+C14*Aliments!$E$5+D14*Aliments!$E$6+E14*Aliments!$E$7+F14*Aliments!$E$8+G14*Aliments!$E$9 -> 18240000 | Q14: =EDATE($A14,-1) -> 46478 | R14: =EDATE($A14,-2) -> 46447
A15: 46539 | B15: =N(Aliments!$C$4)*(N(Aliments!$F$4)*SUMIFS('Aliment par vague'!$D$4:$D$22,Empoissonnement!$B$4:$B$22,$A15)+N(Aliments!$G$4)*SUMIFS('Aliment par vague'!$D$4:$D$22,Empoissonnement!$B$4:$B$22,$Q15)+N(Aliments!$H$4)*SUMIFS('Aliment par vague'!$D$4:$D$22,Empoissonnement!$B$4:$B$22,$R15)) -> 1800 | C15: =N(Aliments!$C$5)*(N(Aliments!$F$5)*SUMIFS('Aliment par vague'!$E$4:$E$22,Empoissonnement!$B$4:$B$22,$A15)+N(Aliments!$G$5)*SUMIFS('Aliment par vague'!$E$4:$E$22,Empoissonnement!$B$4:$B$22,$Q15)+N(Aliments!$H$5)*SUMIFS('Aliment par vague'!$E$4:$E$22,Empoissonnement!$B$4:$B$22,$R15)) -> 4050 | D15: =N(Aliments!$C$6)*(N(Aliments!$F$6)*SUMIFS('Aliment par vague'!$F$4:$F$22,Empoissonnement!$B$4:$B$22,$A15)+N(Aliments!$G$6)*SUMIFS('Aliment par vague'!$F$4:$F$22,Empoissonnement!$B$4:$B$22,$Q15)+N(Aliments!$H$6)*SUMIFS('Aliment par vague'!$F$4:$F$22,Empoissonnement!$B$4:$B$22,$R15)) -> 11250 | E15: =N(Aliments!$C$7)*(N(Aliments!$F$7)*SUMIFS('Aliment par vague'!$G$4:$G$22,Empoissonnement!$B$4:$B$22,$A15)+N(Aliments!$G$7)*SUMIFS('Aliment par vague'!$G$4:$G$22,Empoissonnement!$B$4:$B$22,$Q15)+N(Aliments!$H$7)*SUMIFS('Aliment par vague'!$G$4:$G$22,Empoissonnement!$B$4:$B$22,$R15)) -> 0 | F15: =N(Aliments!$C$8)*(N(Aliments!$F$8)*SUMIFS('Aliment par vague'!$H$4:$H$22,Empoissonnement!$B$4:$B$22,$A15)+N(Aliments!$G$8)*SUMIFS('Aliment par vague'!$H$4:$H$22,Empoissonnement!$B$4:$B$22,$Q15)+N(Aliments!$H$8)*SUMIFS('Aliment par vague'!$H$4:$H$22,Empoissonnement!$B$4:$B$22,$R15)) -> 0 | G15: =N(Aliments!$C$9)*(N(Aliments!$F$9)*SUMIFS('Aliment par vague'!$I$4:$I$22,Empoissonnement!$B$4:$B$22,$A15)+N(Aliments!$G$9)*SUMIFS('Aliment par vague'!$I$4:$I$22,Empoissonnement!$B$4:$B$22,$Q15)+N(Aliments!$H$9)*SUMIFS('Aliment par vague'!$I$4:$I$22,Empoissonnement!$B$4:$B$22,$R15)) -> 0 | H15: =SUM(B15:G15) -> 17100 | I15: =IF(Aliments!$C$4=0,0,IF(Aliments!$C$4="",0,ROUNDUP(B15/Aliments!$C$4,0))) -> 120 | J15: =IF(Aliments!$C$5=0,0,IF(Aliments!$C$5="",0,ROUNDUP(C15/Aliments!$C$5,0))) -> 270 | K15: =IF(Aliments!$C$6=0,0,IF(Aliments!$C$6="",0,ROUNDUP(D15/Aliments!$C$6,0))) -> 750 | L15: =IF(Aliments!$C$7=0,0,IF(Aliments!$C$7="",0,ROUNDUP(E15/Aliments!$C$7,0))) -> 0 | M15: =IF(Aliments!$C$8=0,0,IF(Aliments!$C$8="",0,ROUNDUP(F15/Aliments!$C$8,0))) -> 0 | N15: =IF(Aliments!$C$9=0,0,IF(Aliments!$C$9="",0,ROUNDUP(G15/Aliments!$C$9,0))) -> 0 | O15: =B15*Aliments!$E$4+C15*Aliments!$E$5+D15*Aliments!$E$6+E15*Aliments!$E$7+F15*Aliments!$E$8+G15*Aliments!$E$9 -> 18240000 | Q15: =EDATE($A15,-1) -> 46508 | R15: =EDATE($A15,-2) -> 46478
A16: 46569 | B16: =N(Aliments!$C$4)*(N(Aliments!$F$4)*SUMIFS('Aliment par vague'!$D$4:$D$22,Empoissonnement!$B$4:$B$22,$A16)+N(Aliments!$G$4)*SUMIFS('Aliment par vague'!$D$4:$D$22,Empoissonnement!$B$4:$B$22,$Q16)+N(Aliments!$H$4)*SUMIFS('Aliment par vague'!$D$4:$D$22,Empoissonnement!$B$4:$B$22,$R16)) -> 1800 | C16: =N(Aliments!$C$5)*(N(Aliments!$F$5)*SUMIFS('Aliment par vague'!$E$4:$E$22,Empoissonnement!$B$4:$B$22,$A16)+N(Aliments!$G$5)*SUMIFS('Aliment par vague'!$E$4:$E$22,Empoissonnement!$B$4:$B$22,$Q16)+N(Aliments!$H$5)*SUMIFS('Aliment par vague'!$E$4:$E$22,Empoissonnement!$B$4:$B$22,$R16)) -> 4050 | D16: =N(Aliments!$C$6)*(N(Aliments!$F$6)*SUMIFS('Aliment par vague'!$F$4:$F$22,Empoissonnement!$B$4:$B$22,$A16)+N(Aliments!$G$6)*SUMIFS('Aliment par vague'!$F$4:$F$22,Empoissonnement!$B$4:$B$22,$Q16)+N(Aliments!$H$6)*SUMIFS('Aliment par vague'!$F$4:$F$22,Empoissonnement!$B$4:$B$22,$R16)) -> 11250 | E16: =N(Aliments!$C$7)*(N(Aliments!$F$7)*SUMIFS('Aliment par vague'!$G$4:$G$22,Empoissonnement!$B$4:$B$22,$A16)+N(Aliments!$G$7)*SUMIFS('Aliment par vague'!$G$4:$G$22,Empoissonnement!$B$4:$B$22,$Q16)+N(Aliments!$H$7)*SUMIFS('Aliment par vague'!$G$4:$G$22,Empoissonnement!$B$4:$B$22,$R16)) -> 0 | F16: =N(Aliments!$C$8)*(N(Aliments!$F$8)*SUMIFS('Aliment par vague'!$H$4:$H$22,Empoissonnement!$B$4:$B$22,$A16)+N(Aliments!$G$8)*SUMIFS('Aliment par vague'!$H$4:$H$22,Empoissonnement!$B$4:$B$22,$Q16)+N(Aliments!$H$8)*SUMIFS('Aliment par vague'!$H$4:$H$22,Empoissonnement!$B$4:$B$22,$R16)) -> 0 | G16: =N(Aliments!$C$9)*(N(Aliments!$F$9)*SUMIFS('Aliment par vague'!$I$4:$I$22,Empoissonnement!$B$4:$B$22,$A16)+N(Aliments!$G$9)*SUMIFS('Aliment par vague'!$I$4:$I$22,Empoissonnement!$B$4:$B$22,$Q16)+N(Aliments!$H$9)*SUMIFS('Aliment par vague'!$I$4:$I$22,Empoissonnement!$B$4:$B$22,$R16)) -> 0 | H16: =SUM(B16:G16) -> 17100 | I16: =IF(Aliments!$C$4=0,0,IF(Aliments!$C$4="",0,ROUNDUP(B16/Aliments!$C$4,0))) -> 120 | J16: =IF(Aliments!$C$5=0,0,IF(Aliments!$C$5="",0,ROUNDUP(C16/Aliments!$C$5,0))) -> 270 | K16: =IF(Aliments!$C$6=0,0,IF(Aliments!$C$6="",0,ROUNDUP(D16/Aliments!$C$6,0))) -> 750 | L16: =IF(Aliments!$C$7=0,0,IF(Aliments!$C$7="",0,ROUNDUP(E16/Aliments!$C$7,0))) -> 0 | M16: =IF(Aliments!$C$8=0,0,IF(Aliments!$C$8="",0,ROUNDUP(F16/Aliments!$C$8,0))) -> 0 | N16: =IF(Aliments!$C$9=0,0,IF(Aliments!$C$9="",0,ROUNDUP(G16/Aliments!$C$9,0))) -> 0 | O16: =B16*Aliments!$E$4+C16*Aliments!$E$5+D16*Aliments!$E$6+E16*Aliments!$E$7+F16*Aliments!$E$8+G16*Aliments!$E$9 -> 18240000 | Q16: =EDATE($A16,-1) -> 46539 | R16: =EDATE($A16,-2) -> 46508
... A25: 46844 | B25: =N(Aliments!$C$4)*(N(Aliments!$F$4)*SUMIFS('Aliment par vague'!$D$4:$D$22,Empoissonnement!$B$4:$B$22,$A25)+N(Aliments!$G$4)*SUMIFS('Aliment par vague'!$D$4:$D$22,Empoissonnement!$B$4:$B$22,$Q25)+N(Aliments!$H$4)*SUMIFS('Aliment par vague'!$D$4:$D$22,Empoissonnement!$B$4:$B$22,$R25)) -> 0 | C25: =N(Aliments!$C$5)*(N(Aliments!$F$5)*SUMIFS('Aliment par vague'!$E$4:$E$22,Empoissonnement!$B$4:$B$22,$A25)+N(Aliments!$G$5)*SUMIFS('Aliment par vague'!$E$4:$E$22,Empoissonnement!$B$4:$B$22,$Q25)+N(Aliments!$H$5)*SUMIFS('Aliment par vague'!$E$4:$E$22,Empoissonnement!$B$4:$B$22,$R25)) -> 0 | D25: =N(Aliments!$C$6)*(N(Aliments!$F$6)*SUMIFS('Aliment par vague'!$F$4:$F$22,Empoissonnement!$B$4:$B$22,$A25)+N(Aliments!$G$6)*SUMIFS('Aliment par vague'!$F$4:$F$22,Empoissonnement!$B$4:$B$22,$Q25)+N(Aliments!$H$6)*SUMIFS('Aliment par vague'!$F$4:$F$22,Empoissonnement!$B$4:$B$22,$R25)) -> 6750 | E25: =N(Aliments!$C$7)*(N(Aliments!$F$7)*SUMIFS('Aliment par vague'!$G$4:$G$22,Empoissonnement!$B$4:$B$22,$A25)+N(Aliments!$G$7)*SUMIFS('Aliment par vague'!$G$4:$G$22,Empoissonnement!$B$4:$B$22,$Q25)+N(Aliments!$H$7)*SUMIFS('Aliment par vague'!$G$4:$G$22,Empoissonnement!$B$4:$B$22,$R25)) -> 0 | F25: =N(Aliments!$C$8)*(N(Aliments!$F$8)*SUMIFS('Aliment par vague'!$H$4:$H$22,Empoissonnement!$B$4:$B$22,$A25)+N(Aliments!$G$8)*SUMIFS('Aliment par vague'!$H$4:$H$22,Empoissonnement!$B$4:$B$22,$Q25)+N(Aliments!$H$8)*SUMIFS('Aliment par vague'!$H$4:$H$22,Empoissonnement!$B$4:$B$22,$R25)) -> 0 | G25: =N(Aliments!$C$9)*(N(Aliments!$F$9)*SUMIFS('Aliment par vague'!$I$4:$I$22,Empoissonnement!$B$4:$B$22,$A25)+N(Aliments!$G$9)*SUMIFS('Aliment par vague'!$I$4:$I$22,Empoissonnement!$B$4:$B$22,$Q25)+N(Aliments!$H$9)*SUMIFS('Aliment par vague'!$I$4:$I$22,Empoissonnement!$B$4:$B$22,$R25)) -> 0 | H25: =SUM(B25:G25) -> 6750 | I25: =IF(Aliments!$C$4=0,0,IF(Aliments!$C$4="",0,ROUNDUP(B25/Aliments!$C$4,0))) -> 0 | J25: =IF(Aliments!$C$5=0,0,IF(Aliments!$C$5="",0,ROUNDUP(C25/Aliments!$C$5,0))) -> 0 | K25: =IF(Aliments!$C$6=0,0,IF(Aliments!$C$6="",0,ROUNDUP(D25/Aliments!$C$6,0))) -> 450 | L25: =IF(Aliments!$C$7=0,0,IF(Aliments!$C$7="",0,ROUNDUP(E25/Aliments!$C$7,0))) -> 0 | M25: =IF(Aliments!$C$8=0,0,IF(Aliments!$C$8="",0,ROUNDUP(F25/Aliments!$C$8,0))) -> 0 | N25: =IF(Aliments!$C$9=0,0,IF(Aliments!$C$9="",0,ROUNDUP(G25/Aliments!$C$9,0))) -> 0 | O25: =B25*Aliments!$E$4+C25*Aliments!$E$5+D25*Aliments!$E$6+E25*Aliments!$E$7+F25*Aliments!$E$8+G25*Aliments!$E$9 -> 6975000 | Q25: =EDATE($A25,-1) -> 46813 | R25: =EDATE($A25,-2) -> 46784
A26: TOTAL | B26: =SUM(B5:B25) -> 28920 | C26: =SUM(C5:C25) -> 65070 | D26: =SUM(D5:D25) -> 180750 | E26: =SUM(E5:E25) -> 0 | F26: =SUM(F5:F25) -> 0 | G26: =SUM(G5:G25) -> 0 | H26: =SUM(H5:H25) -> 274740 | I26: =SUM(I5:I25) -> 1930 | ... O26: =SUM(O5:O25) -> 293056000

Sheet Dépenses
A1: DÉPENSES DÉTAILLÉES — postes en lignes, mois en colonnes
A2: Logistique : calculée automatiquement (tarifs au voyage, feuille Paramètres). Charges d'exploitation et ponctuelles : saisissez vos montants en bleu. Le TOTAL du mois remonte dans la ligne « Autres dépenses » des Prévisions.
A3: Poste de dépense | B3: =Prévisions!B$3 -> 46235 | C3: =Prévisions!C$3 -> 46266 | D3: =Prévisions!D$3 -> 46296 | E3: =Prévisions!E$3 -> 46327 | F3: =Prévisions!F$3 -> 46357 | G3: =Prévisions!G$3 -> 46388 | H3: =Prévisions!H$3 -> 46419 | I3: =Prévisions!I$3 -> 46447 | ... V3: =Prévisions!V$3 -> 46844 | W3: TOTAL
A4: LOGISTIQUE — calculée automatiquement
A5: Voyages aliments (nb) | B5: =IF(Paramètres!$B$25=0,0,ROUNDUP(Prévisions!B7/Paramètres!$B$25,0)) -> 1 | C5: =IF(Paramètres!$B$25=0,0,ROUNDUP(Prévisions!C7/Paramètres!$B$25,0)) -> 4 | D5: =IF(Paramètres!$B$25=0,0,ROUNDUP(Prévisions!D7/Paramètres!$B$25,0)) -> 6 | E5: =IF(Paramètres!$B$25=0,0,ROUNDUP(Prévisions!E7/Paramètres!$B$25,0)) -> 9 | F5: =IF(Paramètres!$B$25=0,0,ROUNDUP(Prévisions!F7/Paramètres!$B$25,0)) -> 11 | G5: =IF(Paramètres!$B$25=0,0,ROUNDUP(Prévisions!G7/Paramètres!$B$25,0)) -> 13 | H5: =IF(Paramètres!$B$25=0,0,ROUNDUP(Prévisions!H7/Paramètres!$B$25,0)) -> 15 | I5: =IF(Paramètres!$B$25=0,0,ROUNDUP(Prévisions!I7/Paramètres!$B$25,0)) -> 18 | ... V5: =IF(Paramètres!$B$25=0,0,ROUNDUP(Prévisions!V7/Paramètres!$B$25,0)) -> 8 | W5: =SUM(B5:V5) -> 311
A6: Transport des aliments (FCFA) | B6: =B5*Paramètres!$B$26 -> 15000 | C6: =C5*Paramètres!$B$26 -> 60000 | D6: =D5*Paramètres!$B$26 -> 90000 | E6: =E5*Paramètres!$B$26 -> 135000 | F6: =F5*Paramètres!$B$26 -> 165000 | G6: =G5*Paramètres!$B$26 -> 195000 | H6: =H5*Paramètres!$B$26 -> 225000 | I6: =I5*Paramètres!$B$26 -> 270000 | ... V6: =V5*Paramètres!$B$26 -> 120000 | W6: =SUM(B6:V6) -> 4665000
A7: Voyages poissons (nb) | B7: =IF(Paramètres!$B$27=0,0,ROUNDUP(Prévisions!B24*1000/Paramètres!$B$27,0)) -> 0 | C7: =IF(Paramètres!$B$27=0,0,ROUNDUP(Prévisions!C24*1000/Paramètres!$B$27,0)) -> 0 | D7: =IF(Paramètres!$B$27=0,0,ROUNDUP(Prévisions!D24*1000/Paramètres!$B$27,0)) -> 3 | E7: =IF(Paramètres!$B$27=0,0,ROUNDUP(Prévisions!E24*1000/Paramètres!$B$27,0)) -> 3 | F7: =IF(Paramètres!$B$27=0,0,ROUNDUP(Prévisions!F24*1000/Paramètres!$B$27,0)) -> 6 | G7: =IF(Paramètres!$B$27=0,0,ROUNDUP(Prévisions!G24*1000/Paramètres!$B$27,0)) -> 6 | H7: =IF(Paramètres!$B$27=0,0,ROUNDUP(Prévisions!H24*1000/Paramètres!$B$27,0)) -> 7 | I7: =IF(Paramètres!$B$27=0,0,ROUNDUP(Prévisions!I24*1000/Paramètres!$B$27,0)) -> 8 | ... V7: =IF(Paramètres!$B$27=0,0,ROUNDUP(Prévisions!V24*1000/Paramètres!$B$27,0)) -> 10 | W7: =SUM(B7:V7) -> 163
A8: Livraison des poissons (FCFA) | B8: =B7*Paramètres!$B$28 -> 0 | C8: =C7*Paramètres!$B$28 -> 0 | D8: =D7*Paramètres!$B$28 -> 75000 | E8: =E7*Paramètres!$B$28 -> 75000 | F8: =F7*Paramètres!$B$28 -> 150000 | G8: =G7*Paramètres!$B$28 -> 150000 | H8: =H7*Paramètres!$B$28 -> 175000 | I8: =I7*Paramètres!$B$28 -> 200000 | ... V8: =V7*Paramètres!$B$28 -> 250000 | W8: =SUM(B8:V8) -> 4075000
A9: Voyages alevins (nb) | B9: =IF(Paramètres!$B$29=0,0,ROUNDUP(Prévisions!B5/Paramètres!$B$29,0)) -> 1 | C9: =IF(Paramètres!$B$29=0,0,ROUNDUP(Prévisions!C5/Paramètres!$B$29,0)) -> 1 | D9: =IF(Paramètres!$B$29=0,0,ROUNDUP(Prévisions!D5/Paramètres!$B$29,0)) -> 2 | E9: =IF(Paramètres!$B$29=0,0,ROUNDUP(Prévisions!E5/Paramètres!$B$29,0)) -> 2 | F9: =IF(Paramètres!$B$29=0,0,ROUNDUP(Prévisions!F5/Paramètres!$B$29,0)) -> 2 | G9: =IF(Paramètres!$B$29=0,0,ROUNDUP(Prévisions!G5/Paramètres!$B$29,0)) -> 2 | H9: =IF(Paramètres!$B$29=0,0,ROUNDUP(Prévisions!H5/Paramètres!$B$29,0)) -> 3 | I9: =IF(Paramètres!$B$29=0,0,ROUNDUP(Prévisions!I5/Paramètres!$B$29,0)) -> 3 | ... V9: =IF(Paramètres!$B$29=0,0,ROUNDUP(Prévisions!V5/Paramètres!$B$29,0)) -> 0 | W9: =SUM(B9:V9) -> 49
A10: Transport des alevins (FCFA) | B10: 0 | C10: =C9*Paramètres!$B$30 -> 30000 | D10: =D9*Paramètres!$B$30 -> 60000 | E10: =E9*Paramètres!$B$30 -> 60000 | F10: =F9*Paramètres!$B$30 -> 60000 | G10: =G9*Paramètres!$B$30 -> 60000 | H10: =H9*Paramètres!$B$30 -> 90000 | I10: =I9*Paramètres!$B$30 -> 90000 | J10: =J9*Paramètres!$B$30 -> 90000 | ... V10: =V9*Paramètres!$B$30 -> 0 | W10: =SUM(B10:V10) -> 1440000
A11: Sous-total logistique (FCFA) | B11: =B6+B8+B10 -> 15000 | C11: =C6+C8+C10 -> 90000 | D11: =D6+D8+D10 -> 225000 | E11: =E6+E8+E10 -> 270000 | F11: =F6+F8+F10 -> 375000 | G11: =G6+G8+G10 -> 405000 | H11: =H6+H8+H10 -> 490000 | I11: =I6+I8+I10 -> 560000 | ... V11: =V6+V8+V10 -> 370000 | W11: =SUM(B11:V11) -> 10180000
A13: CHARGES D'EXPLOITATION — à saisir
A14: Main-d'œuvre et salaires | B14: 500000 | C14: 500000 | D14: 500000 | E14: 500000 | F14: 500000 | G14: 500000 | H14: 500000 | I14: 500000 | J14: 500000 | K14: 500000 | L14: 500000 | M14: 500000 | N14: 500000 | O14: 500000 | P14: 500000 | Q14: 500000 | R14: 500000 | S14: 500000 | T14: 500000 | U14: 500000 | V14: 500000 | W14: =SUM(B14:V14) -> 10500000
A15: Énergie et carburant | B15: 120000 | C15: 120000 | D15: 120000 | E15: 120000 | F15: 120000 | G15: 120000 | H15: 120000 | I15: 120000 | J15: 120000 | K15: 120000 | L15: 120000 | M15: 120000 | N15: 120000 | O15: 120000 | P15: 120000 | Q15: 120000 | R15: 120000 | S15: 120000 | T15: 120000 | U15: 120000 | V15: 120000 | W15: =SUM(B15:V15) -> 2520000
A16: Eau et pompage | B16: 0 | C16: 0 | D16: 0 | E16: 0 | F16: 0 | G16: 0 | H16: 0 | I16: 0 | J16: 0 | K16: 0 | L16: 0 | M16: 0 | N16: 0 | O16: 0 | P16: 0 | Q16: 0 | R16: 0 | S16: 0 | T16: 0 | U16: 0 | V16: 0 | W16: =SUM(B16:V16) -> 0
A17: Entretien bassins et matériel | W17: =SUM(B17:V17) -> 0
A18: Produits vétérinaires et intrants | B18: 250000 | C18: 250000 | D18: 250000 | E18: 250000 | F18: 250000 | G18: 250000 | H18: 250000 | I18: 250000 | J18: 250000 | K18: 250000 | L18: 250000 | M18: 250000 | N18: 250000 | O18: 250000 | P18: 250000 | Q18: 250000 | R18: 250000 | S18: 250000 | T18: 250000 | U18: 250000 | V18: 250000 | W18: =SUM(B18:V18) -> 5250000
A19: Loyer et redevances | B19: 110000 | C19: 110000 | D19: 110000 | E19: 110000 | F19: 110000 | G19: 110000 | H19: 110000 | I19: 110000 | J19: 110000 | K19: 110000 | L19: 110000 | M19: 110000 | N19: 110000 | O19: 110000 | P19: 110000 | Q19: 110000 | R19: 110000 | S19: 110000 | T19: 110000 | U19: 110000 | V19: 110000 | W19: =SUM(B19:V19) -> 2310000
A20: Communication et administratif | B20: 0 | C20: 0 | D20: 0 | E20: 0 | F20: 0 | G20: 0 | H20: 0 | I20: 0 | J20: 0 | K20: 0 | L20: 0 | M20: 0 | N20: 0 | O20: 0 | P20: 0 | Q20: 0 | R20: 0 | S20: 0 | T20: 0 | U20: 0 | V20: 0 | W20: =SUM(B20:V20) -> 0
A21: Frais financiers et bancaires | B21: 0 | C21: 0 | D21: 0 | E21: 0 | F21: 0 | G21: 0 | H21: 0 | I21: 0 | J21: 0 | K21: 0 | L21: 0 | M21: 0 | N21: 0 | O21: 0 | P21: 0 | Q21: 0 | R21: 0 | S21: 0 | T21: 0 | U21: 0 | V21: 0 | W21: =SUM(B21:V21) -> 0
A22: Sous-total exploitation (FCFA) | B22: =SUM(B14:B21) -> 980000 | C22: =SUM(C14:C21) -> 980000 | D22: =SUM(D14:D21) -> 980000 | E22: =SUM(E14:E21) -> 980000 | F22: =SUM(F14:F21) -> 980000 | G22: =SUM(G14:G21) -> 980000 | H22: =SUM(H14:H21) -> 980000 | I22: =SUM(I14:I21) -> 980000 | ... V22: =SUM(V14:V21) -> 980000 | W22: =SUM(B22:V22) -> 20580000
A24: DÉPENSES PONCTUELLES — reprises du journal
A25: Opérationnel — général (sans vague) | B25: =SUMIFS(Journal[Montant],Journal[Mois],B$3,Journal[Catégorie],"Opérationnel",Journal[Vague],"") -> 0 | C25: =SUMIFS(Journal[Montant],Journal[Mois],C$3,Journal[Catégorie],"Opérationnel",Journal[Vague],"") -> 0 | D25: =SUMIFS(Journal[Montant],Journal[Mois],D$3,Journal[Catégorie],"Opérationnel",Journal[Vague],"") -> 0 | E25: =SUMIFS(Journal[Montant],Journal[Mois],E$3,Journal[Catégorie],"Opérationnel",Journal[Vague],"") -> 0 | F25: =SUMIFS(Journal[Montant],Journal[Mois],F$3,Journal[Catégorie],"Opérationnel",Journal[Vague],"") -> 0 | G25: =SUMIFS(Journal[Montant],Journal[Mois],G$3,Journal[Catégorie],"Opérationnel",Journal[Vague],"") -> 0 | H25: =SUMIFS(Journal[Montant],Journal[Mois],H$3,Journal[Catégorie],"Opérationnel",Journal[Vague],"") -> 0 | I25: =SUMIFS(Journal[Montant],Journal[Mois],I$3,Journal[Catégorie],"Opérationnel",Journal[Vague],"") -> 0 | ... V25: =SUMIFS(Journal[Montant],Journal[Mois],V$3,Journal[Catégorie],"Opérationnel",Journal[Vague],"") -> 0 | W25: =SUM(B25:V25) -> 0
A26: Opérationnel — affecté à une vague | B26: =SUMIFS(Journal[Montant],Journal[Mois],B$3,Journal[Catégorie],"Opérationnel",Journal[Vague],"<>") -> 0 | C26: =SUMIFS(Journal[Montant],Journal[Mois],C$3,Journal[Catégorie],"Opérationnel",Journal[Vague],"<>") -> 0 | D26: =SUMIFS(Journal[Montant],Journal[Mois],D$3,Journal[Catégorie],"Opérationnel",Journal[Vague],"<>") -> 0 | E26: =SUMIFS(Journal[Montant],Journal[Mois],E$3,Journal[Catégorie],"Opérationnel",Journal[Vague],"<>") -> 0 | F26: =SUMIFS(Journal[Montant],Journal[Mois],F$3,Journal[Catégorie],"Opérationnel",Journal[Vague],"<>") -> 0 | G26: =SUMIFS(Journal[Montant],Journal[Mois],G$3,Journal[Catégorie],"Opérationnel",Journal[Vague],"<>") -> 0 | H26: =SUMIFS(Journal[Montant],Journal[Mois],H$3,Journal[Catégorie],"Opérationnel",Journal[Vague],"<>") -> 0 | I26: =SUMIFS(Journal[Montant],Journal[Mois],I$3,Journal[Catégorie],"Opérationnel",Journal[Vague],"<>") -> 0 | ... V26: =SUMIFS(Journal[Montant],Journal[Mois],V$3,Journal[Catégorie],"Opérationnel",Journal[Vague],"<>") -> 0 | W26: =SUM(B26:V26) -> 0
A27: Investissement / exceptionnel (hors CP)
A28: Crédits | B28: =SUMIFS(Journal[Montant],Journal[Mois],B$3,Journal[Catégorie],"Investissement") -> 0 | C28: =SUMIFS(Journal[Montant],Journal[Mois],C$3,Journal[Catégorie],"Investissement") -> 0 | D28: =SUMIFS(Journal[Montant],Journal[Mois],D$3,Journal[Catégorie],"Investissement") -> 0 | E28: =SUMIFS(Journal[Montant],Journal[Mois],E$3,Journal[Catégorie],"Investissement") -> 0 | F28: =SUMIFS(Journal[Montant],Journal[Mois],F$3,Journal[Catégorie],"Investissement") -> 0 | G28: 5000000 | H28: 5000000 | I28: =SUMIFS(Journal[Montant],Journal[Mois],I$3,Journal[Catégorie],"Investissement") -> 0 | J28: 4000000 | K28: =SUMIFS(Journal[Montant],Journal[Mois],K$3,Journal[Catégorie],"Investissement") -> 0 | L28: 4000000 | M28: =SUMIFS(Journal[Montant],Journal[Mois],M$3,Journal[Catégorie],"Investissement") -> 0 | N28: =SUMIFS(Journal[Montant],Journal[Mois],N$3,Journal[Catégorie],"Investissement") -> 0 | O28: =SUMIFS(Journal[Montant],Journal[Mois],O$3,Journal[Catégorie],"Investissement") -> 0 | P28: =SUMIFS(Journal[Montant],Journal[Mois],P$3,Journal[Catégorie],"Investissement") -> 0 | Q28: =SUMIFS(Journal[Montant],Journal[Mois],Q$3,Journal[Catégorie],"Investissement") -> 0 | R28: =SUMIFS(Journal[Montant],Journal[Mois],R$3,Journal[Catégorie],"Investissement") -> 0 | S28: =SUMIFS(Journal[Montant],Journal[Mois],S$3,Journal[Catégorie],"Investissement") -> 0 | T28: =SUMIFS(Journal[Montant],Journal[Mois],T$3,Journal[Catégorie],"Investissement") -> 0 | ... V28: =SUMIFS(Journal[Montant],Journal[Mois],V$3,Journal[Catégorie],"Investissement") -> 0 | W28: =SUM(B28:V28) -> 18000000
A29: Sous-total journal (FCFA) | B29: =SUM(B25:B28) -> 0 | C29: =SUM(C25:C28) -> 0 | D29: =SUM(D25:D28) -> 0 | E29: =SUM(E25:E28) -> 0 | F29: =SUM(F25:F28) -> 0 | G29: =SUM(G25:G28) -> 5000000 | H29: =SUM(H25:H28) -> 5000000 | I29: =SUM(I25:I28) -> 0 | ... V29: =SUM(V25:V28) -> 0 | W29: =SUM(B29:V29) -> 18000000
A31: Charges opérationnelles générales du mois (base de répartition) | B31: =B11+B22+B25 -> 995000 | C31: =C11+C22+C25 -> 1070000 | D31: =D11+D22+D25 -> 1205000 | E31: =E11+E22+E25 -> 1250000 | F31: =F11+F22+F25 -> 1355000 | G31: =G11+G22+G25 -> 1385000 | H31: =H11+H22+H25 -> 1470000 | I31: =I11+I22+I25 -> 1540000 | ... V31: =V11+V22+V25 -> 1350000 | W31: =SUM(B31:V31) -> 30760000
A32: CHARGES OPÉRATIONNELLES DU MOIS — entrent dans le coût de production | B32: =B31+B26 -> 995000 | C32: =C31+C26 -> 1070000 | D32: =D31+D26 -> 1205000 | E32: =E31+E26 -> 1250000 | F32: =F31+F26 -> 1355000 | G32: =G31+G26 -> 1385000 | H32: =H31+H26 -> 1470000 | I32: =I31+I26 -> 1540000 | ... V32: =V31+V26 -> 1350000 | W32: =SUM(B32:V32) -> 30760000
A33: Investissements et exceptionnels — hors coût de production | B33: =B28 -> 0 | C33: =C28 -> 0 | D33: =D28 -> 0 | E33: =E28 -> 0 | F33: =F28 -> 0 | G33: =G28 -> 5000000 | H33: =H28 -> 5000000 | I33: =I28 -> 0 | J33: 4000000 | K33: 16400000 | L33: =L28 -> 4000000 | M33: =M28 -> 0 | N33: =N28 -> 0 | O33: =O28 -> 0 | P33: =P28 -> 0 | Q33: =Q28 -> 0 | R33: =R28 -> 0 | S33: =S28 -> 0 | ... V33: =V28 -> 0 | W33: =SUM(B33:V33) -> 34400000
A34: TOTAL DÉPENSES DÉTAILLÉES (FCFA) | B34: =B32+B33 -> 995000 | C34: =C32+C33 -> 1070000 | D34: =D32+D33 -> 1205000 | E34: =E32+E33 -> 1250000 | F34: =F32+F33 -> 1355000 | G34: =G32+G33 -> 6385000 | H34: =H32+H33 -> 6470000 | I34: =I32+I33 -> 1540000 | ... V34: =V32+V33 -> 1350000 | W34: =SUM(B34:V34) -> 65160000
A36: Rappel — dépense aliments (FCFA) | B36: =Prévisions!B28 -> 698400 | C36: =Prévisions!C28 -> 3004000 | D36: =Prévisions!D28 -> 5534464 | E36: =Prévisions!E28 -> 7747840 | F36: =Prévisions!F28 -> 9840736 | G36: =Prévisions!G28 -> 11190432 | H36: =Prévisions!H28 -> 13565988 | I36: =Prévisions!I28 -> 15945900 | ... V36: =Prévisions!V28 -> 6556500 | W36: =SUM(B36:V36) -> 277369600
A37: Rappel — dépense alevins (FCFA) | B37: =Prévisions!B29 -> 0 | C37: =Prévisions!C29 -> 0 | D37: =Prévisions!D29 -> 0 | E37: =Prévisions!E29 -> 0 | F37: =Prévisions!F29 -> 0 | G37: =Prévisions!G29 -> 0 | H37: =Prévisions!H29 -> 0 | I37: =Prévisions!I29 -> 0 | ... V37: =Prévisions!V29 -> 0 | W37: =SUM(B37:V37) -> 0
A38: COÛT COMPLET DU MOIS (FCFA) | B38: =B34+B36+B37 -> 1693400 | C38: =C34+C36+C37 -> 4074000 | D38: =D34+D36+D37 -> 6739464 | E38: =E34+E36+E37 -> 8997840 | F38: =F34+F36+F37 -> 11195736 | G38: =G34+G36+G37 -> 17575432 | H38: =H34+H36+H37 -> 20035988 | I38: =I34+I36+I37 -> 17485900 | ... V38: =V34+V36+V37 -> 7906500 | W38: =SUM(B38:V38) -> 342529600

Sheet Journal dépenses
A1: JOURNAL DES DÉPENSES PONCTUELLES ET AFFECTÉES
A2: Une ligne par dépense. Mois : tapez le 1er du mois (ex. 01/11/2026). Vague : laissez vide si la dépense est générale. Catégorie : « Opérationnel » entre dans le coût de production, « Investissement » n'y entre pas. Ajoutez des lignes en tapant simplement sous la dernière — le tableau s'étend tout seul.
A4: Mois | B4: Vague | C4: Libellé | D4: Catégorie | E4: Montant | F4: FCFA
A5: 46327 | B5: V4 | C5: Exemple — 2 bacs de grossissement | D5: Investissement | E5: 0
A6: 46327 | C6: Exemple — analyse d'eau | D6: Opérationnel | E6: 0

Sheet Gantt vagues
A1: GANTT DES VAGUES — cycle de chaque vague dans le temps
A2: Une ligne par vague, une colonne par mois. M1 = empoissonnement et démarrage ; M2 = croissance, premières ventes en fin de mois ; M3 = gros des ventes jusqu'à la fin du stock.
A3: Vague | B3: Objectif (t) | C3: 46235 | D3: 46266 | E3: 46296 | F3: 46327 | G3: 46357 | H3: 46388 | I3: 46419 | J3: 46447 | K3: 46478 | L3: 46508 | M3: 46539 | N3: 46569 | O3: 46600 | P3: 46631 | Q3: 46661 | R3: 46692 | S3: 46722 | T3: 46753 | U3: 46784 | V3: 46813 | W3: 46844
A4: =Empoissonnement!A4 -> V1 | B4: =Empoissonnement!C4 -> 4 | C4: =IF(OR((YEAR(C$3)-YEAR(Empoissonnement!$B4))*12+MONTH(C$3)-MONTH(Empoissonnement!$B4)<0,(YEAR(C$3)-YEAR(Empoissonnement!$B4))*12+MONTH(C$3)-MONTH(Empoissonnement!$B4)>2),"",CHOOSE((YEAR(C$3)-YEAR(Empoissonnement!$B4))*12+MONTH(C$3)-MONTH(Empoissonnement!$B4)+1,"M1","M2-ventes","M3-ventes")) -> M1 | D4: =IF(OR((YEAR(D$3)-YEAR(Empoissonnement!$B4))*12+MONTH(D$3)-MONTH(Empoissonnement!$B4)<0,(YEAR(D$3)-YEAR(Empoissonnement!$B4))*12+MONTH(D$3)-MONTH(Empoissonnement!$B4)>2),"",CHOOSE((YEAR(D$3)-YEAR(Empoissonnement!$B4))*12+MONTH(D$3)-MONTH(Empoissonnement!$B4)+1,"M1","M2-ventes","M3-ventes")) -> M2-ventes | E4: =IF(OR((YEAR(E$3)-YEAR(Empoissonnement!$B4))*12+MONTH(E$3)-MONTH(Empoissonnement!$B4)<0,(YEAR(E$3)-YEAR(Empoissonnement!$B4))*12+MONTH(E$3)-MONTH(Empoissonnement!$B4)>2),"",CHOOSE((YEAR(E$3)-YEAR(Empoissonnement!$B4))*12+MONTH(E$3)-MONTH(Empoissonnement!$B4)+1,"M1","M2-ventes","M3-ventes")) -> M3-ventes | F4: =IF(OR((YEAR(F$3)-YEAR(Empoissonnement!$B4))*12+MONTH(F$3)-MONTH(Empoissonnement!$B4)<0,(YEAR(F$3)-YEAR(Empoissonnement!$B4))*12+MONTH(F$3)-MONTH(Empoissonnement!$B4)>2),"",CHOOSE((YEAR(F$3)-YEAR(Empoissonnement!$B4))*12+MONTH(F$3)-MONTH(Empoissonnement!$B4)+1,"M1","M2-ventes","M3-ventes")) | G4: =IF(OR((YEAR(G$3)-YEAR(Empoissonnement!$B4))*12+MONTH(G$3)-MONTH(Empoissonnement!$B4)<0,(YEAR(G$3)-YEAR(Empoissonnement!$B4))*12+MONTH(G$3)-MONTH(Empoissonnement!$B4)>2),"",CHOOSE((YEAR(G$3)-YEAR(Empoissonnement!$B4))*12+MONTH(G$3)-MONTH(Empoissonnement!$B4)+1,"M1","M2-ventes","M3-ventes")) | H4: =IF(OR((YEAR(H$3)-YEAR(Empoissonnement!$B4))*12+MONTH(H$3)-MONTH(Empoissonnement!$B4)<0,(YEAR(H$3)-YEAR(Empoissonnement!$B4))*12+MONTH(H$3)-MONTH(Empoissonnement!$B4)>2),"",CHOOSE((YEAR(H$3)-YEAR(Empoissonnement!$B4))*12+MONTH(H$3)-MONTH(Empoissonnement!$B4)+1,"M1","M2-ventes","M3-ventes")) | I4: =IF(OR((YEAR(I$3)-YEAR(Empoissonnement!$B4))*12+MONTH(I$3)-MONTH(Empoissonnement!$B4)<0,(YEAR(I$3)-YEAR(Empoissonnement!$B4))*12+MONTH(I$3)-MONTH(Empoissonnement!$B4)>2),"",CHOOSE((YEAR(I$3)-YEAR(Empoissonnement!$B4))*12+MONTH(I$3)-MONTH(Empoissonnement!$B4)+1,"M1","M2-ventes","M3-ventes")) | J4: =IF(OR((YEAR(J$3)-YEAR(Empoissonnement!$B4))*12+MONTH(J$3)-MONTH(Empoissonnement!$B4)<0,(YEAR(J$3)-YEAR(Empoissonnement!$B4))*12+MONTH(J$3)-MONTH(Empoissonnement!$B4)>2),"",CHOOSE((YEAR(J$3)-YEAR(Empoissonnement!$B4))*12+MONTH(J$3)-MONTH(Empoissonnement!$B4)+1,"M1","M2-ventes","M3-ventes")) | ... W4: =IF(OR((YEAR(W$3)-YEAR(Empoissonnement!$B4))*12+MONTH(W$3)-MONTH(Empoissonnement!$B4)<0,(YEAR(W$3)-YEAR(Empoissonnement!$B4))*12+MONTH(W$3)-MONTH(Empoissonnement!$B4)>2),"",CHOOSE((YEAR(W$3)-YEAR(Empoissonnement!$B4))*12+MONTH(W$3)-MONTH(Empoissonnement!$B4)+1,"M1","M2-ventes","M3-ventes"))
A5: =Empoissonnement!A5 -> V2 | B5: =Empoissonnement!C5 -> 4 | C5: =IF(OR((YEAR(C$3)-YEAR(Empoissonnement!$B5))*12+MONTH(C$3)-MONTH(Empoissonnement!$B5)<0,(YEAR(C$3)-YEAR(Empoissonnement!$B5))*12+MONTH(C$3)-MONTH(Empoissonnement!$B5)>2),"",CHOOSE((YEAR(C$3)-YEAR(Empoissonnement!$B5))*12+MONTH(C$3)-MONTH(Empoissonnement!$B5)+1,"M1","M2-ventes","M3-ventes")) | D5: =IF(OR((YEAR(D$3)-YEAR(Empoissonnement!$B5))*12+MONTH(D$3)-MONTH(Empoissonnement!$B5)<0,(YEAR(D$3)-YEAR(Empoissonnement!$B5))*12+MONTH(D$3)-MONTH(Empoissonnement!$B5)>2),"",CHOOSE((YEAR(D$3)-YEAR(Empoissonnement!$B5))*12+MONTH(D$3)-MONTH(Empoissonnement!$B5)+1,"M1","M2-ventes","M3-ventes")) -> M1 | E5: =IF(OR((YEAR(E$3)-YEAR(Empoissonnement!$B5))*12+MONTH(E$3)-MONTH(Empoissonnement!$B5)<0,(YEAR(E$3)-YEAR(Empoissonnement!$B5))*12+MONTH(E$3)-MONTH(Empoissonnement!$B5)>2),"",CHOOSE((YEAR(E$3)-YEAR(Empoissonnement!$B5))*12+MONTH(E$3)-MONTH(Empoissonnement!$B5)+1,"M1","M2-ventes","M3-ventes")) -> M2-ventes | F5: =IF(OR((YEAR(F$3)-YEAR(Empoissonnement!$B5))*12+MONTH(F$3)-MONTH(Empoissonnement!$B5)<0,(YEAR(F$3)-YEAR(Empoissonnement!$B5))*12+MONTH(F$3)-MONTH(Empoissonnement!$B5)>2),"",CHOOSE((YEAR(F$3)-YEAR(Empoissonnement!$B5))*12+MONTH(F$3)-MONTH(Empoissonnement!$B5)+1,"M1","M2-ventes","M3-ventes")) -> M3-ventes | G5: =IF(OR((YEAR(G$3)-YEAR(Empoissonnement!$B5))*12+MONTH(G$3)-MONTH(Empoissonnement!$B5)<0,(YEAR(G$3)-YEAR(Empoissonnement!$B5))*12+MONTH(G$3)-MONTH(Empoissonnement!$B5)>2),"",CHOOSE((YEAR(G$3)-YEAR(Empoissonnement!$B5))*12+MONTH(G$3)-MONTH(Empoissonnement!$B5)+1,"M1","M2-ventes","M3-ventes")) | H5: =IF(OR((YEAR(H$3)-YEAR(Empoissonnement!$B5))*12+MONTH(H$3)-MONTH(Empoissonnement!$B5)<0,(YEAR(H$3)-YEAR(Empoissonnement!$B5))*12+MONTH(H$3)-MONTH(Empoissonnement!$B5)>2),"",CHOOSE((YEAR(H$3)-YEAR(Empoissonnement!$B5))*12+MONTH(H$3)-MONTH(Empoissonnement!$B5)+1,"M1","M2-ventes","M3-ventes")) | I5: =IF(OR((YEAR(I$3)-YEAR(Empoissonnement!$B5))*12+MONTH(I$3)-MONTH(Empoissonnement!$B5)<0,(YEAR(I$3)-YEAR(Empoissonnement!$B5))*12+MONTH(I$3)-MONTH(Empoissonnement!$B5)>2),"",CHOOSE((YEAR(I$3)-YEAR(Empoissonnement!$B5))*12+MONTH(I$3)-MONTH(Empoissonnement!$B5)+1,"M1","M2-ventes","M3-ventes")) | J5: =IF(OR((YEAR(J$3)-YEAR(Empoissonnement!$B5))*12+MONTH(J$3)-MONTH(Empoissonnement!$B5)<0,(YEAR(J$3)-YEAR(Empoissonnement!$B5))*12+MONTH(J$3)-MONTH(Empoissonnement!$B5)>2),"",CHOOSE((YEAR(J$3)-YEAR(Empoissonnement!$B5))*12+MONTH(J$3)-MONTH(Empoissonnement!$B5)+1,"M1","M2-ventes","M3-ventes")) | ... W5: =IF(OR((YEAR(W$3)-YEAR(Empoissonnement!$B5))*12+MONTH(W$3)-MONTH(Empoissonnement!$B5)<0,(YEAR(W$3)-YEAR(Empoissonnement!$B5))*12+MONTH(W$3)-MONTH(Empoissonnement!$B5)>2),"",CHOOSE((YEAR(W$3)-YEAR(Empoissonnement!$B5))*12+MONTH(W$3)-MONTH(Empoissonnement!$B5)+1,"M1","M2-ventes","M3-ventes"))
A6: =Empoissonnement!A6 -> V3 | B6: =Empoissonnement!C6 -> 8 | C6: =IF(OR((YEAR(C$3)-YEAR(Empoissonnement!$B6))*12+MONTH(C$3)-MONTH(Empoissonnement!$B6)<0,(YEAR(C$3)-YEAR(Empoissonnement!$B6))*12+MONTH(C$3)-MONTH(Empoissonnement!$B6)>2),"",CHOOSE((YEAR(C$3)-YEAR(Empoissonnement!$B6))*12+MONTH(C$3)-MONTH(Empoissonnement!$B6)+1,"M1","M2-ventes","M3-ventes")) | D6: =IF(OR((YEAR(D$3)-YEAR(Empoissonnement!$B6))*12+MONTH(D$3)-MONTH(Empoissonnement!$B6)<0,(YEAR(D$3)-YEAR(Empoissonnement!$B6))*12+MONTH(D$3)-MONTH(Empoissonnement!$B6)>2),"",CHOOSE((YEAR(D$3)-YEAR(Empoissonnement!$B6))*12+MONTH(D$3)-MONTH(Empoissonnement!$B6)+1,"M1","M2-ventes","M3-ventes")) | E6: =IF(OR((YEAR(E$3)-YEAR(Empoissonnement!$B6))*12+MONTH(E$3)-MONTH(Empoissonnement!$B6)<0,(YEAR(E$3)-YEAR(Empoissonnement!$B6))*12+MONTH(E$3)-MONTH(Empoissonnement!$B6)>2),"",CHOOSE((YEAR(E$3)-YEAR(Empoissonnement!$B6))*12+MONTH(E$3)-MONTH(Empoissonnement!$B6)+1,"M1","M2-ventes","M3-ventes")) -> M1 | F6: =IF(OR((YEAR(F$3)-YEAR(Empoissonnement!$B6))*12+MONTH(F$3)-MONTH(Empoissonnement!$B6)<0,(YEAR(F$3)-YEAR(Empoissonnement!$B6))*12+MONTH(F$3)-MONTH(Empoissonnement!$B6)>2),"",CHOOSE((YEAR(F$3)-YEAR(Empoissonnement!$B6))*12+MONTH(F$3)-MONTH(Empoissonnement!$B6)+1,"M1","M2-ventes","M3-ventes")) -> M2-ventes | G6: =IF(OR((YEAR(G$3)-YEAR(Empoissonnement!$B6))*12+MONTH(G$3)-MONTH(Empoissonnement!$B6)<0,(YEAR(G$3)-YEAR(Empoissonnement!$B6))*12+MONTH(G$3)-MONTH(Empoissonnement!$B6)>2),"",CHOOSE((YEAR(G$3)-YEAR(Empoissonnement!$B6))*12+MONTH(G$3)-MONTH(Empoissonnement!$B6)+1,"M1","M2-ventes","M3-ventes")) -> M3-ventes | H6: =IF(OR((YEAR(H$3)-YEAR(Empoissonnement!$B6))*12+MONTH(H$3)-MONTH(Empoissonnement!$B6)<0,(YEAR(H$3)-YEAR(Empoissonnement!$B6))*12+MONTH(H$3)-MONTH(Empoissonnement!$B6)>2),"",CHOOSE((YEAR(H$3)-YEAR(Empoissonnement!$B6))*12+MONTH(H$3)-MONTH(Empoissonnement!$B6)+1,"M1","M2-ventes","M3-ventes")) | I6: =IF(OR((YEAR(I$3)-YEAR(Empoissonnement!$B6))*12+MONTH(I$3)-MONTH(Empoissonnement!$B6)<0,(YEAR(I$3)-YEAR(Empoissonnement!$B6))*12+MONTH(I$3)-MONTH(Empoissonnement!$B6)>2),"",CHOOSE((YEAR(I$3)-YEAR(Empoissonnement!$B6))*12+MONTH(I$3)-MONTH(Empoissonnement!$B6)+1,"M1","M2-ventes","M3-ventes")) | J6: =IF(OR((YEAR(J$3)-YEAR(Empoissonnement!$B6))*12+MONTH(J$3)-MONTH(Empoissonnement!$B6)<0,(YEAR(J$3)-YEAR(Empoissonnement!$B6))*12+MONTH(J$3)-MONTH(Empoissonnement!$B6)>2),"",CHOOSE((YEAR(J$3)-YEAR(Empoissonnement!$B6))*12+MONTH(J$3)-MONTH(Empoissonnement!$B6)+1,"M1","M2-ventes","M3-ventes")) | ... W6: =IF(OR((YEAR(W$3)-YEAR(Empoissonnement!$B6))*12+MONTH(W$3)-MONTH(Empoissonnement!$B6)<0,(YEAR(W$3)-YEAR(Empoissonnement!$B6))*12+MONTH(W$3)-MONTH(Empoissonnement!$B6)>2),"",CHOOSE((YEAR(W$3)-YEAR(Empoissonnement!$B6))*12+MONTH(W$3)-MONTH(Empoissonnement!$B6)+1,"M1","M2-ventes","M3-ventes"))
A7: =Empoissonnement!A7 -> V4 | B7: =Empoissonnement!C7 -> 8 | C7: =IF(OR((YEAR(C$3)-YEAR(Empoissonnement!$B7))*12+MONTH(C$3)-MONTH(Empoissonnement!$B7)<0,(YEAR(C$3)-YEAR(Empoissonnement!$B7))*12+MONTH(C$3)-MONTH(Empoissonnement!$B7)>2),"",CHOOSE((YEAR(C$3)-YEAR(Empoissonnement!$B7))*12+MONTH(C$3)-MONTH(Empoissonnement!$B7)+1,"M1","M2-ventes","M3-ventes")) | D7: =IF(OR((YEAR(D$3)-YEAR(Empoissonnement!$B7))*12+MONTH(D$3)-MONTH(Empoissonnement!$B7)<0,(YEAR(D$3)-YEAR(Empoissonnement!$B7))*12+MONTH(D$3)-MONTH(Empoissonnement!$B7)>2),"",CHOOSE((YEAR(D$3)-YEAR(Empoissonnement!$B7))*12+MONTH(D$3)-MONTH(Empoissonnement!$B7)+1,"M1","M2-ventes","M3-ventes")) | E7: =IF(OR((YEAR(E$3)-YEAR(Empoissonnement!$B7))*12+MONTH(E$3)-MONTH(Empoissonnement!$B7)<0,(YEAR(E$3)-YEAR(Empoissonnement!$B7))*12+MONTH(E$3)-MONTH(Empoissonnement!$B7)>2),"",CHOOSE((YEAR(E$3)-YEAR(Empoissonnement!$B7))*12+MONTH(E$3)-MONTH(Empoissonnement!$B7)+1,"M1","M2-ventes","M3-ventes")) | F7: =IF(OR((YEAR(F$3)-YEAR(Empoissonnement!$B7))*12+MONTH(F$3)-MONTH(Empoissonnement!$B7)<0,(YEAR(F$3)-YEAR(Empoissonnement!$B7))*12+MONTH(F$3)-MONTH(Empoissonnement!$B7)>2),"",CHOOSE((YEAR(F$3)-YEAR(Empoissonnement!$B7))*12+MONTH(F$3)-MONTH(Empoissonnement!$B7)+1,"M1","M2-ventes","M3-ventes")) -> M1 | G7: =IF(OR((YEAR(G$3)-YEAR(Empoissonnement!$B7))*12+MONTH(G$3)-MONTH(Empoissonnement!$B7)<0,(YEAR(G$3)-YEAR(Empoissonnement!$B7))*12+MONTH(G$3)-MONTH(Empoissonnement!$B7)>2),"",CHOOSE((YEAR(G$3)-YEAR(Empoissonnement!$B7))*12+MONTH(G$3)-MONTH(Empoissonnement!$B7)+1,"M1","M2-ventes","M3-ventes")) -> M2-ventes | H7: =IF(OR((YEAR(H$3)-YEAR(Empoissonnement!$B7))*12+MONTH(H$3)-MONTH(Empoissonnement!$B7)<0,(YEAR(H$3)-YEAR(Empoissonnement!$B7))*12+MONTH(H$3)-MONTH(Empoissonnement!$B7)>2),"",CHOOSE((YEAR(H$3)-YEAR(Empoissonnement!$B7))*12+MONTH(H$3)-MONTH(Empoissonnement!$B7)+1,"M1","M2-ventes","M3-ventes")) -> M3-ventes | I7: =IF(OR((YEAR(I$3)-YEAR(Empoissonnement!$B7))*12+MONTH(I$3)-MONTH(Empoissonnement!$B7)<0,(YEAR(I$3)-YEAR(Empoissonnement!$B7))*12+MONTH(I$3)-MONTH(Empoissonnement!$B7)>2),"",CHOOSE((YEAR(I$3)-YEAR(Empoissonnement!$B7))*12+MONTH(I$3)-MONTH(Empoissonnement!$B7)+1,"M1","M2-ventes","M3-ventes")) | J7: =IF(OR((YEAR(J$3)-YEAR(Empoissonnement!$B7))*12+MONTH(J$3)-MONTH(Empoissonnement!$B7)<0,(YEAR(J$3)-YEAR(Empoissonnement!$B7))*12+MONTH(J$3)-MONTH(Empoissonnement!$B7)>2),"",CHOOSE((YEAR(J$3)-YEAR(Empoissonnement!$B7))*12+MONTH(J$3)-MONTH(Empoissonnement!$B7)+1,"M1","M2-ventes","M3-ventes")) | ... W7: =IF(OR((YEAR(W$3)-YEAR(Empoissonnement!$B7))*12+MONTH(W$3)-MONTH(Empoissonnement!$B7)<0,(YEAR(W$3)-YEAR(Empoissonnement!$B7))*12+MONTH(W$3)-MONTH(Empoissonnement!$B7)>2),"",CHOOSE((YEAR(W$3)-YEAR(Empoissonnement!$B7))*12+MONTH(W$3)-MONTH(Empoissonnement!$B7)+1,"M1","M2-ventes","M3-ventes"))
A8: =Empoissonnement!A8 -> V5 | B8: =Empoissonnement!C8 -> 10 | C8: =IF(OR((YEAR(C$3)-YEAR(Empoissonnement!$B8))*12+MONTH(C$3)-MONTH(Empoissonnement!$B8)<0,(YEAR(C$3)-YEAR(Empoissonnement!$B8))*12+MONTH(C$3)-MONTH(Empoissonnement!$B8)>2),"",CHOOSE((YEAR(C$3)-YEAR(Empoissonnement!$B8))*12+MONTH(C$3)-MONTH(Empoissonnement!$B8)+1,"M1","M2-ventes","M3-ventes")) | D8: =IF(OR((YEAR(D$3)-YEAR(Empoissonnement!$B8))*12+MONTH(D$3)-MONTH(Empoissonnement!$B8)<0,(YEAR(D$3)-YEAR(Empoissonnement!$B8))*12+MONTH(D$3)-MONTH(Empoissonnement!$B8)>2),"",CHOOSE((YEAR(D$3)-YEAR(Empoissonnement!$B8))*12+MONTH(D$3)-MONTH(Empoissonnement!$B8)+1,"M1","M2-ventes","M3-ventes")) | E8: =IF(OR((YEAR(E$3)-YEAR(Empoissonnement!$B8))*12+MONTH(E$3)-MONTH(Empoissonnement!$B8)<0,(YEAR(E$3)-YEAR(Empoissonnement!$B8))*12+MONTH(E$3)-MONTH(Empoissonnement!$B8)>2),"",CHOOSE((YEAR(E$3)-YEAR(Empoissonnement!$B8))*12+MONTH(E$3)-MONTH(Empoissonnement!$B8)+1,"M1","M2-ventes","M3-ventes")) | F8: =IF(OR((YEAR(F$3)-YEAR(Empoissonnement!$B8))*12+MONTH(F$3)-MONTH(Empoissonnement!$B8)<0,(YEAR(F$3)-YEAR(Empoissonnement!$B8))*12+MONTH(F$3)-MONTH(Empoissonnement!$B8)>2),"",CHOOSE((YEAR(F$3)-YEAR(Empoissonnement!$B8))*12+MONTH(F$3)-MONTH(Empoissonnement!$B8)+1,"M1","M2-ventes","M3-ventes")) | G8: =IF(OR((YEAR(G$3)-YEAR(Empoissonnement!$B8))*12+MONTH(G$3)-MONTH(Empoissonnement!$B8)<0,(YEAR(G$3)-YEAR(Empoissonnement!$B8))*12+MONTH(G$3)-MONTH(Empoissonnement!$B8)>2),"",CHOOSE((YEAR(G$3)-YEAR(Empoissonnement!$B8))*12+MONTH(G$3)-MONTH(Empoissonnement!$B8)+1,"M1","M2-ventes","M3-ventes")) -> M1 | H8: =IF(OR((YEAR(H$3)-YEAR(Empoissonnement!$B8))*12+MONTH(H$3)-MONTH(Empoissonnement!$B8)<0,(YEAR(H$3)-YEAR(Empoissonnement!$B8))*12+MONTH(H$3)-MONTH(Empoissonnement!$B8)>2),"",CHOOSE((YEAR(H$3)-YEAR(Empoissonnement!$B8))*12+MONTH(H$3)-MONTH(Empoissonnement!$B8)+1,"M1","M2-ventes","M3-ventes")) -> M2-ventes | I8: =IF(OR((YEAR(I$3)-YEAR(Empoissonnement!$B8))*12+MONTH(I$3)-MONTH(Empoissonnement!$B8)<0,(YEAR(I$3)-YEAR(Empoissonnement!$B8))*12+MONTH(I$3)-MONTH(Empoissonnement!$B8)>2),"",CHOOSE((YEAR(I$3)-YEAR(Empoissonnement!$B8))*12+MONTH(I$3)-MONTH(Empoissonnement!$B8)+1,"M1","M2-ventes","M3-ventes")) -> M3-ventes | J8: =IF(OR((YEAR(J$3)-YEAR(Empoissonnement!$B8))*12+MONTH(J$3)-MONTH(Empoissonnement!$B8)<0,(YEAR(J$3)-YEAR(Empoissonnement!$B8))*12+MONTH(J$3)-MONTH(Empoissonnement!$B8)>2),"",CHOOSE((YEAR(J$3)-YEAR(Empoissonnement!$B8))*12+MONTH(J$3)-MONTH(Empoissonnement!$B8)+1,"M1","M2-ventes","M3-ventes")) | ... W8: =IF(OR((YEAR(W$3)-YEAR(Empoissonnement!$B8))*12+MONTH(W$3)-MONTH(Empoissonnement!$B8)<0,(YEAR(W$3)-YEAR(Empoissonnement!$B8))*12+MONTH(W$3)-MONTH(Empoissonnement!$B8)>2),"",CHOOSE((YEAR(W$3)-YEAR(Empoissonnement!$B8))*12+MONTH(W$3)-MONTH(Empoissonnement!$B8)+1,"M1","M2-ventes","M3-ventes"))
A9: =Empoissonnement!A9 -> V6 | B9: =Empoissonnement!C9 -> 12 | C9: =IF(OR((YEAR(C$3)-YEAR(Empoissonnement!$B9))*12+MONTH(C$3)-MONTH(Empoissonnement!$B9)<0,(YEAR(C$3)-YEAR(Empoissonnement!$B9))*12+MONTH(C$3)-MONTH(Empoissonnement!$B9)>2),"",CHOOSE((YEAR(C$3)-YEAR(Empoissonnement!$B9))*12+MONTH(C$3)-MONTH(Empoissonnement!$B9)+1,"M1","M2-ventes","M3-ventes")) | D9: =IF(OR((YEAR(D$3)-YEAR(Empoissonnement!$B9))*12+MONTH(D$3)-MONTH(Empoissonnement!$B9)<0,(YEAR(D$3)-YEAR(Empoissonnement!$B9))*12+MONTH(D$3)-MONTH(Empoissonnement!$B9)>2),"",CHOOSE((YEAR(D$3)-YEAR(Empoissonnement!$B9))*12+MONTH(D$3)-MONTH(Empoissonnement!$B9)+1,"M1","M2-ventes","M3-ventes")) | E9: =IF(OR((YEAR(E$3)-YEAR(Empoissonnement!$B9))*12+MONTH(E$3)-MONTH(Empoissonnement!$B9)<0,(YEAR(E$3)-YEAR(Empoissonnement!$B9))*12+MONTH(E$3)-MONTH(Empoissonnement!$B9)>2),"",CHOOSE((YEAR(E$3)-YEAR(Empoissonnement!$B9))*12+MONTH(E$3)-MONTH(Empoissonnement!$B9)+1,"M1","M2-ventes","M3-ventes")) | F9: =IF(OR((YEAR(F$3)-YEAR(Empoissonnement!$B9))*12+MONTH(F$3)-MONTH(Empoissonnement!$B9)<0,(YEAR(F$3)-YEAR(Empoissonnement!$B9))*12+MONTH(F$3)-MONTH(Empoissonnement!$B9)>2),"",CHOOSE((YEAR(F$3)-YEAR(Empoissonnement!$B9))*12+MONTH(F$3)-MONTH(Empoissonnement!$B9)+1,"M1","M2-ventes","M3-ventes")) | G9: =IF(OR((YEAR(G$3)-YEAR(Empoissonnement!$B9))*12+MONTH(G$3)-MONTH(Empoissonnement!$B9)<0,(YEAR(G$3)-YEAR(Empoissonnement!$B9))*12+MONTH(G$3)-MONTH(Empoissonnement!$B9)>2),"",CHOOSE((YEAR(G$3)-YEAR(Empoissonnement!$B9))*12+MONTH(G$3)-MONTH(Empoissonnement!$B9)+1,"M1","M2-ventes","M3-ventes")) | H9: =IF(OR((YEAR(H$3)-YEAR(Empoissonnement!$B9))*12+MONTH(H$3)-MONTH(Empoissonnement!$B9)<0,(YEAR(H$3)-YEAR(Empoissonnement!$B9))*12+MONTH(H$3)-MONTH(Empoissonnement!$B9)>2),"",CHOOSE((YEAR(H$3)-YEAR(Empoissonnement!$B9))*12+MONTH(H$3)-MONTH(Empoissonnement!$B9)+1,"M1","M2-ventes","M3-ventes")) -> M1 | I9: =IF(OR((YEAR(I$3)-YEAR(Empoissonnement!$B9))*12+MONTH(I$3)-MONTH(Empoissonnement!$B9)<0,(YEAR(I$3)-YEAR(Empoissonnement!$B9))*12+MONTH(I$3)-MONTH(Empoissonnement!$B9)>2),"",CHOOSE((YEAR(I$3)-YEAR(Empoissonnement!$B9))*12+MONTH(I$3)-MONTH(Empoissonnement!$B9)+1,"M1","M2-ventes","M3-ventes")) -> M2-ventes | J9: =IF(OR((YEAR(J$3)-YEAR(Empoissonnement!$B9))*12+MONTH(J$3)-MONTH(Empoissonnement!$B9)<0,(YEAR(J$3)-YEAR(Empoissonnement!$B9))*12+MONTH(J$3)-MONTH(Empoissonnement!$B9)>2),"",CHOOSE((YEAR(J$3)-YEAR(Empoissonnement!$B9))*12+MONTH(J$3)-MONTH(Empoissonnement!$B9)+1,"M1","M2-ventes","M3-ventes")) -> M3-ventes | ... W9: =IF(OR((YEAR(W$3)-YEAR(Empoissonnement!$B9))*12+MONTH(W$3)-MONTH(Empoissonnement!$B9)<0,(YEAR(W$3)-YEAR(Empoissonnement!$B9))*12+MONTH(W$3)-MONTH(Empoissonnement!$B9)>2),"",CHOOSE((YEAR(W$3)-YEAR(Empoissonnement!$B9))*12+MONTH(W$3)-MONTH(Empoissonnement!$B9)+1,"M1","M2-ventes","M3-ventes"))
A10: =Empoissonnement!A10 -> V7 | B10: =Empoissonnement!C10 -> 15 | C10: =IF(OR((YEAR(C$3)-YEAR(Empoissonnement!$B10))*12+MONTH(C$3)-MONTH(Empoissonnement!$B10)<0,(YEAR(C$3)-YEAR(Empoissonnement!$B10))*12+MONTH(C$3)-MONTH(Empoissonnement!$B10)>2),"",CHOOSE((YEAR(C$3)-YEAR(Empoissonnement!$B10))*12+MONTH(C$3)-MONTH(Empoissonnement!$B10)+1,"M1","M2-ventes","M3-ventes")) | D10: =IF(OR((YEAR(D$3)-YEAR(Empoissonnement!$B10))*12+MONTH(D$3)-MONTH(Empoissonnement!$B10)<0,(YEAR(D$3)-YEAR(Empoissonnement!$B10))*12+MONTH(D$3)-MONTH(Empoissonnement!$B10)>2),"",CHOOSE((YEAR(D$3)-YEAR(Empoissonnement!$B10))*12+MONTH(D$3)-MONTH(Empoissonnement!$B10)+1,"M1","M2-ventes","M3-ventes")) | E10: =IF(OR((YEAR(E$3)-YEAR(Empoissonnement!$B10))*12+MONTH(E$3)-MONTH(Empoissonnement!$B10)<0,(YEAR(E$3)-YEAR(Empoissonnement!$B10))*12+MONTH(E$3)-MONTH(Empoissonnement!$B10)>2),"",CHOOSE((YEAR(E$3)-YEAR(Empoissonnement!$B10))*12+MONTH(E$3)-MONTH(Empoissonnement!$B10)+1,"M1","M2-ventes","M3-ventes")) | F10: =IF(OR((YEAR(F$3)-YEAR(Empoissonnement!$B10))*12+MONTH(F$3)-MONTH(Empoissonnement!$B10)<0,(YEAR(F$3)-YEAR(Empoissonnement!$B10))*12+MONTH(F$3)-MONTH(Empoissonnement!$B10)>2),"",CHOOSE((YEAR(F$3)-YEAR(Empoissonnement!$B10))*12+MONTH(F$3)-MONTH(Empoissonnement!$B10)+1,"M1","M2-ventes","M3-ventes")) | G10: =IF(OR((YEAR(G$3)-YEAR(Empoissonnement!$B10))*12+MONTH(G$3)-MONTH(Empoissonnement!$B10)<0,(YEAR(G$3)-YEAR(Empoissonnement!$B10))*12+MONTH(G$3)-MONTH(Empoissonnement!$B10)>2),"",CHOOSE((YEAR(G$3)-YEAR(Empoissonnement!$B10))*12+MONTH(G$3)-MONTH(Empoissonnement!$B10)+1,"M1","M2-ventes","M3-ventes")) | H10: =IF(OR((YEAR(H$3)-YEAR(Empoissonnement!$B10))*12+MONTH(H$3)-MONTH(Empoissonnement!$B10)<0,(YEAR(H$3)-YEAR(Empoissonnement!$B10))*12+MONTH(H$3)-MONTH(Empoissonnement!$B10)>2),"",CHOOSE((YEAR(H$3)-YEAR(Empoissonnement!$B10))*12+MONTH(H$3)-MONTH(Empoissonnement!$B10)+1,"M1","M2-ventes","M3-ventes")) | I10: =IF(OR((YEAR(I$3)-YEAR(Empoissonnement!$B10))*12+MONTH(I$3)-MONTH(Empoissonnement!$B10)<0,(YEAR(I$3)-YEAR(Empoissonnement!$B10))*12+MONTH(I$3)-MONTH(Empoissonnement!$B10)>2),"",CHOOSE((YEAR(I$3)-YEAR(Empoissonnement!$B10))*12+MONTH(I$3)-MONTH(Empoissonnement!$B10)+1,"M1","M2-ventes","M3-ventes")) -> M1 | J10: =IF(OR((YEAR(J$3)-YEAR(Empoissonnement!$B10))*12+MONTH(J$3)-MONTH(Empoissonnement!$B10)<0,(YEAR(J$3)-YEAR(Empoissonnement!$B10))*12+MONTH(J$3)-MONTH(Empoissonnement!$B10)>2),"",CHOOSE((YEAR(J$3)-YEAR(Empoissonnement!$B10))*12+MONTH(J$3)-MONTH(Empoissonnement!$B10)+1,"M1","M2-ventes","M3-ventes")) -> M2-ventes | ... W10: =IF(OR((YEAR(W$3)-YEAR(Empoissonnement!$B10))*12+MONTH(W$3)-MONTH(Empoissonnement!$B10)<0,(YEAR(W$3)-YEAR(Empoissonnement!$B10))*12+MONTH(W$3)-MONTH(Empoissonnement!$B10)>2),"",CHOOSE((YEAR(W$3)-YEAR(Empoissonnement!$B10))*12+MONTH(W$3)-MONTH(Empoissonnement!$B10)+1,"M1","M2-ventes","M3-ventes"))
A11: =Empoissonnement!A11 -> V8 | B11: =Empoissonnement!C11 -> 15 | C11: =IF(OR((YEAR(C$3)-YEAR(Empoissonnement!$B11))*12+MONTH(C$3)-MONTH(Empoissonnement!$B11)<0,(YEAR(C$3)-YEAR(Empoissonnement!$B11))*12+MONTH(C$3)-MONTH(Empoissonnement!$B11)>2),"",CHOOSE((YEAR(C$3)-YEAR(Empoissonnement!$B11))*12+MONTH(C$3)-MONTH(Empoissonnement!$B11)+1,"M1","M2-ventes","M3-ventes")) | D11: =IF(OR((YEAR(D$3)-YEAR(Empoissonnement!$B11))*12+MONTH(D$3)-MONTH(Empoissonnement!$B11)<0,(YEAR(D$3)-YEAR(Empoissonnement!$B11))*12+MONTH(D$3)-MONTH(Empoissonnement!$B11)>2),"",CHOOSE((YEAR(D$3)-YEAR(Empoissonnement!$B11))*12+MONTH(D$3)-MONTH(Empoissonnement!$B11)+1,"M1","M2-ventes","M3-ventes")) | E11: =IF(OR((YEAR(E$3)-YEAR(Empoissonnement!$B11))*12+MONTH(E$3)-MONTH(Empoissonnement!$B11)<0,(YEAR(E$3)-YEAR(Empoissonnement!$B11))*12+MONTH(E$3)-MONTH(Empoissonnement!$B11)>2),"",CHOOSE((YEAR(E$3)-YEAR(Empoissonnement!$B11))*12+MONTH(E$3)-MONTH(Empoissonnement!$B11)+1,"M1","M2-ventes","M3-ventes")) | F11: =IF(OR((YEAR(F$3)-YEAR(Empoissonnement!$B11))*12+MONTH(F$3)-MONTH(Empoissonnement!$B11)<0,(YEAR(F$3)-YEAR(Empoissonnement!$B11))*12+MONTH(F$3)-MONTH(Empoissonnement!$B11)>2),"",CHOOSE((YEAR(F$3)-YEAR(Empoissonnement!$B11))*12+MONTH(F$3)-MONTH(Empoissonnement!$B11)+1,"M1","M2-ventes","M3-ventes")) | G11: =IF(OR((YEAR(G$3)-YEAR(Empoissonnement!$B11))*12+MONTH(G$3)-MONTH(Empoissonnement!$B11)<0,(YEAR(G$3)-YEAR(Empoissonnement!$B11))*12+MONTH(G$3)-MONTH(Empoissonnement!$B11)>2),"",CHOOSE((YEAR(G$3)-YEAR(Empoissonnement!$B11))*12+MONTH(G$3)-MONTH(Empoissonnement!$B11)+1,"M1","M2-ventes","M3-ventes")) | H11: =IF(OR((YEAR(H$3)-YEAR(Empoissonnement!$B11))*12+MONTH(H$3)-MONTH(Empoissonnement!$B11)<0,(YEAR(H$3)-YEAR(Empoissonnement!$B11))*12+MONTH(H$3)-MONTH(Empoissonnement!$B11)>2),"",CHOOSE((YEAR(H$3)-YEAR(Empoissonnement!$B11))*12+MONTH(H$3)-MONTH(Empoissonnement!$B11)+1,"M1","M2-ventes","M3-ventes")) | I11: =IF(OR((YEAR(I$3)-YEAR(Empoissonnement!$B11))*12+MONTH(I$3)-MONTH(Empoissonnement!$B11)<0,(YEAR(I$3)-YEAR(Empoissonnement!$B11))*12+MONTH(I$3)-MONTH(Empoissonnement!$B11)>2),"",CHOOSE((YEAR(I$3)-YEAR(Empoissonnement!$B11))*12+MONTH(I$3)-MONTH(Empoissonnement!$B11)+1,"M1","M2-ventes","M3-ventes")) | J11: =IF(OR((YEAR(J$3)-YEAR(Empoissonnement!$B11))*12+MONTH(J$3)-MONTH(Empoissonnement!$B11)<0,(YEAR(J$3)-YEAR(Empoissonnement!$B11))*12+MONTH(J$3)-MONTH(Empoissonnement!$B11)>2),"",CHOOSE((YEAR(J$3)-YEAR(Empoissonnement!$B11))*12+MONTH(J$3)-MONTH(Empoissonnement!$B11)+1,"M1","M2-ventes","M3-ventes")) -> M1 | ... W11: =IF(OR((YEAR(W$3)-YEAR(Empoissonnement!$B11))*12+MONTH(W$3)-MONTH(Empoissonnement!$B11)<0,(YEAR(W$3)-YEAR(Empoissonnement!$B11))*12+MONTH(W$3)-MONTH(Empoissonnement!$B11)>2),"",CHOOSE((YEAR(W$3)-YEAR(Empoissonnement!$B11))*12+MONTH(W$3)-MONTH(Empoissonnement!$B11)+1,"M1","M2-ventes","M3-ventes"))
A12: =Empoissonnement!A12 -> V9 | B12: =Empoissonnement!C12 -> 15 | C12: =IF(OR((YEAR(C$3)-YEAR(Empoissonnement!$B12))*12+MONTH(C$3)-MONTH(Empoissonnement!$B12)<0,(YEAR(C$3)-YEAR(Empoissonnement!$B12))*12+MONTH(C$3)-MONTH(Empoissonnement!$B12)>2),"",CHOOSE((YEAR(C$3)-YEAR(Empoissonnement!$B12))*12+MONTH(C$3)-MONTH(Empoissonnement!$B12)+1,"M1","M2-ventes","M3-ventes")) | D12: =IF(OR((YEAR(D$3)-YEAR(Empoissonnement!$B12))*12+MONTH(D$3)-MONTH(Empoissonnement!$B12)<0,(YEAR(D$3)-YEAR(Empoissonnement!$B12))*12+MONTH(D$3)-MONTH(Empoissonnement!$B12)>2),"",CHOOSE((YEAR(D$3)-YEAR(Empoissonnement!$B12))*12+MONTH(D$3)-MONTH(Empoissonnement!$B12)+1,"M1","M2-ventes","M3-ventes")) | E12: =IF(OR((YEAR(E$3)-YEAR(Empoissonnement!$B12))*12+MONTH(E$3)-MONTH(Empoissonnement!$B12)<0,(YEAR(E$3)-YEAR(Empoissonnement!$B12))*12+MONTH(E$3)-MONTH(Empoissonnement!$B12)>2),"",CHOOSE((YEAR(E$3)-YEAR(Empoissonnement!$B12))*12+MONTH(E$3)-MONTH(Empoissonnement!$B12)+1,"M1","M2-ventes","M3-ventes")) | F12: =IF(OR((YEAR(F$3)-YEAR(Empoissonnement!$B12))*12+MONTH(F$3)-MONTH(Empoissonnement!$B12)<0,(YEAR(F$3)-YEAR(Empoissonnement!$B12))*12+MONTH(F$3)-MONTH(Empoissonnement!$B12)>2),"",CHOOSE((YEAR(F$3)-YEAR(Empoissonnement!$B12))*12+MONTH(F$3)-MONTH(Empoissonnement!$B12)+1,"M1","M2-ventes","M3-ventes")) | G12: =IF(OR((YEAR(G$3)-YEAR(Empoissonnement!$B12))*12+MONTH(G$3)-MONTH(Empoissonnement!$B12)<0,(YEAR(G$3)-YEAR(Empoissonnement!$B12))*12+MONTH(G$3)-MONTH(Empoissonnement!$B12)>2),"",CHOOSE((YEAR(G$3)-YEAR(Empoissonnement!$B12))*12+MONTH(G$3)-MONTH(Empoissonnement!$B12)+1,"M1","M2-ventes","M3-ventes")) | H12: =IF(OR((YEAR(H$3)-YEAR(Empoissonnement!$B12))*12+MONTH(H$3)-MONTH(Empoissonnement!$B12)<0,(YEAR(H$3)-YEAR(Empoissonnement!$B12))*12+MONTH(H$3)-MONTH(Empoissonnement!$B12)>2),"",CHOOSE((YEAR(H$3)-YEAR(Empoissonnement!$B12))*12+MONTH(H$3)-MONTH(Empoissonnement!$B12)+1,"M1","M2-ventes","M3-ventes")) | I12: =IF(OR((YEAR(I$3)-YEAR(Empoissonnement!$B12))*12+MONTH(I$3)-MONTH(Empoissonnement!$B12)<0,(YEAR(I$3)-YEAR(Empoissonnement!$B12))*12+MONTH(I$3)-MONTH(Empoissonnement!$B12)>2),"",CHOOSE((YEAR(I$3)-YEAR(Empoissonnement!$B12))*12+MONTH(I$3)-MONTH(Empoissonnement!$B12)+1,"M1","M2-ventes","M3-ventes")) | J12: =IF(OR((YEAR(J$3)-YEAR(Empoissonnement!$B12))*12+MONTH(J$3)-MONTH(Empoissonnement!$B12)<0,(YEAR(J$3)-YEAR(Empoissonnement!$B12))*12+MONTH(J$3)-MONTH(Empoissonnement!$B12)>2),"",CHOOSE((YEAR(J$3)-YEAR(Empoissonnement!$B12))*12+MONTH(J$3)-MONTH(Empoissonnement!$B12)+1,"M1","M2-ventes","M3-ventes")) | ... W12: =IF(OR((YEAR(W$3)-YEAR(Empoissonnement!$B12))*12+MONTH(W$3)-MONTH(Empoissonnement!$B12)<0,(YEAR(W$3)-YEAR(Empoissonnement!$B12))*12+MONTH(W$3)-MONTH(Empoissonnement!$B12)>2),"",CHOOSE((YEAR(W$3)-YEAR(Empoissonnement!$B12))*12+MONTH(W$3)-MONTH(Empoissonnement!$B12)+1,"M1","M2-ventes","M3-ventes"))
A13: =Empoissonnement!A13 -> V10 | B13: =Empoissonnement!C13 -> 15 | C13: =IF(OR((YEAR(C$3)-YEAR(Empoissonnement!$B13))*12+MONTH(C$3)-MONTH(Empoissonnement!$B13)<0,(YEAR(C$3)-YEAR(Empoissonnement!$B13))*12+MONTH(C$3)-MONTH(Empoissonnement!$B13)>2),"",CHOOSE((YEAR(C$3)-YEAR(Empoissonnement!$B13))*12+MONTH(C$3)-MONTH(Empoissonnement!$B13)+1,"M1","M2-ventes","M3-ventes")) | D13: =IF(OR((YEAR(D$3)-YEAR(Empoissonnement!$B13))*12+MONTH(D$3)-MONTH(Empoissonnement!$B13)<0,(YEAR(D$3)-YEAR(Empoissonnement!$B13))*12+MONTH(D$3)-MONTH(Empoissonnement!$B13)>2),"",CHOOSE((YEAR(D$3)-YEAR(Empoissonnement!$B13))*12+MONTH(D$3)-MONTH(Empoissonnement!$B13)+1,"M1","M2-ventes","M3-ventes")) | E13: =IF(OR((YEAR(E$3)-YEAR(Empoissonnement!$B13))*12+MONTH(E$3)-MONTH(Empoissonnement!$B13)<0,(YEAR(E$3)-YEAR(Empoissonnement!$B13))*12+MONTH(E$3)-MONTH(Empoissonnement!$B13)>2),"",CHOOSE((YEAR(E$3)-YEAR(Empoissonnement!$B13))*12+MONTH(E$3)-MONTH(Empoissonnement!$B13)+1,"M1","M2-ventes","M3-ventes")) | F13: =IF(OR((YEAR(F$3)-YEAR(Empoissonnement!$B13))*12+MONTH(F$3)-MONTH(Empoissonnement!$B13)<0,(YEAR(F$3)-YEAR(Empoissonnement!$B13))*12+MONTH(F$3)-MONTH(Empoissonnement!$B13)>2),"",CHOOSE((YEAR(F$3)-YEAR(Empoissonnement!$B13))*12+MONTH(F$3)-MONTH(Empoissonnement!$B13)+1,"M1","M2-ventes","M3-ventes")) | G13: =IF(OR((YEAR(G$3)-YEAR(Empoissonnement!$B13))*12+MONTH(G$3)-MONTH(Empoissonnement!$B13)<0,(YEAR(G$3)-YEAR(Empoissonnement!$B13))*12+MONTH(G$3)-MONTH(Empoissonnement!$B13)>2),"",CHOOSE((YEAR(G$3)-YEAR(Empoissonnement!$B13))*12+MONTH(G$3)-MONTH(Empoissonnement!$B13)+1,"M1","M2-ventes","M3-ventes")) | H13: =IF(OR((YEAR(H$3)-YEAR(Empoissonnement!$B13))*12+MONTH(H$3)-MONTH(Empoissonnement!$B13)<0,(YEAR(H$3)-YEAR(Empoissonnement!$B13))*12+MONTH(H$3)-MONTH(Empoissonnement!$B13)>2),"",CHOOSE((YEAR(H$3)-YEAR(Empoissonnement!$B13))*12+MONTH(H$3)-MONTH(Empoissonnement!$B13)+1,"M1","M2-ventes","M3-ventes")) | I13: =IF(OR((YEAR(I$3)-YEAR(Empoissonnement!$B13))*12+MONTH(I$3)-MONTH(Empoissonnement!$B13)<0,(YEAR(I$3)-YEAR(Empoissonnement!$B13))*12+MONTH(I$3)-MONTH(Empoissonnement!$B13)>2),"",CHOOSE((YEAR(I$3)-YEAR(Empoissonnement!$B13))*12+MONTH(I$3)-MONTH(Empoissonnement!$B13)+1,"M1","M2-ventes","M3-ventes")) | J13: =IF(OR((YEAR(J$3)-YEAR(Empoissonnement!$B13))*12+MONTH(J$3)-MONTH(Empoissonnement!$B13)<0,(YEAR(J$3)-YEAR(Empoissonnement!$B13))*12+MONTH(J$3)-MONTH(Empoissonnement!$B13)>2),"",CHOOSE((YEAR(J$3)-YEAR(Empoissonnement!$B13))*12+MONTH(J$3)-MONTH(Empoissonnement!$B13)+1,"M1","M2-ventes","M3-ventes")) | ... W13: =IF(OR((YEAR(W$3)-YEAR(Empoissonnement!$B13))*12+MONTH(W$3)-MONTH(Empoissonnement!$B13)<0,(YEAR(W$3)-YEAR(Empoissonnement!$B13))*12+MONTH(W$3)-MONTH(Empoissonnement!$B13)>2),"",CHOOSE((YEAR(W$3)-YEAR(Empoissonnement!$B13))*12+MONTH(W$3)-MONTH(Empoissonnement!$B13)+1,"M1","M2-ventes","M3-ventes"))
A14: =Empoissonnement!A14 -> V11 | B14: =Empoissonnement!C14 -> 15 | C14: =IF(OR((YEAR(C$3)-YEAR(Empoissonnement!$B14))*12+MONTH(C$3)-MONTH(Empoissonnement!$B14)<0,(YEAR(C$3)-YEAR(Empoissonnement!$B14))*12+MONTH(C$3)-MONTH(Empoissonnement!$B14)>2),"",CHOOSE((YEAR(C$3)-YEAR(Empoissonnement!$B14))*12+MONTH(C$3)-MONTH(Empoissonnement!$B14)+1,"M1","M2-ventes","M3-ventes")) | D14: =IF(OR((YEAR(D$3)-YEAR(Empoissonnement!$B14))*12+MONTH(D$3)-MONTH(Empoissonnement!$B14)<0,(YEAR(D$3)-YEAR(Empoissonnement!$B14))*12+MONTH(D$3)-MONTH(Empoissonnement!$B14)>2),"",CHOOSE((YEAR(D$3)-YEAR(Empoissonnement!$B14))*12+MONTH(D$3)-MONTH(Empoissonnement!$B14)+1,"M1","M2-ventes","M3-ventes")) | E14: =IF(OR((YEAR(E$3)-YEAR(Empoissonnement!$B14))*12+MONTH(E$3)-MONTH(Empoissonnement!$B14)<0,(YEAR(E$3)-YEAR(Empoissonnement!$B14))*12+MONTH(E$3)-MONTH(Empoissonnement!$B14)>2),"",CHOOSE((YEAR(E$3)-YEAR(Empoissonnement!$B14))*12+MONTH(E$3)-MONTH(Empoissonnement!$B14)+1,"M1","M2-ventes","M3-ventes")) | F14: =IF(OR((YEAR(F$3)-YEAR(Empoissonnement!$B14))*12+MONTH(F$3)-MONTH(Empoissonnement!$B14)<0,(YEAR(F$3)-YEAR(Empoissonnement!$B14))*12+MONTH(F$3)-MONTH(Empoissonnement!$B14)>2),"",CHOOSE((YEAR(F$3)-YEAR(Empoissonnement!$B14))*12+MONTH(F$3)-MONTH(Empoissonnement!$B14)+1,"M1","M2-ventes","M3-ventes")) | G14: =IF(OR((YEAR(G$3)-YEAR(Empoissonnement!$B14))*12+MONTH(G$3)-MONTH(Empoissonnement!$B14)<0,(YEAR(G$3)-YEAR(Empoissonnement!$B14))*12+MONTH(G$3)-MONTH(Empoissonnement!$B14)>2),"",CHOOSE((YEAR(G$3)-YEAR(Empoissonnement!$B14))*12+MONTH(G$3)-MONTH(Empoissonnement!$B14)+1,"M1","M2-ventes","M3-ventes")) | H14: =IF(OR((YEAR(H$3)-YEAR(Empoissonnement!$B14))*12+MONTH(H$3)-MONTH(Empoissonnement!$B14)<0,(YEAR(H$3)-YEAR(Empoissonnement!$B14))*12+MONTH(H$3)-MONTH(Empoissonnement!$B14)>2),"",CHOOSE((YEAR(H$3)-YEAR(Empoissonnement!$B14))*12+MONTH(H$3)-MONTH(Empoissonnement!$B14)+1,"M1","M2-ventes","M3-ventes")) | I14: =IF(OR((YEAR(I$3)-YEAR(Empoissonnement!$B14))*12+MONTH(I$3)-MONTH(Empoissonnement!$B14)<0,(YEAR(I$3)-YEAR(Empoissonnement!$B14))*12+MONTH(I$3)-MONTH(Empoissonnement!$B14)>2),"",CHOOSE((YEAR(I$3)-YEAR(Empoissonnement!$B14))*12+MONTH(I$3)-MONTH(Empoissonnement!$B14)+1,"M1","M2-ventes","M3-ventes")) | J14: =IF(OR((YEAR(J$3)-YEAR(Empoissonnement!$B14))*12+MONTH(J$3)-MONTH(Empoissonnement!$B14)<0,(YEAR(J$3)-YEAR(Empoissonnement!$B14))*12+MONTH(J$3)-MONTH(Empoissonnement!$B14)>2),"",CHOOSE((YEAR(J$3)-YEAR(Empoissonnement!$B14))*12+MONTH(J$3)-MONTH(Empoissonnement!$B14)+1,"M1","M2-ventes","M3-ventes")) | ... W14: =IF(OR((YEAR(W$3)-YEAR(Empoissonnement!$B14))*12+MONTH(W$3)-MONTH(Empoissonnement!$B14)<0,(YEAR(W$3)-YEAR(Empoissonnement!$B14))*12+MONTH(W$3)-MONTH(Empoissonnement!$B14)>2),"",CHOOSE((YEAR(W$3)-YEAR(Empoissonnement!$B14))*12+MONTH(W$3)-MONTH(Empoissonnement!$B14)+1,"M1","M2-ventes","M3-ventes"))
A15: =Empoissonnement!A15 -> V12 | B15: =Empoissonnement!C15 -> 15 | C15: =IF(OR((YEAR(C$3)-YEAR(Empoissonnement!$B15))*12+MONTH(C$3)-MONTH(Empoissonnement!$B15)<0,(YEAR(C$3)-YEAR(Empoissonnement!$B15))*12+MONTH(C$3)-MONTH(Empoissonnement!$B15)>2),"",CHOOSE((YEAR(C$3)-YEAR(Empoissonnement!$B15))*12+MONTH(C$3)-MONTH(Empoissonnement!$B15)+1,"M1","M2-ventes","M3-ventes")) | D15: =IF(OR((YEAR(D$3)-YEAR(Empoissonnement!$B15))*12+MONTH(D$3)-MONTH(Empoissonnement!$B15)<0,(YEAR(D$3)-YEAR(Empoissonnement!$B15))*12+MONTH(D$3)-MONTH(Empoissonnement!$B15)>2),"",CHOOSE((YEAR(D$3)-YEAR(Empoissonnement!$B15))*12+MONTH(D$3)-MONTH(Empoissonnement!$B15)+1,"M1","M2-ventes","M3-ventes")) | E15: =IF(OR((YEAR(E$3)-YEAR(Empoissonnement!$B15))*12+MONTH(E$3)-MONTH(Empoissonnement!$B15)<0,(YEAR(E$3)-YEAR(Empoissonnement!$B15))*12+MONTH(E$3)-MONTH(Empoissonnement!$B15)>2),"",CHOOSE((YEAR(E$3)-YEAR(Empoissonnement!$B15))*12+MONTH(E$3)-MONTH(Empoissonnement!$B15)+1,"M1","M2-ventes","M3-ventes")) | F15: =IF(OR((YEAR(F$3)-YEAR(Empoissonnement!$B15))*12+MONTH(F$3)-MONTH(Empoissonnement!$B15)<0,(YEAR(F$3)-YEAR(Empoissonnement!$B15))*12+MONTH(F$3)-MONTH(Empoissonnement!$B15)>2),"",CHOOSE((YEAR(F$3)-YEAR(Empoissonnement!$B15))*12+MONTH(F$3)-MONTH(Empoissonnement!$B15)+1,"M1","M2-ventes","M3-ventes")) | G15: =IF(OR((YEAR(G$3)-YEAR(Empoissonnement!$B15))*12+MONTH(G$3)-MONTH(Empoissonnement!$B15)<0,(YEAR(G$3)-YEAR(Empoissonnement!$B15))*12+MONTH(G$3)-MONTH(Empoissonnement!$B15)>2),"",CHOOSE((YEAR(G$3)-YEAR(Empoissonnement!$B15))*12+MONTH(G$3)-MONTH(Empoissonnement!$B15)+1,"M1","M2-ventes","M3-ventes")) | H15: =IF(OR((YEAR(H$3)-YEAR(Empoissonnement!$B15))*12+MONTH(H$3)-MONTH(Empoissonnement!$B15)<0,(YEAR(H$3)-YEAR(Empoissonnement!$B15))*12+MONTH(H$3)-MONTH(Empoissonnement!$B15)>2),"",CHOOSE((YEAR(H$3)-YEAR(Empoissonnement!$B15))*12+MONTH(H$3)-MONTH(Empoissonnement!$B15)+1,"M1","M2-ventes","M3-ventes")) | I15: =IF(OR((YEAR(I$3)-YEAR(Empoissonnement!$B15))*12+MONTH(I$3)-MONTH(Empoissonnement!$B15)<0,(YEAR(I$3)-YEAR(Empoissonnement!$B15))*12+MONTH(I$3)-MONTH(Empoissonnement!$B15)>2),"",CHOOSE((YEAR(I$3)-YEAR(Empoissonnement!$B15))*12+MONTH(I$3)-MONTH(Empoissonnement!$B15)+1,"M1","M2-ventes","M3-ventes")) | J15: =IF(OR((YEAR(J$3)-YEAR(Empoissonnement!$B15))*12+MONTH(J$3)-MONTH(Empoissonnement!$B15)<0,(YEAR(J$3)-YEAR(Empoissonnement!$B15))*12+MONTH(J$3)-MONTH(Empoissonnement!$B15)>2),"",CHOOSE((YEAR(J$3)-YEAR(Empoissonnement!$B15))*12+MONTH(J$3)-MONTH(Empoissonnement!$B15)+1,"M1","M2-ventes","M3-ventes")) | ... W15: =IF(OR((YEAR(W$3)-YEAR(Empoissonnement!$B15))*12+MONTH(W$3)-MONTH(Empoissonnement!$B15)<0,(YEAR(W$3)-YEAR(Empoissonnement!$B15))*12+MONTH(W$3)-MONTH(Empoissonnement!$B15)>2),"",CHOOSE((YEAR(W$3)-YEAR(Empoissonnement!$B15))*12+MONTH(W$3)-MONTH(Empoissonnement!$B15)+1,"M1","M2-ventes","M3-ventes"))
... A22: =Empoissonnement!A22 -> V19 | B22: =Empoissonnement!C22 -> 15 | C22: =IF(OR((YEAR(C$3)-YEAR(Empoissonnement!$B22))*12+MONTH(C$3)-MONTH(Empoissonnement!$B22)<0,(YEAR(C$3)-YEAR(Empoissonnement!$B22))*12+MONTH(C$3)-MONTH(Empoissonnement!$B22)>2),"",CHOOSE((YEAR(C$3)-YEAR(Empoissonnement!$B22))*12+MONTH(C$3)-MONTH(Empoissonnement!$B22)+1,"M1","M2-ventes","M3-ventes")) | D22: =IF(OR((YEAR(D$3)-YEAR(Empoissonnement!$B22))*12+MONTH(D$3)-MONTH(Empoissonnement!$B22)<0,(YEAR(D$3)-YEAR(Empoissonnement!$B22))*12+MONTH(D$3)-MONTH(Empoissonnement!$B22)>2),"",CHOOSE((YEAR(D$3)-YEAR(Empoissonnement!$B22))*12+MONTH(D$3)-MONTH(Empoissonnement!$B22)+1,"M1","M2-ventes","M3-ventes")) | E22: =IF(OR((YEAR(E$3)-YEAR(Empoissonnement!$B22))*12+MONTH(E$3)-MONTH(Empoissonnement!$B22)<0,(YEAR(E$3)-YEAR(Empoissonnement!$B22))*12+MONTH(E$3)-MONTH(Empoissonnement!$B22)>2),"",CHOOSE((YEAR(E$3)-YEAR(Empoissonnement!$B22))*12+MONTH(E$3)-MONTH(Empoissonnement!$B22)+1,"M1","M2-ventes","M3-ventes")) | F22: =IF(OR((YEAR(F$3)-YEAR(Empoissonnement!$B22))*12+MONTH(F$3)-MONTH(Empoissonnement!$B22)<0,(YEAR(F$3)-YEAR(Empoissonnement!$B22))*12+MONTH(F$3)-MONTH(Empoissonnement!$B22)>2),"",CHOOSE((YEAR(F$3)-YEAR(Empoissonnement!$B22))*12+MONTH(F$3)-MONTH(Empoissonnement!$B22)+1,"M1","M2-ventes","M3-ventes")) | G22: =IF(OR((YEAR(G$3)-YEAR(Empoissonnement!$B22))*12+MONTH(G$3)-MONTH(Empoissonnement!$B22)<0,(YEAR(G$3)-YEAR(Empoissonnement!$B22))*12+MONTH(G$3)-MONTH(Empoissonnement!$B22)>2),"",CHOOSE((YEAR(G$3)-YEAR(Empoissonnement!$B22))*12+MONTH(G$3)-MONTH(Empoissonnement!$B22)+1,"M1","M2-ventes","M3-ventes")) | H22: =IF(OR((YEAR(H$3)-YEAR(Empoissonnement!$B22))*12+MONTH(H$3)-MONTH(Empoissonnement!$B22)<0,(YEAR(H$3)-YEAR(Empoissonnement!$B22))*12+MONTH(H$3)-MONTH(Empoissonnement!$B22)>2),"",CHOOSE((YEAR(H$3)-YEAR(Empoissonnement!$B22))*12+MONTH(H$3)-MONTH(Empoissonnement!$B22)+1,"M1","M2-ventes","M3-ventes")) | I22: =IF(OR((YEAR(I$3)-YEAR(Empoissonnement!$B22))*12+MONTH(I$3)-MONTH(Empoissonnement!$B22)<0,(YEAR(I$3)-YEAR(Empoissonnement!$B22))*12+MONTH(I$3)-MONTH(Empoissonnement!$B22)>2),"",CHOOSE((YEAR(I$3)-YEAR(Empoissonnement!$B22))*12+MONTH(I$3)-MONTH(Empoissonnement!$B22)+1,"M1","M2-ventes","M3-ventes")) | J22: =IF(OR((YEAR(J$3)-YEAR(Empoissonnement!$B22))*12+MONTH(J$3)-MONTH(Empoissonnement!$B22)<0,(YEAR(J$3)-YEAR(Empoissonnement!$B22))*12+MONTH(J$3)-MONTH(Empoissonnement!$B22)>2),"",CHOOSE((YEAR(J$3)-YEAR(Empoissonnement!$B22))*12+MONTH(J$3)-MONTH(Empoissonnement!$B22)+1,"M1","M2-ventes","M3-ventes")) | ... W22: =IF(OR((YEAR(W$3)-YEAR(Empoissonnement!$B22))*12+MONTH(W$3)-MONTH(Empoissonnement!$B22)<0,(YEAR(W$3)-YEAR(Empoissonnement!$B22))*12+MONTH(W$3)-MONTH(Empoissonnement!$B22)>2),"",CHOOSE((YEAR(W$3)-YEAR(Empoissonnement!$B22))*12+MONTH(W$3)-MONTH(Empoissonnement!$B22)+1,"M1","M2-ventes","M3-ventes")) -> M3-ventes
A24: Légende : | B24: M1 — empoissonnement + démarrage | D24: M2 — croissance, 1res ventes en fin de mois | G24: M3 — gros des ventes, fin du stock

Sheet Prévisions
A1: PRÉVISIONS MENSUELLES — indicateurs en lignes, mois en colonnes
A2: Dépenses aliments et alevins : calculées automatiquement (prix réels de la feuille Aliments, remises incluses). Ligne « Autres dépenses » : total de la feuille Dépenses (logistique calculée + charges saisies). Ventes = 3e mois de chaque vague (répartition pilotée par Paramètres B7/B8). Apport en capital : ligne à saisir librement (fonds propres, prêt, subvention) — elle s'ajoute au chiffre d'affaires dans le total des entrées. Les sacs par granulé reprennent la feuille Besoins aliments.
A3: Indicateur | B3: 46235 | C3: 46266 | D3: 46296 | E3: 46327 | F3: 46357 | G3: 46388 | H3: 46419 | I3: 46447 | J3: 46478 | K3: 46508 | L3: 46539 | M3: 46569 | N3: 46600 | O3: 46631 | P3: 46661 | Q3: 46692 | R3: 46722 | S3: 46753 | T3: 46784 | U3: 46813 | V3: 46844 | W3: TOTAL
A4: Empoissonné (t) | B4: =SUMIFS(Empoissonnement!$C$4:$C$22,Empoissonnement!$B$4:$B$22,B$3) -> 4 | C4: =SUMIFS(Empoissonnement!$C$4:$C$22,Empoissonnement!$B$4:$B$22,C$3) -> 4 | D4: =SUMIFS(Empoissonnement!$C$4:$C$22,Empoissonnement!$B$4:$B$22,D$3) -> 8 | E4: =SUMIFS(Empoissonnement!$C$4:$C$22,Empoissonnement!$B$4:$B$22,E$3) -> 8 | F4: =SUMIFS(Empoissonnement!$C$4:$C$22,Empoissonnement!$B$4:$B$22,F$3) -> 10 | G4: =SUMIFS(Empoissonnement!$C$4:$C$22,Empoissonnement!$B$4:$B$22,G$3) -> 12 | H4: =SUMIFS(Empoissonnement!$C$4:$C$22,Empoissonnement!$B$4:$B$22,H$3) -> 15 | I4: =SUMIFS(Empoissonnement!$C$4:$C$22,Empoissonnement!$B$4:$B$22,I$3) -> 15 | ... V4: =SUMIFS(Empoissonnement!$C$4:$C$22,Empoissonnement!$B$4:$B$22,V$3) -> 0 | W4: =SUM(B4:V4) -> 241
A5: Alevins à commander (nb) | B5: =SUMIFS(Empoissonnement!$E$4:$E$22,Empoissonnement!$B$4:$B$22,B$3) -> 11000 | C5: =SUMIFS(Empoissonnement!$E$4:$E$22,Empoissonnement!$B$4:$B$22,C$3) -> 11000 | D5: =SUMIFS(Empoissonnement!$E$4:$E$22,Empoissonnement!$B$4:$B$22,D$3) -> 22000 | E5: =SUMIFS(Empoissonnement!$E$4:$E$22,Empoissonnement!$B$4:$B$22,E$3) -> 22000 | F5: =SUMIFS(Empoissonnement!$E$4:$E$22,Empoissonnement!$B$4:$B$22,F$3) -> 27500 | G5: =SUMIFS(Empoissonnement!$E$4:$E$22,Empoissonnement!$B$4:$B$22,G$3) -> 33000 | H5: =SUMIFS(Empoissonnement!$E$4:$E$22,Empoissonnement!$B$4:$B$22,H$3) -> 41250 | I5: =SUMIFS(Empoissonnement!$E$4:$E$22,Empoissonnement!$B$4:$B$22,I$3) -> 41250 | ... V5: =SUMIFS(Empoissonnement!$E$4:$E$22,Empoissonnement!$B$4:$B$22,V$3) -> 0 | W5: =SUM(B5:V5) -> 662750
A6: Besoin en aliments (kg) | B6: ='Besoins aliments'!$H5 -> 600 | C6: ='Besoins aliments'!$H6 -> 2760 | D6: ='Besoins aliments'!$H7 -> 5160 | E6: ='Besoins aliments'!$H8 -> 7320 | F6: ='Besoins aliments'!$H9 -> 9420 | G6: ='Besoins aliments'!$H10 -> 10800 | H6: ='Besoins aliments'!$H11 -> 13230 | I6: ='Besoins aliments'!$H12 -> 15750 | J6: ='Besoins aliments'!$H13 -> 17100 | K6: ='Besoins aliments'!$H14 -> 17100 | L6: ='Besoins aliments'!$H15 -> 17100 | M6: ='Besoins aliments'!$H16 -> 17100 | N6: ='Besoins aliments'!$H17 -> 17100 | O6: ='Besoins aliments'!$H18 -> 17100 | P6: ='Besoins aliments'!$H19 -> 17100 | Q6: ='Besoins aliments'!$H20 -> 17100 | R6: ='Besoins aliments'!$H21 -> 17100 | S6: ='Besoins aliments'!$H22 -> 17100 | T6: ='Besoins aliments'!$H23 -> 17100 | U6: ='Besoins aliments'!$H24 -> 14850 | V6: ='Besoins aliments'!$H25 -> 6750 | W6: =SUM(B6:V6) -> 274740
A7: Sacs à acheter (total) | B7: =SUM('Besoins aliments'!$I5:$N5) -> 41 | C7: =SUM('Besoins aliments'!$I6:$N6) -> 184 | D7: =SUM('Besoins aliments'!$I7:$N7) -> 345 | E7: =SUM('Besoins aliments'!$I8:$N8) -> 488 | F7: =SUM('Besoins aliments'!$I9:$N9) -> 629 | G7: =SUM('Besoins aliments'!$I10:$N10) -> 721 | H7: =SUM('Besoins aliments'!$I11:$N11) -> 883 | I7: =SUM('Besoins aliments'!$I12:$N12) -> 1050 | J7: =SUM('Besoins aliments'!$I13:$N13) -> 1140 | K7: =SUM('Besoins aliments'!$I14:$N14) -> 1140 | L7: =SUM('Besoins aliments'!$I15:$N15) -> 1140 | M7: =SUM('Besoins aliments'!$I16:$N16) -> 1140 | N7: =SUM('Besoins aliments'!$I17:$N17) -> 1140 | O7: =SUM('Besoins aliments'!$I18:$N18) -> 1140 | P7: =SUM('Besoins aliments'!$I19:$N19) -> 1140 | Q7: =SUM('Besoins aliments'!$I20:$N20) -> 1140 | R7: =SUM('Besoins aliments'!$I21:$N21) -> 1140 | S7: =SUM('Besoins aliments'!$I22:$N22) -> 1140 | T7: =SUM('Besoins aliments'!$I23:$N23) -> 1140 | U7: =SUM('Besoins aliments'!$I24:$N24) -> 990 | V7: =SUM('Besoins aliments'!$I25:$N25) -> 450 | W7: =SUM(B7:V7) -> 18321
A8: =" dont sacs "&Aliments!$A$4 -> dont sacs 2 mm | B8: ='Besoins aliments'!$I5 -> 26 | C8: ='Besoins aliments'!$I6 -> 32 | D8: ='Besoins aliments'!$I7 -> 58 | E8: ='Besoins aliments'!$I8 -> 64 | F8: ='Besoins aliments'!$I9 -> 77 | G8: ='Besoins aliments'!$I10 -> 93 | H8: ='Besoins aliments'!$I11 -> 116 | I8: ='Besoins aliments'!$I12 -> 120 | J8: ='Besoins aliments'!$I13 -> 120 | K8: ='Besoins aliments'!$I14 -> 120 | L8: ='Besoins aliments'!$I15 -> 120 | M8: ='Besoins aliments'!$I16 -> 120 | N8: ='Besoins aliments'!$I17 -> 120 | O8: ='Besoins aliments'!$I18 -> 120 | P8: ='Besoins aliments'!$I19 -> 120 | Q8: ='Besoins aliments'!$I20 -> 120 | R8: ='Besoins aliments'!$I21 -> 120 | S8: ='Besoins aliments'!$I22 -> 120 | T8: ='Besoins aliments'!$I23 -> 120 | U8: ='Besoins aliments'!$I24 -> 24 | V8: ='Besoins aliments'!$I25 -> 0 | W8: =SUM(B8:V8) -> 1930
A9: =" dont sacs "&Aliments!$A$5 -> dont sacs 3 mm | B9: ='Besoins aliments'!$J5 -> 15 | C9: ='Besoins aliments'!$J6 -> 72 | D9: ='Besoins aliments'!$J7 -> 87 | E9: ='Besoins aliments'!$J8 -> 144 | F9: ='Besoins aliments'!$J9 -> 152 | G9: ='Besoins aliments'!$J10 -> 188 | H9: ='Besoins aliments'!$J11 -> 227 | I9: ='Besoins aliments'!$J12 -> 270 | J9: ='Besoins aliments'!$J13 -> 270 | K9: ='Besoins aliments'!$J14 -> 270 | L9: ='Besoins aliments'!$J15 -> 270 | M9: ='Besoins aliments'!$J16 -> 270 | N9: ='Besoins aliments'!$J17 -> 270 | O9: ='Besoins aliments'!$J18 -> 270 | P9: ='Besoins aliments'!$J19 -> 270 | Q9: ='Besoins aliments'!$J20 -> 270 | R9: ='Besoins aliments'!$J21 -> 270 | S9: ='Besoins aliments'!$J22 -> 270 | T9: ='Besoins aliments'!$J23 -> 270 | U9: ='Besoins aliments'!$J24 -> 216 | V9: ='Besoins aliments'!$J25 -> 0 | W9: =SUM(B9:V9) -> 4341
A10: =" dont sacs "&Aliments!$A$6 -> dont sacs 4 mm | B10: ='Besoins aliments'!$K5 -> 0 | C10: ='Besoins aliments'!$K6 -> 80 | D10: ='Besoins aliments'!$K7 -> 200 | E10: ='Besoins aliments'!$K8 -> 280 | F10: ='Besoins aliments'!$K9 -> 400 | G10: ='Besoins aliments'!$K10 -> 440 | H10: ='Besoins aliments'!$K11 -> 540 | I10: ='Besoins aliments'!$K12 -> 660 | J10: ='Besoins aliments'!$K13 -> 750 | K10: ='Besoins aliments'!$K14 -> 750 | L10: ='Besoins aliments'!$K15 -> 750 | M10: ='Besoins aliments'!$K16 -> 750 | N10: ='Besoins aliments'!$K17 -> 750 | O10: ='Besoins aliments'!$K18 -> 750 | P10: ='Besoins aliments'!$K19 -> 750 | Q10: ='Besoins aliments'!$K20 -> 750 | R10: ='Besoins aliments'!$K21 -> 750 | S10: ='Besoins aliments'!$K22 -> 750 | T10: ='Besoins aliments'!$K23 -> 750 | U10: ='Besoins aliments'!$K24 -> 750 | V10: ='Besoins aliments'!$K25 -> 450 | W10: =SUM(B10:V10) -> 12050
A11: DÉTAIL PAR VAGUE — sacs consommés dans le mois (indicatif)
A12: Vague en 1er mois de cycle | B12: =IFERROR(INDEX(Empoissonnement!$A$4:$A$22,MATCH(B$3,Empoissonnement!$B$4:$B$22,0)),"—") -> V1 | C12: =IFERROR(INDEX(Empoissonnement!$A$4:$A$22,MATCH(C$3,Empoissonnement!$B$4:$B$22,0)),"—") -> V2 | D12: =IFERROR(INDEX(Empoissonnement!$A$4:$A$22,MATCH(D$3,Empoissonnement!$B$4:$B$22,0)),"—") -> V3 | E12: =IFERROR(INDEX(Empoissonnement!$A$4:$A$22,MATCH(E$3,Empoissonnement!$B$4:$B$22,0)),"—") -> V4 | F12: =IFERROR(INDEX(Empoissonnement!$A$4:$A$22,MATCH(F$3,Empoissonnement!$B$4:$B$22,0)),"—") -> V5 | G12: =IFERROR(INDEX(Empoissonnement!$A$4:$A$22,MATCH(G$3,Empoissonnement!$B$4:$B$22,0)),"—") -> V6 | H12: =IFERROR(INDEX(Empoissonnement!$A$4:$A$22,MATCH(H$3,Empoissonnement!$B$4:$B$22,0)),"—") -> V7 | I12: =IFERROR(INDEX(Empoissonnement!$A$4:$A$22,MATCH(I$3,Empoissonnement!$B$4:$B$22,0)),"—") -> V8 | ... V12: =IFERROR(INDEX(Empoissonnement!$A$4:$A$22,MATCH(V$3,Empoissonnement!$B$4:$B$22,0)),"—") -> —
A13: =" dont sacs "&Aliments!$A$4 -> dont sacs 2 mm | B13: =ROUND(SUMIFS('Aliment par vague'!$D$4:$D$22,Empoissonnement!$B$4:$B$22,B$3)*N(Aliments!$F$4),0) -> 26 | C13: =ROUND(SUMIFS('Aliment par vague'!$D$4:$D$22,Empoissonnement!$B$4:$B$22,C$3)*N(Aliments!$F$4),0) -> 26 | D13: =ROUND(SUMIFS('Aliment par vague'!$D$4:$D$22,Empoissonnement!$B$4:$B$22,D$3)*N(Aliments!$F$4),0) -> 51 | E13: =ROUND(SUMIFS('Aliment par vague'!$D$4:$D$22,Empoissonnement!$B$4:$B$22,E$3)*N(Aliments!$F$4),0) -> 51 | F13: =ROUND(SUMIFS('Aliment par vague'!$D$4:$D$22,Empoissonnement!$B$4:$B$22,F$3)*N(Aliments!$F$4),0) -> 64 | G13: =ROUND(SUMIFS('Aliment par vague'!$D$4:$D$22,Empoissonnement!$B$4:$B$22,G$3)*N(Aliments!$F$4),0) -> 77 | H13: =ROUND(SUMIFS('Aliment par vague'!$D$4:$D$22,Empoissonnement!$B$4:$B$22,H$3)*N(Aliments!$F$4),0) -> 96 | I13: =ROUND(SUMIFS('Aliment par vague'!$D$4:$D$22,Empoissonnement!$B$4:$B$22,I$3)*N(Aliments!$F$4),0) -> 96 | ... V13: =ROUND(SUMIFS('Aliment par vague'!$D$4:$D$22,Empoissonnement!$B$4:$B$22,V$3)*N(Aliments!$F$4),0) -> 0 | W13: =SUM(B13:V13) -> 1543
A14: =" dont sacs "&Aliments!$A$5 -> dont sacs 3 mm | B14: =ROUND(SUMIFS('Aliment par vague'!$E$4:$E$22,Empoissonnement!$B$4:$B$22,B$3)*N(Aliments!$F$5),0) -> 14 | C14: =ROUND(SUMIFS('Aliment par vague'!$E$4:$E$22,Empoissonnement!$B$4:$B$22,C$3)*N(Aliments!$F$5),0) -> 14 | D14: =ROUND(SUMIFS('Aliment par vague'!$E$4:$E$22,Empoissonnement!$B$4:$B$22,D$3)*N(Aliments!$F$5),0) -> 29 | E14: =ROUND(SUMIFS('Aliment par vague'!$E$4:$E$22,Empoissonnement!$B$4:$B$22,E$3)*N(Aliments!$F$5),0) -> 29 | F14: =ROUND(SUMIFS('Aliment par vague'!$E$4:$E$22,Empoissonnement!$B$4:$B$22,F$3)*N(Aliments!$F$5),0) -> 36 | G14: =ROUND(SUMIFS('Aliment par vague'!$E$4:$E$22,Empoissonnement!$B$4:$B$22,G$3)*N(Aliments!$F$5),0) -> 43 | H14: =ROUND(SUMIFS('Aliment par vague'!$E$4:$E$22,Empoissonnement!$B$4:$B$22,H$3)*N(Aliments!$F$5),0) -> 54 | I14: =ROUND(SUMIFS('Aliment par vague'!$E$4:$E$22,Empoissonnement!$B$4:$B$22,I$3)*N(Aliments!$F$5),0) -> 54 | ... V14: =ROUND(SUMIFS('Aliment par vague'!$E$4:$E$22,Empoissonnement!$B$4:$B$22,V$3)*N(Aliments!$F$5),0) -> 0 | W14: =SUM(B14:V14) -> 867
A15: =" dont sacs "&Aliments!$A$6 -> dont sacs 4 mm | B15: =ROUND(SUMIFS('Aliment par vague'!$F$4:$F$22,Empoissonnement!$B$4:$B$22,B$3)*N(Aliments!$F$6),0) -> 0 | C15: =ROUND(SUMIFS('Aliment par vague'!$F$4:$F$22,Empoissonnement!$B$4:$B$22,C$3)*N(Aliments!$F$6),0) -> 0 | D15: =ROUND(SUMIFS('Aliment par vague'!$F$4:$F$22,Empoissonnement!$B$4:$B$22,D$3)*N(Aliments!$F$6),0) -> 0 | E15: =ROUND(SUMIFS('Aliment par vague'!$F$4:$F$22,Empoissonnement!$B$4:$B$22,E$3)*N(Aliments!$F$6),0) -> 0 | F15: =ROUND(SUMIFS('Aliment par vague'!$F$4:$F$22,Empoissonnement!$B$4:$B$22,F$3)*N(Aliments!$F$6),0) -> 0 | G15: =ROUND(SUMIFS('Aliment par vague'!$F$4:$F$22,Empoissonnement!$B$4:$B$22,G$3)*N(Aliments!$F$6),0) -> 0 | H15: =ROUND(SUMIFS('Aliment par vague'!$F$4:$F$22,Empoissonnement!$B$4:$B$22,H$3)*N(Aliments!$F$6),0) -> 0 | I15: =ROUND(SUMIFS('Aliment par vague'!$F$4:$F$22,Empoissonnement!$B$4:$B$22,I$3)*N(Aliments!$F$6),0) -> 0 | ... V15: =ROUND(SUMIFS('Aliment par vague'!$F$4:$F$22,Empoissonnement!$B$4:$B$22,V$3)*N(Aliments!$F$6),0) -> 0 | W15: =SUM(B15:V15) -> 0
A16: Vague en 2e mois de cycle | B16: =IFERROR(INDEX(Empoissonnement!$A$4:$A$22,MATCH(B$37,Empoissonnement!$B$4:$B$22,0)),"—") -> — | C16: =IFERROR(INDEX(Empoissonnement!$A$4:$A$22,MATCH(C$37,Empoissonnement!$B$4:$B$22,0)),"—") -> V1 | D16: =IFERROR(INDEX(Empoissonnement!$A$4:$A$22,MATCH(D$37,Empoissonnement!$B$4:$B$22,0)),"—") -> V2 | E16: =IFERROR(INDEX(Empoissonnement!$A$4:$A$22,MATCH(E$37,Empoissonnement!$B$4:$B$22,0)),"—") -> V3 | F16: =IFERROR(INDEX(Empoissonnement!$A$4:$A$22,MATCH(F$37,Empoissonnement!$B$4:$B$22,0)),"—") -> V4 | G16: =IFERROR(INDEX(Empoissonnement!$A$4:$A$22,MATCH(G$37,Empoissonnement!$B$4:$B$22,0)),"—") -> V5 | H16: =IFERROR(INDEX(Empoissonnement!$A$4:$A$22,MATCH(H$37,Empoissonnement!$B$4:$B$22,0)),"—") -> V6 | I16: =IFERROR(INDEX(Empoissonnement!$A$4:$A$22,MATCH(I$37,Empoissonnement!$B$4:$B$22,0)),"—") -> V7 | ... V16: =IFERROR(INDEX(Empoissonnement!$A$4:$A$22,MATCH(V$37,Empoissonnement!$B$4:$B$22,0)),"—") -> —
A17: =" dont sacs "&Aliments!$A$4 -> dont sacs 2 mm | B17: =ROUND(SUMIFS('Aliment par vague'!$D$4:$D$22,Empoissonnement!$B$4:$B$22,B$37)*N(Aliments!$G$4),0) -> 0 | C17: =ROUND(SUMIFS('Aliment par vague'!$D$4:$D$22,Empoissonnement!$B$4:$B$22,C$37)*N(Aliments!$G$4),0) -> 6 | D17: =ROUND(SUMIFS('Aliment par vague'!$D$4:$D$22,Empoissonnement!$B$4:$B$22,D$37)*N(Aliments!$G$4),0) -> 6 | E17: =ROUND(SUMIFS('Aliment par vague'!$D$4:$D$22,Empoissonnement!$B$4:$B$22,E$37)*N(Aliments!$G$4),0) -> 13 | F17: =ROUND(SUMIFS('Aliment par vague'!$D$4:$D$22,Empoissonnement!$B$4:$B$22,F$37)*N(Aliments!$G$4),0) -> 13 | G17: =ROUND(SUMIFS('Aliment par vague'!$D$4:$D$22,Empoissonnement!$B$4:$B$22,G$37)*N(Aliments!$G$4),0) -> 16 | H17: =ROUND(SUMIFS('Aliment par vague'!$D$4:$D$22,Empoissonnement!$B$4:$B$22,H$37)*N(Aliments!$G$4),0) -> 19 | I17: =ROUND(SUMIFS('Aliment par vague'!$D$4:$D$22,Empoissonnement!$B$4:$B$22,I$37)*N(Aliments!$G$4),0) -> 24 | ... V17: =ROUND(SUMIFS('Aliment par vague'!$D$4:$D$22,Empoissonnement!$B$4:$B$22,V$37)*N(Aliments!$G$4),0) -> 0 | W17: =SUM(B17:V17) -> 385
A18: =" dont sacs "&Aliments!$A$5 -> dont sacs 3 mm | B18: =ROUND(SUMIFS('Aliment par vague'!$E$4:$E$22,Empoissonnement!$B$4:$B$22,B$37)*N(Aliments!$G$5),0) -> 0 | C18: =ROUND(SUMIFS('Aliment par vague'!$E$4:$E$22,Empoissonnement!$B$4:$B$22,C$37)*N(Aliments!$G$5),0) -> 58 | D18: =ROUND(SUMIFS('Aliment par vague'!$E$4:$E$22,Empoissonnement!$B$4:$B$22,D$37)*N(Aliments!$G$5),0) -> 58 | E18: =ROUND(SUMIFS('Aliment par vague'!$E$4:$E$22,Empoissonnement!$B$4:$B$22,E$37)*N(Aliments!$G$5),0) -> 115 | F18: =ROUND(SUMIFS('Aliment par vague'!$E$4:$E$22,Empoissonnement!$B$4:$B$22,F$37)*N(Aliments!$G$5),0) -> 115 | G18: =ROUND(SUMIFS('Aliment par vague'!$E$4:$E$22,Empoissonnement!$B$4:$B$22,G$37)*N(Aliments!$G$5),0) -> 144 | H18: =ROUND(SUMIFS('Aliment par vague'!$E$4:$E$22,Empoissonnement!$B$4:$B$22,H$37)*N(Aliments!$G$5),0) -> 173 | I18: =ROUND(SUMIFS('Aliment par vague'!$E$4:$E$22,Empoissonnement!$B$4:$B$22,I$37)*N(Aliments!$G$5),0) -> 216 | ... V18: =ROUND(SUMIFS('Aliment par vague'!$E$4:$E$22,Empoissonnement!$B$4:$B$22,V$37)*N(Aliments!$G$5),0) -> 0 | W18: =SUM(B18:V18) -> 3471
A19: =" dont sacs "&Aliments!$A$6 -> dont sacs 4 mm | B19: =ROUND(SUMIFS('Aliment par vague'!$F$4:$F$22,Empoissonnement!$B$4:$B$22,B$37)*N(Aliments!$G$6),0) -> 0 | C19: =ROUND(SUMIFS('Aliment par vague'!$F$4:$F$22,Empoissonnement!$B$4:$B$22,C$37)*N(Aliments!$G$6),0) -> 80 | D19: =ROUND(SUMIFS('Aliment par vague'!$F$4:$F$22,Empoissonnement!$B$4:$B$22,D$37)*N(Aliments!$G$6),0) -> 80 | E19: =ROUND(SUMIFS('Aliment par vague'!$F$4:$F$22,Empoissonnement!$B$4:$B$22,E$37)*N(Aliments!$G$6),0) -> 160 | F19: =ROUND(SUMIFS('Aliment par vague'!$F$4:$F$22,Empoissonnement!$B$4:$B$22,F$37)*N(Aliments!$G$6),0) -> 160 | G19: =ROUND(SUMIFS('Aliment par vague'!$F$4:$F$22,Empoissonnement!$B$4:$B$22,G$37)*N(Aliments!$G$6),0) -> 200 | H19: =ROUND(SUMIFS('Aliment par vague'!$F$4:$F$22,Empoissonnement!$B$4:$B$22,H$37)*N(Aliments!$G$6),0) -> 240 | I19: =ROUND(SUMIFS('Aliment par vague'!$F$4:$F$22,Empoissonnement!$B$4:$B$22,I$37)*N(Aliments!$G$6),0) -> 300 | ... V19: =ROUND(SUMIFS('Aliment par vague'!$F$4:$F$22,Empoissonnement!$B$4:$B$22,V$37)*N(Aliments!$G$6),0) -> 0 | W19: =SUM(B19:V19) -> 4820
A20: Vague en 3e mois de cycle | B20: =IFERROR(INDEX(Empoissonnement!$A$4:$A$22,MATCH(B$38,Empoissonnement!$B$4:$B$22,0)),"—") -> — | C20: =IFERROR(INDEX(Empoissonnement!$A$4:$A$22,MATCH(C$38,Empoissonnement!$B$4:$B$22,0)),"—") -> — | D20: =IFERROR(INDEX(Empoissonnement!$A$4:$A$22,MATCH(D$38,Empoissonnement!$B$4:$B$22,0)),"—") -> V1 | E20: =IFERROR(INDEX(Empoissonnement!$A$4:$A$22,MATCH(E$38,Empoissonnement!$B$4:$B$22,0)),"—") -> V2 | F20: =IFERROR(INDEX(Empoissonnement!$A$4:$A$22,MATCH(F$38,Empoissonnement!$B$4:$B$22,0)),"—") -> V3 | G20: =IFERROR(INDEX(Empoissonnement!$A$4:$A$22,MATCH(G$38,Empoissonnement!$B$4:$B$22,0)),"—") -> V4 | H20: =IFERROR(INDEX(Empoissonnement!$A$4:$A$22,MATCH(H$38,Empoissonnement!$B$4:$B$22,0)),"—") -> V5 | I20: =IFERROR(INDEX(Empoissonnement!$A$4:$A$22,MATCH(I$38,Empoissonnement!$B$4:$B$22,0)),"—") -> V6 | ... V20: =IFERROR(INDEX(Empoissonnement!$A$4:$A$22,MATCH(V$38,Empoissonnement!$B$4:$B$22,0)),"—") -> V19
A21: =" dont sacs "&Aliments!$A$4 -> dont sacs 2 mm | B21: =ROUND(SUMIFS('Aliment par vague'!$D$4:$D$22,Empoissonnement!$B$4:$B$22,B$38)*N(Aliments!$H$4),0) -> 0 | C21: =ROUND(SUMIFS('Aliment par vague'!$D$4:$D$22,Empoissonnement!$B$4:$B$22,C$38)*N(Aliments!$H$4),0) -> 0 | D21: =ROUND(SUMIFS('Aliment par vague'!$D$4:$D$22,Empoissonnement!$B$4:$B$22,D$38)*N(Aliments!$H$4),0) -> 0 | E21: =ROUND(SUMIFS('Aliment par vague'!$D$4:$D$22,Empoissonnement!$B$4:$B$22,E$38)*N(Aliments!$H$4),0) -> 0 | F21: =ROUND(SUMIFS('Aliment par vague'!$D$4:$D$22,Empoissonnement!$B$4:$B$22,F$38)*N(Aliments!$H$4),0) -> 0 | G21: =ROUND(SUMIFS('Aliment par vague'!$D$4:$D$22,Empoissonnement!$B$4:$B$22,G$38)*N(Aliments!$H$4),0) -> 0 | H21: =ROUND(SUMIFS('Aliment par vague'!$D$4:$D$22,Empoissonnement!$B$4:$B$22,H$38)*N(Aliments!$H$4),0) -> 0 | I21: =ROUND(SUMIFS('Aliment par vague'!$D$4:$D$22,Empoissonnement!$B$4:$B$22,I$38)*N(Aliments!$H$4),0) -> 0 | ... V21: =ROUND(SUMIFS('Aliment par vague'!$D$4:$D$22,Empoissonnement!$B$4:$B$22,V$38)*N(Aliments!$H$4),0) -> 0 | W21: =SUM(B21:V21) -> 0
A22: =" dont sacs "&Aliments!$A$5 -> dont sacs 3 mm | B22: =ROUND(SUMIFS('Aliment par vague'!$E$4:$E$22,Empoissonnement!$B$4:$B$22,B$38)*N(Aliments!$H$5),0) -> 0 | C22: =ROUND(SUMIFS('Aliment par vague'!$E$4:$E$22,Empoissonnement!$B$4:$B$22,C$38)*N(Aliments!$H$5),0) -> 0 | D22: =ROUND(SUMIFS('Aliment par vague'!$E$4:$E$22,Empoissonnement!$B$4:$B$22,D$38)*N(Aliments!$H$5),0) -> 0 | E22: =ROUND(SUMIFS('Aliment par vague'!$E$4:$E$22,Empoissonnement!$B$4:$B$22,E$38)*N(Aliments!$H$5),0) -> 0 | F22: =ROUND(SUMIFS('Aliment par vague'!$E$4:$E$22,Empoissonnement!$B$4:$B$22,F$38)*N(Aliments!$H$5),0) -> 0 | G22: =ROUND(SUMIFS('Aliment par vague'!$E$4:$E$22,Empoissonnement!$B$4:$B$22,G$38)*N(Aliments!$H$5),0) -> 0 | H22: =ROUND(SUMIFS('Aliment par vague'!$E$4:$E$22,Empoissonnement!$B$4:$B$22,H$38)*N(Aliments!$H$5),0) -> 0 | I22: =ROUND(SUMIFS('Aliment par vague'!$E$4:$E$22,Empoissonnement!$B$4:$B$22,I$38)*N(Aliments!$H$5),0) -> 0 | ... V22: =ROUND(SUMIFS('Aliment par vague'!$E$4:$E$22,Empoissonnement!$B$4:$B$22,V$38)*N(Aliments!$H$5),0) -> 0 | W22: =SUM(B22:V22) -> 0
A23: =" dont sacs "&Aliments!$A$6 -> dont sacs 4 mm | B23: =ROUND(SUMIFS('Aliment par vague'!$F$4:$F$22,Empoissonnement!$B$4:$B$22,B$38)*N(Aliments!$H$6),0) -> 0 | C23: =ROUND(SUMIFS('Aliment par vague'!$F$4:$F$22,Empoissonnement!$B$4:$B$22,C$38)*N(Aliments!$H$6),0) -> 0 | D23: =ROUND(SUMIFS('Aliment par vague'!$F$4:$F$22,Empoissonnement!$B$4:$B$22,D$38)*N(Aliments!$H$6),0) -> 120 | E23: =ROUND(SUMIFS('Aliment par vague'!$F$4:$F$22,Empoissonnement!$B$4:$B$22,E$38)*N(Aliments!$H$6),0) -> 120 | F23: =ROUND(SUMIFS('Aliment par vague'!$F$4:$F$22,Empoissonnement!$B$4:$B$22,F$38)*N(Aliments!$H$6),0) -> 240 | G23: =ROUND(SUMIFS('Aliment par vague'!$F$4:$F$22,Empoissonnement!$B$4:$B$22,G$38)*N(Aliments!$H$6),0) -> 240 | H23: =ROUND(SUMIFS('Aliment par vague'!$F$4:$F$22,Empoissonnement!$B$4:$B$22,H$38)*N(Aliments!$H$6),0) -> 300 | I23: =ROUND(SUMIFS('Aliment par vague'!$F$4:$F$22,Empoissonnement!$B$4:$B$22,I$38)*N(Aliments!$H$6),0) -> 360 | ... V23: =ROUND(SUMIFS('Aliment par vague'!$F$4:$F$22,Empoissonnement!$B$4:$B$22,V$38)*N(Aliments!$H$6),0) -> 450 | W23: =SUM(B23:V23) -> 7230
A24: Ventes (t) | B24: =SUMIFS(Empoissonnement!$C$4:$C$22,Empoissonnement!$B$4:$B$22,B$37)*Paramètres!$B$7+SUMIFS(Empoissonnement!$C$4:$C$22,Empoissonnement!$B$4:$B$22,B$38)*Paramètres!$B$8 -> 0 | C24: =SUMIFS(Empoissonnement!$C$4:$C$22,Empoissonnement!$B$4:$B$22,C$37)*Paramètres!$B$7+SUMIFS(Empoissonnement!$C$4:$C$22,Empoissonnement!$B$4:$B$22,C$38)*Paramètres!$B$8 -> 0 | D24: =SUMIFS(Empoissonnement!$C$4:$C$22,Empoissonnement!$B$4:$B$22,D$37)*Paramètres!$B$7+SUMIFS(Empoissonnement!$C$4:$C$22,Empoissonnement!$B$4:$B$22,D$38)*Paramètres!$B$8 -> 4 | E24: =SUMIFS(Empoissonnement!$C$4:$C$22,Empoissonnement!$B$4:$B$22,E$37)*Paramètres!$B$7+SUMIFS(Empoissonnement!$C$4:$C$22,Empoissonnement!$B$4:$B$22,E$38)*Paramètres!$B$8 -> 4 | F24: =SUMIFS(Empoissonnement!$C$4:$C$22,Empoissonnement!$B$4:$B$22,F$37)*Paramètres!$B$7+SUMIFS(Empoissonnement!$C$4:$C$22,Empoissonnement!$B$4:$B$22,F$38)*Paramètres!$B$8 -> 8 | G24: =SUMIFS(Empoissonnement!$C$4:$C$22,Empoissonnement!$B$4:$B$22,G$37)*Paramètres!$B$7+SUMIFS(Empoissonnement!$C$4:$C$22,Empoissonnement!$B$4:$B$22,G$38)*Paramètres!$B$8 -> 8 | H24: =SUMIFS(Empoissonnement!$C$4:$C$22,Empoissonnement!$B$4:$B$22,H$37)*Paramètres!$B$7+SUMIFS(Empoissonnement!$C$4:$C$22,Empoissonnement!$B$4:$B$22,H$38)*Paramètres!$B$8 -> 10 | I24: =SUMIFS(Empoissonnement!$C$4:$C$22,Empoissonnement!$B$4:$B$22,I$37)*Paramètres!$B$7+SUMIFS(Empoissonnement!$C$4:$C$22,Empoissonnement!$B$4:$B$22,I$38)*Paramètres!$B$8 -> 12 | ... V24: =SUMIFS(Empoissonnement!$C$4:$C$22,Empoissonnement!$B$4:$B$22,V$37)*Paramètres!$B$7+SUMIFS(Empoissonnement!$C$4:$C$22,Empoissonnement!$B$4:$B$22,V$38)*Paramètres!$B$8 -> 15 | W24: =SUM(B24:V24) -> 241
A25: Entrées — chiffre d'affaires (FCFA) | B25: =B24*1000*Paramètres!$B$5 -> 0 | C25: =C24*1000*Paramètres!$B$5 -> 0 | D25: =D24*1000*Paramètres!$B$5 -> 7600000 | E25: =E24*1000*Paramètres!$B$5 -> 7600000 | F25: =F24*1000*Paramètres!$B$5 -> 15200000 | G25: =G24*1000*Paramètres!$B$5 -> 15200000 | H25: =H24*1000*Paramètres!$B$5 -> 19000000 | I25: =I24*1000*Paramètres!$B$5 -> 22800000 | ... V25: =V24*1000*Paramètres!$B$5 -> 28500000 | W25: =SUM(B25:V25) -> 457900000
A26: Apport en capital (FCFA) — à saisir | B26: 4000000 | C26: 6000000 | D26: 4000000 | E26: 0 | F26: 4000000 | G26: 10000000 | H26: 2000000 | I26: 0 | J26: 0 | K26: 0 | L26: 0 | M26: 0 | N26: 0 | O26: 0 | P26: 0 | Q26: 0 | R26: 0 | S26: 0 | T26: 0 | U26: 0 | V26: 0 | W26: =SUM(B26:V26) -> 30000000
A27: Total des entrées (FCFA) | B27: =B25+B26 -> 4000000 | C27: =C25+C26 -> 6000000 | D27: =D25+D26 -> 11600000 | E27: =E25+E26 -> 7600000 | F27: =F25+F26 -> 19200000 | G27: =G25+G26 -> 25200000 | H27: =H25+H26 -> 21000000 | I27: =I25+I26 -> 22800000 | ... V27: =V25+V26 -> 28500000 | W27: =SUM(B27:V27) -> 487900000
A28: Dépense aliments (FCFA) | B28: =SUMIFS('Aliment par vague'!$N$4:$N$22,Empoissonnement!$B$4:$B$22,B$3)+SUMIFS('Aliment par vague'!$O$4:$O$22,Empoissonnement!$B$4:$B$22,B$37)+SUMIFS('Aliment par vague'!$P$4:$P$22,Empoissonnement!$B$4:$B$22,B$38) -> 698400 | C28: =SUMIFS('Aliment par vague'!$N$4:$N$22,Empoissonnement!$B$4:$B$22,C$3)+SUMIFS('Aliment par vague'!$O$4:$O$22,Empoissonnement!$B$4:$B$22,C$37)+SUMIFS('Aliment par vague'!$P$4:$P$22,Empoissonnement!$B$4:$B$22,C$38) -> 3004000 | D28: =SUMIFS('Aliment par vague'!$N$4:$N$22,Empoissonnement!$B$4:$B$22,D$3)+SUMIFS('Aliment par vague'!$O$4:$O$22,Empoissonnement!$B$4:$B$22,D$37)+SUMIFS('Aliment par vague'!$P$4:$P$22,Empoissonnement!$B$4:$B$22,D$38) -> 5534464 | E28: =SUMIFS('Aliment par vague'!$N$4:$N$22,Empoissonnement!$B$4:$B$22,E$3)+SUMIFS('Aliment par vague'!$O$4:$O$22,Empoissonnement!$B$4:$B$22,E$37)+SUMIFS('Aliment par vague'!$P$4:$P$22,Empoissonnement!$B$4:$B$22,E$38) -> 7747840 | F28: =SUMIFS('Aliment par vague'!$N$4:$N$22,Empoissonnement!$B$4:$B$22,F$3)+SUMIFS('Aliment par vague'!$O$4:$O$22,Empoissonnement!$B$4:$B$22,F$37)+SUMIFS('Aliment par vague'!$P$4:$P$22,Empoissonnement!$B$4:$B$22,F$38) -> 9840736 | G28: =SUMIFS('Aliment par vague'!$N$4:$N$22,Empoissonnement!$B$4:$B$22,G$3)+SUMIFS('Aliment par vague'!$O$4:$O$22,Empoissonnement!$B$4:$B$22,G$37)+SUMIFS('Aliment par vague'!$P$4:$P$22,Empoissonnement!$B$4:$B$22,G$38) -> 11190432 | H28: =SUMIFS('Aliment par vague'!$N$4:$N$22,Empoissonnement!$B$4:$B$22,H$3)+SUMIFS('Aliment par vague'!$O$4:$O$22,Empoissonnement!$B$4:$B$22,H$37)+SUMIFS('Aliment par vague'!$P$4:$P$22,Empoissonnement!$B$4:$B$22,H$38) -> 13565988 | I28: =SUMIFS('Aliment par vague'!$N$4:$N$22,Empoissonnement!$B$4:$B$22,I$3)+SUMIFS('Aliment par vague'!$O$4:$O$22,Empoissonnement!$B$4:$B$22,I$37)+SUMIFS('Aliment par vague'!$P$4:$P$22,Empoissonnement!$B$4:$B$22,I$38) -> 15945900 | ... V28: =SUMIFS('Aliment par vague'!$N$4:$N$22,Empoissonnement!$B$4:$B$22,V$3)+SUMIFS('Aliment par vague'!$O$4:$O$22,Empoissonnement!$B$4:$B$22,V$37)+SUMIFS('Aliment par vague'!$P$4:$P$22,Empoissonnement!$B$4:$B$22,V$38) -> 6556500 | W28: =SUM(B28:V28) -> 277369600
A29: Dépense alevins (FCFA) | B29: =SUMIFS(Empoissonnement!$H$4:$H$22,Empoissonnement!$B$4:$B$22,B$3) -> 0 | C29: =SUMIFS(Empoissonnement!$H$4:$H$22,Empoissonnement!$B$4:$B$22,C$3) -> 0 | D29: =SUMIFS(Empoissonnement!$H$4:$H$22,Empoissonnement!$B$4:$B$22,D$3) -> 0 | E29: =SUMIFS(Empoissonnement!$H$4:$H$22,Empoissonnement!$B$4:$B$22,E$3) -> 0 | F29: =SUMIFS(Empoissonnement!$H$4:$H$22,Empoissonnement!$B$4:$B$22,F$3) -> 0 | G29: =SUMIFS(Empoissonnement!$H$4:$H$22,Empoissonnement!$B$4:$B$22,G$3) -> 0 | H29: =SUMIFS(Empoissonnement!$H$4:$H$22,Empoissonnement!$B$4:$B$22,H$3) -> 0 | I29: =SUMIFS(Empoissonnement!$H$4:$H$22,Empoissonnement!$B$4:$B$22,I$3) -> 0 | ... V29: =SUMIFS(Empoissonnement!$H$4:$H$22,Empoissonnement!$B$4:$B$22,V$3) -> 0 | W29: =SUM(B29:V29) -> 0
A30: Autres dépenses (FCFA) — feuille Dépenses | B30: =Dépenses!B34 -> 995000 | C30: =Dépenses!C34 -> 1070000 | D30: =Dépenses!D34 -> 1205000 | E30: =Dépenses!E34 -> 1250000 | F30: =Dépenses!F34 -> 1355000 | G30: =Dépenses!G34 -> 6385000 | H30: =Dépenses!H34 -> 6470000 | I30: =Dépenses!I34 -> 1540000 | ... V30: =Dépenses!V34 -> 1350000 | W30: =SUM(B30:V30) -> 65160000
A31: dont investissements (hors coût de production) | B31: =Dépenses!B33 -> 0 | C31: =Dépenses!C33 -> 0 | D31: =Dépenses!D33 -> 0 | E31: =Dépenses!E33 -> 0 | F31: =Dépenses!F33 -> 0 | G31: =Dépenses!G33 -> 5000000 | H31: =Dépenses!H33 -> 5000000 | I31: =Dépenses!I33 -> 0 | ... V31: =Dépenses!V33 -> 0 | W31: =SUM(B31:V31) -> 34400000
A32: Dépenses totales (FCFA) | B32: =B28+B29+B30 -> 1693400 | C32: =C28+C29+C30 -> 4074000 | D32: =D28+D29+D30 -> 6739464 | E32: =E28+E29+E30 -> 8997840 | F32: =F28+F29+F30 -> 11195736 | G32: =G28+G29+G30 -> 17575432 | H32: =H28+H29+H30 -> 20035988 | I32: =I28+I29+I30 -> 17485900 | ... V32: =V28+V29+V30 -> 7906500 | W32: =SUM(B32:V32) -> 342529600
A33: Résultat du mois (FCFA) | B33: =B27-B32 -> 2306600 | C33: =C27-C32 -> 1926000 | D33: =D27-D32 -> 4860536 | E33: =E27-E32 -> -1397840 | F33: =F27-F32 -> 8004264 | G33: =G27-G32 -> 7624568 | H33: =H27-H32 -> 964012 | I33: =I27-I32 -> 5314100 | ... V33: =V27-V32 -> 20593500 | W33: =SUM(B33:V33) -> 145370400
A34: Épargne conseillée (FCFA) | B34: =MAX(0,B33)*Paramètres!$B$36 -> 691980 | C34: =MAX(0,C33)*Paramètres!$B$36 -> 577800 | D34: =MAX(0,D33)*Paramètres!$B$36 -> 1458160.8 | E34: =MAX(0,E33)*Paramètres!$B$36 -> 0 | F34: =MAX(0,F33)*Paramètres!$B$36 -> 2401279.2 | G34: =MAX(0,G33)*Paramètres!$B$36 -> 2287370.4 | H34: =MAX(0,H33)*Paramètres!$B$36 -> 289203.6 | I34: =MAX(0,I33)*Paramètres!$B$36 -> 1594230 | ... V34: =MAX(0,V33)*Paramètres!$B$36 -> 6178050 | W34: =SUM(B34:V34) -> 46025652
A35: Trésorerie cumulée (FCFA) | B35: =Paramètres!$B$37+B33 -> 2306600 | C35: =B35+C33 -> 4232600 | D35: =C35+D33 -> 9093136 | E35: =D35+E33 -> 7695296 | F35: =E35+F33 -> 15699560 | G35: =F35+G33 -> 23324128 | H35: =G35+H33 -> 24288140 | I35: =H35+I33 -> 29602240 | J35: =I35+J33 -> 35351640 | ... V35: =U35+V33 -> 145370400 | W35: =V35 -> 145370400
A37: aide : mois -1 | B37: =EDATE(B$3,-1) -> 46204 | C37: =EDATE(C$3,-1) -> 46235 | D37: =EDATE(D$3,-1) -> 46266 | E37: =EDATE(E$3,-1) -> 46296 | F37: =EDATE(F$3,-1) -> 46327 | G37: =EDATE(G$3,-1) -> 46357 | H37: =EDATE(H$3,-1) -> 46388 | I37: =EDATE(I$3,-1) -> 46419 | ... V37: =EDATE(V$3,-1) -> 46813
A38: aide : mois -2 | B38: =EDATE(B$3,-2) -> 46174 | C38: =EDATE(C$3,-2) -> 46204 | D38: =EDATE(D$3,-2) -> 46235 | E38: =EDATE(E$3,-2) -> 46266 | F38: =EDATE(F$3,-2) -> 46296 | G38: =EDATE(G$3,-2) -> 46327 | H38: =EDATE(H$3,-2) -> 46357 | I38: =EDATE(I$3,-2) -> 46388 | ... V38: =EDATE(V$3,-2) -> 46784

Sheet Synthèse
A1: SYNTHÈSE — août 2026 à avril 2028
A3: Tonnage total vendu (t) | B3: =Prévisions!W24 -> 241
A4: Entrées totales — chiffre d'affaires (FCFA) | B4: =Prévisions!W25 -> 457900000
A5: Apports en capital (FCFA) | B5: =Prévisions!W26 -> 30000000
A6: Dépenses totales (FCFA) | B6: =Prévisions!W32 -> 342529600
A7: dont aliments (FCFA) | B7: =Prévisions!W28 -> 277369600
A8: dont alevins (FCFA) | B8: =Prévisions!W29 -> 0
A9: dont autres dépenses (FCFA) | B9: =Prévisions!W30 -> 65160000
A10: dont logistique (FCFA) | B10: =Dépenses!W11 -> 10180000
A11: dont charges d'exploitation (FCFA) | B11: =Dépenses!W22+Dépenses!W25+Dépenses!W26 -> 20580000
A12: dont investissements et exceptionnels — hors CP (FCFA) | B12: =Dépenses!W33 -> 34400000
A13: Résultat cumulé (FCFA) | B13: =Prévisions!W33 -> 145370400
A14: Épargne potentielle cumulée (FCFA) | B14: =Prévisions!W34 -> 46025652
A15: Trésorerie finale (FCFA) | B15: =Prévisions!V35 -> 145370400
A16: Point le plus bas de la trésorerie (FCFA) | B16: =MIN(Prévisions!B35:V35) -> 2306600 | C16: Si négatif : montant de financement à prévoir pendant la montée en charge.
A17: Alevins à commander sur la période (nb) | B17: =Prévisions!W5 -> 662750
A18: Besoin mensuel maximal en aliments (kg) | B18: =MAX(Prévisions!B6:V6) -> 17100
A19: Coût de production complet (FCFA / kg vendu, hors investissements) | B19: =IF(Prévisions!W24=0,0,(Prévisions!W32-Dépenses!W33)/(Prévisions!W24*1000)) -> 1278.5461 | C19: Le coût moyen inclut les « Autres dépenses » que vous saisissez dans les Prévisions.
A20: Marge nette moyenne (FCFA / kg vendu) | B20: =Paramètres!B5-B19 -> 621.45394
